Workbook

Sheet Resumen P.P.
C3: MILLHOUSE MEXICO
C4: CÁLCULO DE PAGOS PROVISIONALES MENSUALES
C5: IMPUESTO SOBRE LA RENTA (personas morales)
C6: 2025
A8: OP'N. | B8: CONCEPTO | C8: ENERO | D8: ENERO | E8: FEBRERO | F8: MARZO | G8: ABRIL | H8: MAYO | I8: JUNIO | J8: JULIO | K8: AGOSTO | L8: SEPTIEMBRE | M8: OCTUBRE | N8: NOVIEMBRE | O8: DICIEMBRE | P8: ANUAL
A10: DETERMINACIÓN DE LOS INGRESOS
A11: ( = ) | B11: Ventas | C11: ='FACTURAS INGRESOS'!P297 -> 25551509 | D11: =C11 -> 25551509 | E11: ='FACTURAS INGRESOS'!P480 -> 8179265.4 | F11: =ING.MIADMIN!AD241 -> 9532314.5 | G11: HOJA "ING.MIADMIN" | P11: =SUM(D11:O11) -> 43263089
A12: ( - ) | B12: Dev.Reb. Y Desc. Sobre vtas | P12: =SUM(C12:O12) -> 0
A13: ( + ) | B13: Anticipos de Clientes | E13: ='BAL2'!G622 -> 5000 | F13: ='BAL3'!G649 -> 16960 | G13: HOJA "ANT. DE CLIENTES" | P13: =SUM(D13:O13) -> 21960
A14: ( - ) | B14: Cancelacion Anticipos Clientes | P14: =SUM(D14:O14) -> 0
A15: ( + ) | B15: Otros Ingresos | E15: ='BAL01'!G635+'BAL2'!G687 -> 203006.37 | F15: ='BAL3'!G716 -> 0.32 | P15: =SUM(D15:O15) -> 203006.69
A16: ( + ) | B16: Ingreso Venta Activo Fijo | P16: =SUM(D16:O16) -> 0
A17: ( + ) | B17: Intereses a Favor | P17: =SUM(D17:O17) -> 0
A18: ( + ) | B18: Utilidad Cambiaria | C18: ='BAL01'!G682 -> 249688.79 | D18: 552957.23 | E18: ='BAL2'!G782 -> 627113.61 | F18: ='BAL3'!G786 -> 294636.77 | G18: HOJA "UTILIDAD CAMB" | P18: =SUM(D18:O18) -> 1474707.6
A19: ( + ) | B19: Otros Financieros | P19: =SUM(D19:O19) -> 0
A20: ( Ʃ ) | B20: INGRESOS NOMINALES DEL MES | C20: =+C11-C12+C13-C14+C15+C16+C17+C18+C19 -> 25801198 | D20: =+D11-D12+D13-D14+D15+D16+D17+D18+D19 -> 26104466 | E20: =+E11-E12+E13-E14+E15+E16+E17+E18+E19 -> 9014385.4 | F20: =+F11-F12+F13-F14+F15+F16+F17+F18+F19 -> 9843911.6 | G20: =+G11-G12+G13-G14+G15+G16+G17+G18+G19 -> #VALUE! | H20: =+H11-H12+H13-H14+H15+H16+H17+H18+H19 -> 0 | I20: =+I11-I12+I13-I14+I15+I16+I17++I19 -> 0 | J20: =+J11-J12+J13-J14+J15+J16+J17+J18+J19 -> 0 | K20: =+K11-K12+K13-K14+K15+K16+K17+K18+K19 -> 0 | L20: =+L11-L12+L13-L14+L15+L16+L17+L18+L19 -> 0 | M20: =+M11-M12+M13-M14+M15+M16+M17+M18+M19 -> 0 | N20: =+N11-N12+N13-N14+N15+N16+N17+N18+N19 -> 0 | O20: =+O11-O12+O13-O14+O15+O16+O17+O18+O19 -> 0 | P20: =+P11-P12+P13-P14+P15+P16+P17+P18+P19 -> 44962763
A21: ( = ) | B21: INGRESOS ACUMULADOS | C21: =+C20 -> 25801198 | D21: =+D20 -> 26104466 | E21: =+D21+E20 -> 35118852 | F21: =+E21+F20 -> 44962763 | G21: =+F21+G20 -> #VALUE! | H21: =+G21+H20 -> #VALUE! | I21: =+H21+I20 -> #VALUE! | J21: =+I21+J20 -> #VALUE! | K21: =+J21+K20 -> #VALUE! | L21: =+K21+L20 -> #VALUE! | ... O21: =+N21+O20 -> #VALUE! | P21: =+P20 -> 44962763
A24: DETERMINACIÓN DE LA UTILIDAD FISCAL
A25: ( * ) | B25: COEFICIENTE DE UTILIDAD | C25: 0.0715 | D25: 0.0715 | E25: =+C25 -> 0.0715 | F25: 0.3349 | G25: =+F25 -> 0.3349 | H25: =+G25 -> 0.3349 | I25: =+H25 -> 0.3349 | J25: =+I25 -> 0.3349 | K25: =+J25 -> 0.3349 | L25: =+K25 -> 0.3349 | M25: =+L25 -> 0.3349 | N25: =+M25 -> 0.3349 | O25: =+N25 -> 0.3349
A26: ( = ) | B26: UTILIDAD FISCAL | C26: =+C21*C25 -> 1844785.6 | D26: =+D21*D25 -> 1866469.3 | E26: =+E21*E25 -> 2510997.9 | F26: =+F21*F25 -> 15058029 | G26: =+G21*G25-1 -> #VALUE! | H26: =+H21*H25-1 -> #VALUE! | I26: =+I21*I25 -> #VALUE! | J26: =+J21*J25 -> #VALUE! | K26: =+K21*K25 -> #VALUE! | L26: =+L21*L25 -> #VALUE! | M26: =+M21*M25 -> #VALUE! | N26: =+N21*N25 -> #VALUE! | O26: =+O21*O25 -> #VALUE! | P26: =+P21*P25 -> 0
O27: 0
A29: DETERMINACIÓN DEL RESULTADO FISCAL
A30: ( + ) | B30: INVENTARIO ACUMULABLE | C30: 0 | E30: 0 | F30: 0 | G30: 0 | H30: 0 | I30: 0 | J30: 0 | K30: 0 | L30: 0 | M30: 0 | N30: 0 | O30: 0 | P30: =SUM(C30:O30) -> 0
A31: ( - ) | B31: PERDIDAS FISCALES ANTERIORES | C31: 0 | E31: 0 | F31: 0 | G31: =+F3 -> 0 | H31: =+G31 -> 0 | I31: =+H31 -> 0 | J31: =+I31 -> 0 | K31: =+J31 -> 0 | L31: =+K31 -> 0 | M31: =+L31 -> 0 | N31: =+M31 -> 0 | O31: =+N31 -> 0 | P31: 0
A32: ( - ) | B32: PTU PAGADA | C32: 0 | E32: 0 | F32: 0 | G32: 0 | I32: 0 | J32: =+I32 -> 0 | K32: =+J32 -> 0 | L32: =+K32 -> 0 | M32: =+L32 -> 0 | N32: =+M32 -> 0 | O32: =+N32 -> 0 | P32: 0
A33: ( = ) | B33: RESULTADO FISCAL | C33: =+C26+C30-C31-C32 -> 1844785.6 | D33: =D26 -> 1866469.3 | E33: =+E26+E30-E31-E32 -> 2510997.9 | F33: =+F26+F30-F31-F32 -> 15058029 | G33: =+G26+G30-G31-G32 -> #VALUE! | H33: =+H26+H30-H31-H32 -> #VALUE! | I33: =+I26+I30-I31-I32 -> #VALUE! | J33: =+J26+J30-J31-J32 -> #VALUE! | K33: =+K26+K30-K31-K32 -> #VALUE! | L33: =+L26+L30-L31-L32 -> #VALUE! | ... P33: =+P26+P30-P31-P32 -> 0
A36: DETERMINACIÓN DE IMPUESTO
A37: ( * ) | B37: TASA | C37: 0.3 | D37: 0.3 | E37: 0.3 | F37: 0.3 | G37: 0.3 | H37: 0.3 | I37: 0.3 | J37: 0.3 | K37: 0.3 | L37: 0.3 | M37: 30 | N37: 0.3 | O37: 0.3 | P37: 0.3
A38: ( = ) | B38: ISR CAUSADO | C38: =+C33*C37 -> 553435.69 | D38: =+D33*D37 -> 559940.8 | E38: =+E33*E37 -> 753299.37 | F38: =+F33*F37 -> 4517408.8 | G38: =+G33*G37 -> #VALUE! | H38: =+H33*H37 -> #VALUE! | I38: =+I33*I37 -> #VALUE! | J38: =+J33*J37 -> #VALUE! | ... L38: =+L33*L37 -> #VALUE! | M38: =M33*M37% -> #VALUE! | N38: =+N33*N37 -> #VALUE! | O38: =+O33*O37 -> #VALUE! | P38: =+P33*P37 -> 0
A39: ( - ) | B39: PAGOS PROV. EFECTUADOS C/ANTERIORIDAD | C39: 0 | D39: =C38 -> 553435.69 | E39: =+C38 -> 553435.69 | F39: =+E38 -> 753299.37 | G39: =+F39 -> 753299.37 | H39: =+G39 -> 753299.37 | I39: =+H39 -> 753299.37 | J39: =+I39 -> 753299.37 | K39: =+J39 -> 753299.37 | L39: =+K39 -> 753299.37 | M39: =+L39 -> 753299.37 | N39: =+M39 -> 753299.37 | O39: =+N39 -> 753299.37 | P39: 0
A40: ( - ) | B40: RETENCIONES DE ISR BANCARIAS | F40: 1818590
A41: ( = ) | B41: IMPUESTO A CARGO | C41: =+C38-C39-C40 -> 553435.69 | D41: =+D38-D39-D40 -> 6505.108 | E41: =+E38-E39-E40 -> 199863.67 | F41: =+F38-F39-F40 -> 1945519.5 | G41: =+G38-G39-G40 -> #VALUE! | H41: =+H38-H39-H40 -> #VALUE! | I41: =+I38-I39-I40 -> #VALUE! | J41: =+J38-J39-J40 -> #VALUE! | ... P41: =+P38-P39-P40 -> 0
A44: COMPARATIVO vs DECLARACIÓN PRESENTADA
A45: ( vs ) | B45: ISR ENTERADO EN PAGOS PROVISIONALES
A46: ( = ) | B46: DIFERENCIA A CARGO (A FAVOR) | C46: =+C41-C45 -> 553435.69 | E46: =+E41-E45 -> 199863.67 | F46: =+F41-F45 -> 1945519.5 | G46: =+G41-G45 -> #VALUE! | H46: =+H41-H45 -> #VALUE! | I46: =+I41-I45 -> #VALUE! | J46: =+J41-J45 -> #VALUE! | K46: =+K41-K45 -> #VALUE! | L46: =+L41-L45 -> #VALUE! | ... O46: =+O41-O45 -> #VALUE! | P46: =P41-P45 -> 0
A51: DETERMINACIÓN DE IVA
B54: CONCEPTO | C54: ENERO | E54: FEBRERO | F54: MARZO | G54: ABRIL | H54: MAYO | I54: JUNIO | J54: JULIO | K54: AGOSTO | L54: SEPTIEMBRE | M54: OCTUBRE | N54: NOVIEMBRE | O54: DICIEMBRE
B55: IVA ACREDITABLE PAGADO | C55: ='IVA Acreditable'!G251 -> 752187.16 | E55: ='IVA Acreditable'!G443 -> 702016.44 | F55: ='IVA Acreditable'!G661+'IVA 8%'!G5 -> 613498.86
B56: VENTAS COBRADAS 0 Y 16% | C56: ='Aux. ingresos'!AB198 -> 13793677 | E56: ='Aux. ingresos'!AB809 -> 28339739 | F56: ='Aux. ingresos'!AB1006 -> 13578389
B57: TOTAL INGRESOS COBRADOS TASA 0% 16% Y EXENTO | C57: ='Aux. ingresos'!AB199 -> 13879497 | E57: ='Aux. ingresos'!AB808 -> 28623901 | F57: ='Aux. ingresos'!AB1007 -> 13578389
B58: FACTOR | C58: =TRUNC((C56/C57),4) -> 0.9938 | E58: =TRUNC((E56/E57),4)+0.0001 -> 0.9901 | F58: =TRUNC((F56/F57),4) -> 1 | G58: =TRUNC((G56/G57),4) -> #DIV/0! | H58: =TRUNC((H56/H57),4) -> #DIV/0! | I58: =TRUNC((I56/I57),4) -> #DIV/0! | J58: =TRUNC((J56/J57),4) -> #DIV/0! | K58: =TRUNC((K56/K57),4) -> #DIV/0! | L58: =TRUNC((L56/L57),4) -> #DIV/0! | M58: =TRUNC((M56/M57),4) -> #DIV/0! | ... O58: =TRUNC((O56/O57),4) -> #DIV/0!
B59: IVA ACREDITABLE PAGADO | C59: =+C55*C58 -> 747523.6 | E59: =+E55*E58 -> 695066.48 | F59: =+F55*F58 -> 613498.86 | G59: =+G55*G58 -> #DIV/0! | H59: =+H55*H58 -> #DIV/0! | I59: =+I55*I58 -> #DIV/0! | J59: =+J55*J58 -> #DIV/0! | K59: =+K55*K58 -> #DIV/0! | L59: =+L55*L58 -> #DIV/0! | ... O59: =+O55*O58 -> #DIV/0!
L61: =L64/0.16 -> #DIV/0!
B62: CONCEPTO | C62: ENERO | E62: FEBRERO | F62: MARZO | G62: ABRIL | H62: MAYO | I62: JUNIO | J62: JULIO | K62: AGOSTO | L62: SEPTIEMBRE | M62: OCTUBRE | N62: NOVIEMBRE | O62: DICIEMBRE
B63: IVA TRASLADADO COBRADO | C63: ='IVA Trasladado'!H42 -> 298399.55 | E63: ='IVA Trasladado'!H153 -> 529090.95 | F63: ='Aux. ingresos'!AH1005 -> 216805 | G63: HOJA "AUX. INGRESOS" | Q63: =O63/0.16 -> 0
B64: IVA ACREDITABLE PAGADO | C64: =C59 -> 747523.6 | D64: =D59 -> 0 | E64: =E59 -> 695066.48 | F64: ='Aux. egresos'!AH1001+'Aux. egresos'!AI1001 -> 613498.86 | G64: HOJA "AUX. EGRESOS" | H64: =H59 -> #DIV/0! | I64: =I59 -> #DIV/0! | J64: =J59 -> #DIV/0! | K64: =K59 -> #DIV/0! | L64: =L59 -> #DIV/0! | M64: =M59 -> #DIV/0! | N64: =N59 -> #DIV/0! | O64: =O59 -> #DIV/0! | Q64: =O64/0.16 -> #DIV/0!
B65: IVA RET. DEL MES | C65: ='Aux. egresos'!AJ390 -> 133558.9 | E65: ='Aux. egresos'!AJ695 -> 103625.56 | F65: =SUM(F84:F87) -> 97888.2
B66: IVA RET. DEL MES PAGADO | C66: 60898 | E66: =C65 -> 133558.9 | F66: =E65 -> 103625.56 | Q66: =M65-M66 -> 0
B67: IVA ACREDITABLE PAGADO | C67: =+C64-C65+C66 -> 674862.7 | E67: =+E64-E65+E66 -> 724999.81 | F67: =+F64-F65+F66 -> 619236.22 | G67: =+G64-G65+G66 -> #VALUE! | H67: =+H64-H65+H66 -> #DIV/0! | I67: =+I64-I65+I66 -> #DIV/0! | J67: =+J64-J65+J66 -> #DIV/0! | K67: =+K64-K65+K66 -> #DIV/0! | L67: =+L64-L65+L66 -> #DIV/0! | M67: =+M64+M65-M66 -> #DIV/0! | N67: =+N64-N65+N66 -> #DIV/0! | O67: =+O64-O65+O66 -> #DIV/0!
B68: DIF. DE IVA | C68: =+C63-C67 -> -376463.15 | E68: =E63-E67 -> -195908.86 | F68: =+F63-F67 -> -402431.22 | G68: =+G63-G67 -> #VALUE! | H68: =+H63-H67 -> #DIV/0! | I68: =+I63-I67 -> #DIV/0! | J68: =+J63-J67 -> #DIV/0! | K68: =+K63-K67 -> #DIV/0! | L68: =+L63-L67 -> #DIV/0! | M68: =+M63-M67 -> #DIV/0! | ... O68: =+O63-O67 -> #DIV/0! | P68: =+P63-P64 -> 0
B69: ACREDITAMIENTOS DE IVA
A70: ( = ) | B70: DIFERENCIA A CARGO (A FAVOR) | C70: =+C68-C69 -> -376463.15 | E70: =+E68-E69 -> -195908.86 | F70: =+F68-F69 -> -402431.22 | G70: =+G68-G69 -> #VALUE! | H70: =+H68-H69 -> #DIV/0! | I70: =+I68-I69 -> #DIV/0! | J70: =+J68-J69 -> #DIV/0! | K70: =+K68-K69 -> #DIV/0! | L70: =+L68-L69 -> #DIV/0! | ... P70: =+P68-P69 -> 0
B71: Monto pagado con anterioridad
B72: Recargos
B73: Cantidad a pagar
A77: IMPUESTOS RETENIDOS
B80: CONCEPTO | C80: ENERO | E80: FEBRERO | F80: MARZO | G80: ABRIL | H80: MAYO | I80: JUNIO | J80: JULIO | K80: AGOSTO | L80: SEPTIEMBRE | M80: OCTUBRE | N80: NOVIEMBRE | O80: DICIEMBRE
B81: ISR RET. POR SUELDOS YSAL. | C81: =Nomina!$AR$175 -> 652482.6 | E81: =Nomina!AR290 -> 423318.93 | F81: =Nomina!AT398 -> 673797.41 | G81: HOJA "NOMINA" | P81: =SUM(C81:O81) -> 1749598.9
B82: ISR RET. HONORARIOS
B83: ISR RETENIDO | C83: ='Aux. egresos'!AK390 -> 6580.7736 | E83: ='Aux. egresos'!AK695 -> 4465.3558 | F83: ='Aux. egresos'!AK1001 -> 6949.2374 | G83: HOJA "AUX. EGRESOS"
B84: IVA RET. HONORARIOS | C84: ='Aux. egresos'!AJ394 -> 959.4
B85: IVA RET. POR ARRENDAMIENTO
B86: IVA RET. POR FLETES | C86: ='Aux. egresos'!AJ393 -> 132599.5 | E86: ='Aux. egresos'!AJ695 -> 103625.56 | F86: ='Aux. egresos'!AJ1001 -> 97888.2 | G86: HOJA "AUX. EGRESOS"
B87: IVA RET. POR OUTSOURCING
A88: ( = ) | B88: RET. POR PAGAR | C88: =SUM(C81:C87) -> 792622.27 | E88: =SUM(E81:E87) -> 531409.85 | F88: =SUM(F81:F87) -> 778634.85 | G88: =SUM(G81:G87) -> 0 | H88: =SUM(H81:H87) -> 0 | I88: =SUM(I81:I87) -> 0 | J88: =SUM(J81:J87) -> 0 | K88: =SUM(K81:K87) -> 0 | L88: =SUM(L81:L87) -> 0 | ... P88: =SUM(P81:P87) -> 1749598.9
B91: TOTAL A PAGAR | C91: =+C70+C88 -> 416159.12 | E91: =+E70+E88 -> 335500.99 | F91: =+F70+F88 -> 376203.63 | G91: =+G70+G88 -> #VALUE! | H91: =+H70+H88 -> #DIV/0! | I91: =+I70+I88 -> #DIV/0! | J91: =+J70+J88 -> #DIV/0! | K91: =+K88 -> 0 | L91: =L88+L70 -> #DIV/0! | M91: =M88+M70 -> #DIV/0!
B93: SUBSIDIO AL EMPLEO

Sheet UT. CAMBIARIA
C1: MILLHOUSE MEXICO
C2: MME1507071ZA
A3: Tipo Moneda: MXN | C3: AUXILIAR DE CUENTAS DE 1/03/2025 AL 31/03/2025 | J3: 45765
C4: Cuenta 702-01
A5: Cuenta: | B5: 702-01~Utilidad cambiaria | J5: Saldo Inicial: | K5: 1180070.8
A6: FOLIO | B6: FECHA | C6: TIPO DE POLIZA | D6: DOCUMENTO | E6: TERCERO | F6: CUENTA | G6: DEBE | H6: HABER | I6: SALDO | J6: C. COSTOS | K6: NOTAS
B7: 45722 | C7: Movimiento Conciliado | D7: F4393,F4393,F4394 | E7: CHASE PLASTICS DE MEXICO | F7: 702-01~Utilidad cambiaria | G7: 0 | H7: 2218.63 | I7: 1182289.5
B8: 45723 | C8: Movimiento Conciliado | D8: 12031 | E8: MACH 1 AERO SERVICIOS | F8: 702-01~Utilidad cambiaria | G8: 0 | H8: 48.39 | I8: 1182337.9
B9: 45723 | C9: Movimiento Conciliado | D9: F4001,F3528,F3533,F3524,F3523,F3797,F3526 | E9: HELLA AUTOMOTIVE MEXICO | F9: 702-01~Utilidad cambiaria | G9: 0 | H9: 11182.91 | I9: 1193520.8
B10: 45723 | C10: Movimiento Conciliado | D10: 257527257157 | E10: FAST FORWARD CONSOLIDATORS | F10: 702-01~Utilidad cambiaria | G10: 0 | H10: 108.39 | I10: 1193629.2
B11: 45726 | C11: Movimiento Conciliado | D11: F3604,F3813,F3603,F3785,F3784,F3786 | E11: JABIL EMS SWITZERLAND | F11: 702-01~Utilidad cambiaria | G11: 0 | H11: 12220.87 | I11: 1205850
B12: 45729 | C12: Movimiento Conciliado | D12: 1.0405008e+18 | E12: CBM BANCO, SOCIEDAD ANONIMA, INSTITUCION DE BANCA MULTIPLE, INTEGRANTE DEL GRUPO FINANCIERO CITIBANAMEX | F12: 702-01~Utilidad cambiaria | G12: 0 | H12: 6.89 | I12: 1205856.9
B13: 45729 | C13: Movimiento Conciliado | D13: 1.0405008e+18 | E13: CBM BANCO, SOCIEDAD ANONIMA, INSTITUCION DE BANCA MULTIPLE, INTEGRANTE DEL GRUPO FINANCIERO CITIBANAMEX | F13: 702-01~Utilidad cambiaria | G13: 0 | H13: 1.1 | I13: 1205858
B14: 45730 | C14: Movimiento Conciliado | D14: 8040 | E14: RAGA EXPRESS DE NUEVO LAREDO | F14: 702-01~Utilidad cambiaria | G14: 0 | H14: 1005.59 | I14: 1206863.6
B15: 45730 | C15: Movimiento Conciliado | D15: 284102855 | E15: TRM ESPECIALIZADOS | F15: 702-01~Utilidad cambiaria | G15: 0 | H15: 1532.92 | I15: 1208396.5
B16: 45730 | C16: Movimiento Conciliado | D16: 116114113 | E16: AUTOLINEAS LEGAR | F16: 702-01~Utilidad cambiaria | G16: 0 | H16: 627.09 | I16: 1209023.6
B17: 45730 | C17: Movimiento Conciliado | D17: 254 | E17: COSVERINI | F17: 702-01~Utilidad cambiaria | G17: 0 | H17: 1004.13 | I17: 1210027.8
B18: 45737 | C18: Movimiento Conciliado | D18: 5262 | E18: SPERANTUS | F18: 702-01~Utilidad cambiaria | G18: 0 | H18: 43.86 | I18: 1210071.6
B19: 45737 | C19: Movimiento Conciliado | D19: F3781 | E19: HELLA AUTOMOTIVE MEXICO | F19: 702-01~Utilidad cambiaria | G19: 0 | H19: 66.68 | I19: 1210138.3
B20: 45737 | C20: Movimiento Conciliado | D20: 255 | E20: COSVERINI | F20: 702-01~Utilidad cambiaria | G20: 0 | H20: 584.78 | I20: 1210723.1
B21: 45743 | C21: Movimiento Conciliado | D21: 260 | E21: COSVERINI | F21: 702-01~Utilidad cambiaria | G21: 0 | H21: 595.47 | I21: 1211318.5
B22: 45743 | C22: Movimiento Conciliado | D22: 139132 | E22: AUTOLINEAS LEGAR | F22: 702-01~Utilidad cambiaria | G22: 0 | H22: 499.93 | I22: 1211818.5
B23: 45743 | C23: Movimiento Conciliado | D23: 2985 | E23: TRM ESPECIALIZADOS | F23: 702-01~Utilidad cambiaria | G23: 0 | H23: 386.23 | I23: 1212204.7
B24: 45747 | C24: Movimiento Conciliado | D24: F4427 | E24: BONANZA LOGISTICS | F24: 702-01~Utilidad cambiaria | G24: 0 | H24: 169.5 | I24: 1212374.2
B25: 45747 | C25: Poliza Manual | D25: PM319723-0081 | E25: Fluctuación mes de Marzo (20.4380 - 1 = 19.4380) | F25: 702-01~Utilidad cambiaria | G25: 0 | H25: 262333.41 | I25: 1474707.6 | K25: Fluctuación mes de Marzo (20.4380 - 1 = 19.4380)
F26: 1180070.8 | G26: 0 | H26: 294636.77 | I26: 1474707.6

Sheet ANT. CLIENTES
C1: MILLHOUSE MEXICO
C2: MME1507071ZA
A3: Tipo Moneda: MXN | C3: AUXILIAR DE CUENTAS DE 1/03/2025 AL 31/03/2025 | J3: 45765
C4: Cuenta 206
A5: Cuenta: | B5: 206-01-009~Continental | J5: Saldo Inicial: | K5: 0
A6: FOLIO | B6: FECHA | C6: TIPO DE POLIZA | D6: DOCUMENTO | E6: TERCERO | F6: CUENTA | G6: DEBE | H6: HABER | I6: SALDO | J6: C. COSTOS | K6: NOTAS
B7: 45737 | C7: Movimiento Conciliado | D7: 821600 700405000009772025 | E7: Cobro | F7: 206-01-009~Continental | G7: 0 | H7: 5400 | I7: 5400
B8: 45737 | C8: Movimiento Conciliado | D8: 821599 70040500009762025 | E8: Cobro | F8: 206-01-009~Continental | G8: 0 | H8: 11560 | I8: 16960
H9: =SUM(H7:H8) -> 16960

Sheet PARTE ACTUALIZADA
B3: MONTO PENDIENTE DE PAGAR | C3: INPC ACTUAL | D3: INPC DEL MES EN EL QUE SE DEBIO PAGAR | E3: FACTOR DE ACTUALIZACION | F3: TOTAL DE ACTUALIZACIONES | G3: RECARGOS | H3: TOTAL DE RECARGOS | I3: MONTO A PAGAR
B4: ='Resumen P.P.'!D41 -> 6505.108 | C4: =Hoja1!C5 -> 138.726 | D4: =Hoja1!C4 -> 138.343 | E4: =C4/D4 -> 1.0027685 | F4: =B4*E4 -> 6523.1173 | G4: =Hoja1!I4*2 -> 2.94 | H4: =F4*G4% -> 191.77965 | I4: =F4+H4 -> 6714.897
F5: =F4-B4 -> 18.00927

Sheet Hoja1
B3: Mes | C3: 2025 | D3: 2024 | E3: 2023 | F3: 2022 | G3: 2021 | I3: RECARGO
B4: ENE | C4: 138.343 | D4: 133555 | E4: 1273360 | F4: 1180020 | G4: 1102100 | I4: 1.47
B5: FEB | C5: 138.726 | D5: 133681 | E5: 1280460 | F5: 1189810 | G5: 1109070
B6: MAR | D6: 1340650 | E6: 1283890 | F6: 1201590 | G6: 1118240
B7: ABR | D7: 1343360 | E7: 1283630 | F7: 1208090 | G7: 1121900
B8: MAY | D8: 1340870 | E8: 1280840 | F8: 1210220 | G8: 1124190
B9: JUN | D9: 1345940 | E9: 1282140 | F9: 1220440 | G9: 1130180
B10: JUL | D10: 1360030 | E10: 1288320 | F10: 1229480 | G10: 1136820
B11: AGO | D11: 1360130 | E11: 1295450 | F11: 1238030 | G11: 1138990
B12: SEP | D12: 1360800 | E12: 1301200 | F12: 1245710 | G12: 1146010
B13: OCT | D13: 1368280 | E13: 1306090 | F13: 1252760 | G13: 1155610
B14: NOV | D14: 1374240 | E14: 1314450 | F14: 1259970 | G14: 1168840
B15: DIC | D15: 1379490 | E15: 1323730 | F15: 1264780 | G15: 1173080

Sheet EDR
B1: MILLHOUSE MEXICO
B2: MME1507071ZA
A3: Tipo Moneda: MXN | B3: ESTADO DE RESULTADOS DE 1 DE ENERO DE 2025 AL 28 DE FEBRERO DE 2025
C4: ENERO | D4: FEBRERO | E4: MARZO | F4: ABRIL | G4: MAYO | H4: JUNIO | I4: JULIO | J4: AGOSTO | K4: SEPTIEMBRE | L4: OCTUBRE | M4: NOVIEMBRE | N4: DICIEMBRE | O4: TOTAL | P4: PAGOS PROVISIONAL | Q4: DIFERENCIA | R4: MOTIVO
A5: Ingresos
A6: Ingresos | C6: 25661509 | D6: 8272271.5 | E6: - | F6: - | G6: - | H6: - | I6: - | J6: - | K6: - | L6: - | M6: - | N6: - | O6: 33933781 | P6: ='Resumen P.P.'!P11 -> 43263089 | Q6: =O6-P6 -> -9329308.2
A7: Ventas y/o servicios gravados a la tasa general | C7: 4215287.7 | D7: 1490445.6 | E7: - | F7: - | G7: - | H7: - | I7: - | J7: - | K7: - | L7: - | M7: - | N7: - | O7: 5705733.3
A8: Ventas y/o servicios gravados al 0% | C8: 21336221 | D8: 6688819.8 | E8: - | F8: - | G8: - | H8: - | I8: - | J8: - | K8: - | L8: - | M8: - | N8: - | O8: 28025041
A9: Otros ingresos propios | C9: 110000.25 | D9: 93006.12 | E9: - | F9: - | G9: - | H9: - | I9: - | J9: - | K9: - | L9: - | M9: - | N9: - | O9: 203006.37 | P9: ='Resumen P.P.'!P15 -> 203006.69 | Q9: =O9-P9 -> -0.32
A10: Total | C10: 25661509 | D10: 8272271.5 | E10: - | F10: - | G10: - | H10: - | I10: - | J10: - | K10: - | L10: - | M10: - | N10: - | O10: 33933781
A12: Costos
A13: Devoluciones, descuentos o bonificaciones sobre compras | C13: 277218.22 | D13: 103340.61 | E13: - | F13: - | G13: - | H13: - | I13: - | J13: - | K13: - | L13: - | M13: - | N13: - | O13: 380558.83
A14: Devoluciones, descuentos o bonificaciones sobre compras | C14: 277218.22 | D14: 103340.61 | E14: - | F14: - | G14: - | H14: - | I14: - | J14: - | K14: - | L14: - | M14: - | N14: - | O14: 380558.83
A15: Total | C15: -277218.22 | D15: -103340.61 | E15: - | F15: - | G15: - | H15: - | I15: - | J15: - | K15: - | L15: - | M15: - | N15: - | O15: -380558.83
A17: Gastos
A18: Gastos generales | C18: 56138.61 | D18: 318182.07 | E18: - | F18: - | G18: - | H18: - | I18: - | J18: - | K18: - | L18: - | M18: - | N18: - | O18: 374320.68
A19: Sueldos y salarios | C19: 6.01 | D19: 2.81 | E19: - | F19: - | G19: - | H19: - | I19: - | J19: - | K19: - | L19: - | M19: - | N19: - | O19: 8.82
A20: Indemnizaciones | C20: 27333.6 | D20: 289079.26 | E20: - | F20: - | G20: - | H20: - | I20: - | J20: - | K20: - | L20: - | M20: - | N20: - | O20: 316412.86
A21: Honorarios a personas morales residentes nacionales | C21: 28799 | D21: 29100 | E21: - | F21: - | G21: - | H21: - | I21: - | J21: - | K21: - | L21: - | M21: - | N21: - | O21: 57899
A22: Arrendamiento a personas morales residentes nacionales | C22: 26536.77 | D22: 256600.46 | E22: - | F22: - | G22: - | H22: - | I22: - | J22: - | K22: - | L22: - | M22: - | N22: - | O22: 283137.23
A23: RENTA DE EQUIPO DE TRANSPORTE | C23: - | D23: 1437.87 | E23: - | F23: - | G23: - | H23: - | I23: - | J23: - | K23: - | L23: - | M23: - | N23: - | O23: 1437.87
A24: RENTA DE EQUIPOS | C24: 23174.7 | D24: 23079.62 | E24: - | F24: - | G24: - | H24: - | I24: - | J24: - | K24: - | L24: - | M24: - | N24: - | O24: 46254.32
A25: RENTA LOCAL | C25: 3362.07 | D25: 229910.56 | E25: - | F25: - | G25: - | H25: - | I25: - | J25: - | K25: - | L25: - | M25: - | N25: - | O25: 233272.63
A26: RENTA ESTACIONAMIENTO | C26: - | D26: 2172.41 | E26: - | F26: - | G26: - | H26: - | I26: - | J26: - | K26: - | L26: - | M26: - | N26: - | O26: 2172.41
A27: Gastos generales | C27: 4600245.2 | D27: 3095006.3 | E27: - | F27: - | G27: - | H27: - | I27: - | J27: - | K27: - | L27: - | M27: - | N27: - | O27: 7695251.5
A28: Viáticos y gastos de viaje | C28: 1187.94 | D28: 10793.75 | E28: - | F28: - | G28: - | H28: - | I28: - | J28: - | K28: - | L28: - | M28: - | N28: - | O28: 11981.69
A29: Teléfono, internet | C29: 37317.17 | D29: 25096.27 | E29: - | F29: - | G29: - | H29: - | I29: - | J29: - | K29: - | L29: - | M29: - | N29: - | O29: 62413.44
A30: Limpieza | C30: - | D30: 853.05 | E30: - | F30: - | G30: - | H30: - | I30: - | J30: - | K30: - | L30: - | M30: - | N30: - | O30: 853.05
A31: Seguros y fianzas | C31: - | D31: 10775.42 | E31: - | F31: - | G31: - | H31: - | I31: - | J31: - | K31: - | L31: - | M31: - | N31: - | O31: 10775.42
A32: Cuotas y suscripciones | C32: 274601 | D32: 177922.31 | E32: - | F32: - | G32: - | H32: - | I32: - | J32: - | K32: - | L32: - | M32: - | N32: - | O32: 452523.31
A33: Fletes y acarreos | C33: 4191443.6 | D33: 2766661.5 | E33: - | F33: - | G33: - | H33: - | I33: - | J33: - | K33: - | L33: - | M33: - | N33: - | O33: 6958105.2
A34: Comisiones sobre ventas | C34: 261 | D34: 607 | E34: - | F34: - | G34: - | H34: - | I34: - | J34: - | K34: - | L34: - | M34: - | N34: - | O34: 868
A35: Gastos no deducibles (sin requisitos fiscales) | C35: 95434.43 | D35: 102296.99 | E35: - | F35: - | G35: - | H35: - | I35: - | J35: - | K35: - | L35: - | M35: - | N35: - | O35: 197731.42
A36: Otros gastos generales | C36: 340670.53 | D36: 338425.67 | E36: - | F36: - | G36: - | H36: - | I36: - | J36: - | K36: - | L36: - | M36: - | N36: - | O36: 679096.2
A37: RECOLECCION BASURA | C37: 3100 | D37: 22783.42 | E37: - | F37: - | G37: - | H37: - | I37: - | J37: - | K37: - | L37: - | M37: - | N37: - | O37: 25883.42
A38: SERVICIOS (TEL,AGUA,CFE,CEL ) | C38: 11810.39 | D38: 4056.75 | E38: - | F38: - | G38: - | H38: - | I38: - | J38: - | K38: - | L38: - | M38: - | N38: - | O38: 15867.14
A39: SERVICIO DE LOGISTICA | C39: 321179.8 | D39: 311585.5 | E39: - | F39: - | G39: - | H39: - | I39: - | J39: - | K39: - | L39: - | M39: - | N39: - | O39: 632765.3
A40: CONSUMOS | C40: 4580.34 | D40: - | E40: - | F40: - | G40: - | H40: - | I40: - | J40: - | K40: - | L40: - | M40: - | N40: - | O40: 4580.34
A41: Gastos generales | C41: 12600 | D41: 2356.5 | E41: - | F41: - | G41: - | H41: - | I41: - | J41: - | K41: - | L41: - | M41: - | N41: - | O41: 14956.5
A42: Renta de montacargas | C42: 12600 | D42: - | E42: - | F42: - | G42: - | H42: - | I42: - | J42: - | K42: - | L42: - | M42: - | N42: - | O42: 12600
A43: Comisiones Bancarias | C43: - | D43: 2356.5 | E43: - | F43: - | G43: - | H43: - | I43: - | J43: - | K43: - | L43: - | M43: - | N43: - | O43: 2356.5
A44: Gastos de venta | C44: 44118.11 | D44: - | E44: - | F44: - | G44: - | H44: - | I44: - | J44: - | K44: - | L44: - | M44: - | N44: - | O44: 44118.11
A45: Mantenimiento y conservación | C45: 44118.11 | D45: - | E45: - | F45: - | G45: - | H45: - | I45: - | J45: - | K45: - | L45: - | M45: - | N45: - | O45: 44118.11
A46: Gastos de administración | C46: 3397572.7 | D46: 2518762.6 | E46: - | F46: - | G46: - | H46: - | I46: - | J46: - | K46: - | L46: - | M46: - | N46: - | O46: 5916335.3
A47: Sueldos y salarios | C47: 2453680.9 | D47: 1464026.8 | E47: - | F47: - | G47: - | H47: - | I47: - | J47: - | K47: - | L47: - | M47: - | N47: - | O47: 3917707.7
A48: Compensaciones | C48: 404628.21 | D48: 170631.83 | E48: - | F48: - | G48: - | H48: - | I48: - | J48: - | K48: - | L48: - | M48: - | N48: - | O48: 575260.04
A49: Tiempos extras | C49: 36595.81 | D49: 40308.32 | E49: - | F49: - | G49: - | H49: - | I49: - | J49: - | K49: - | L49: - | M49: - | N49: - | O49: 76904.13
A50: Prima vacacional | C50: 43446.54 | D50: 16554.34 | E50: - | F50: - | G50: - | H50: - | I50: - | J50: - | K50: - | L50: - | M50: - | N50: - | O50: 60000.88
A51: Prima dominical | C51: 9439.44 | D51: 7460.82 | E51: - | F51: - | G51: - | H51: - | I51: - | J51: - | K51: - | L51: - | M51: - | N51: - | O51: 16900.26
A52: Primas de antigüedad | C52: 13382.4 | D52: 101827.5 | E52: - | F52: - | G52: - | H52: - | I52: - | J52: - | K52: - | L52: - | M52: - | N52: - | O52: 115209.9
A53: Aguinaldo | C53: 3926.33 | D53: 7303.31 | E53: - | F53: - | G53: - | H53: - | I53: - | J53: - | K53: - | L53: - | M53: - | N53: - | O53: 11229.64
A54: Indemnizaciones | C54: 115500.3 | D54: 424748.7 | E54: - | F54: - | G54: - | H54: - | I54: - | J54: - | K54: - | L54: - | M54: - | N54: - | O54: 540249
A55: Asimilados a salarios | C55: 106692.66 | D55: 79562.66 | E55: - | F55: - | G55: - | H55: - | I55: - | J55: - | K55: - | L55: - | M55: - | N55: - | O55: 186255.32
A56: Servicios administrativos | C56: 16615.1 | D56: 50000 | E56: - | F56: - | G56: - | H56: - | I56: - | J56: - | K56: - | L56: - | M56: - | N56: - | O56: 66615.1
A57: Honorarios a personas morales residentes nacionales | C57: 36000 | D57: - | E57: - | F57: - | G57: - | H57: - | I57: - | J57: - | K57: - | L57: - | M57: - | N57: - | O57: 36000
A58: Arrendamiento a personas morales residentes nacionales | C58: 114694.11 | D58: - | E58: - | F58: - | G58: - | H58: - | I58: - | J58: - | K58: - | L58: - | M58: - | N58: - | O58: 114694.11
A59: Combustibles y lubricantes | C59: 4717.47 | D59: - | E59: - | F59: - | G59: - | H59: - | I59: - | J59: - | K59: - | L59: - | M59: - | N59: - | O59: 4717.47
A60: Mantenimiento y conservación | C60: 11979.74 | D60: 62563.13 | E60: - | F60: - | G60: - | H60: - | I60: - | J60: - | K60: - | L60: - | M60: - | N60: - | O60: 74542.87
A61: Seguros y fianzas | C61: - | D61: 20289.2 | E61: - | F61: - | G61: - | H61: - | I61: - | J61: - | K61: - | L61: - | M61: - | N61: - | O61: 20289.2
A62: Cuotas y suscripciones | C62: - | D62: 32578.9 | E62: - | F62: - | G62: - | H62: - | I62: - | J62: - | K62: - | L62: - | M62: - | N62: - | O62: 32578.9
A63: Propaganda y publicidad | C63: - | D63: 1599 | E63: - | F63: - | G63: - | H63: - | I63: - | J63: - | K63: - | L63: - | M63: - | N63: - | O63: 1599
A64: Capacitación al personal | C64: 14000 | D64: - | E64: - | F64: - | G64: - | H64: - | I64: - | J64: - | K64: - | L64: - | M64: - | N64: - | O64: 14000
A65: Gastos no deducibles (sin requisitos fiscales) | C65: - | D65: 16243.23 | E65: - | F65: - | G65: - | H65: - | I65: - | J65: - | K65: - | L65: - | M65: - | N65: - | O65: 16243.23
A66: Otros gastos de administración | C66: 12273.7 | D66: 23064.83 | E66: - | F66: - | G66: - | H66: - | I66: - | J66: - | K66: - | L66: - | M66: - | N66: - | O66: 35338.53
A67: Depreciación contable | C67: 43985.3 | D67: 43985.3 | E67: - | F67: - | G67: - | H67: - | I67: - | J67: - | K67: - | L67: - | M67: - | N67: - | O67: 87970.6
A68: Depreciación de mobiliario y equipo de oficina | C68: 24299 | D68: 24299 | E68: - | F68: - | G68: - | H68: - | I68: - | J68: - | K68: - | L68: - | M68: - | N68: - | O68: 48598
A69: Depreciación de equipo de cómputo | C69: 19686.3 | D69: 19686.3 | E69: - | F69: - | G69: - | H69: - | I69: - | J69: - | K69: - | L69: - | M69: - | N69: - | O69: 39372.6
A70: Gastos Tasa 0% | C70: 7317992.8 | D70: 1128500.3 | E70: - | F70: - | G70: - | H70: - | I70: - | J70: - | K70: - | L70: - | M70: - | N70: - | O70: 8446493.1
A71: Fletes 0% | C71: 7317992.8 | D71: 1128386.3 | E71: - | F71: - | G71: - | H71: - | I71: - | J71: - | K71: - | L71: - | M71: - | N71: - | O71: 8446379.1
A72: Casetas | C72: - | D72: 114 | E72: - | F72: - | G72: - | H72: - | I72: - | J72: - | K72: - | L72: - | M72: - | N72: - | O72: 114
A73: Total | C73: 15839860 | D73: 7701819.2 | E73: - | F73: - | G73: - | H73: - | I73: - | J73: - | K73: - | L73: - | M73: - | N73: - | O73: 23541679
A75: Resultado integral de financiamiento
A76: Gastos financieros | C76: 75991.92 | D76: 603596.31 | E76: - | F76: - | G76: - | H76: - | I76: - | J76: - | K76: - | L76: - | M76: - | N76: - | O76: 679588.23
A77: Pérdida cambiaria | C77: 75991.92 | D77: 603596.31 | E77: - | F77: - | G77: - | H77: - | I77: - | J77: - | K77: - | L77: - | M77: - | N77: - | O77: 679588.23
A78: Productos financieros | C78: 552957.23 | D78: 627113.61 | E78: - | F78: - | G78: - | H78: - | I78: - | J78: - | K78: - | L78: - | M78: - | N78: - | O78: 1180070.8
A79: Utilidad cambiaria | C79: 552957.23 | D79: 627113.61 | E79: - | F79: - | G79: - | H79: - | I79: - | J79: - | K79: - | L79: - | M79: - | N79: - | O79: 1180070.8 | P79: ='Resumen P.P.'!P18 -> 1474707.6 | Q79: =O79-P79 -> -294636.77
A80: Total | C80: -476965.31 | D80: -23517.3 | E80: - | F80: - | G80: - | H80: - | I80: - | J80: - | K80: - | L80: - | M80: - | N80: - | O80: -500482.61
A82: Utilidad Total | C82: 10575833 | D82: 697310.22 | E82: - | F82: - | G82: - | H82: - | I82: - | J82: - | K82: - | L82: - | M82: - | N82: - | O82: 11273143

Sheet BAL01
C1: MILLHOUSE MEXICO
C2: MME1507071ZA
A3: Tipo Moneda: MXN | C3: BALANZA DE COMPROBACION DE 1/01/2025 AL 31/01/2025 | E3: MES ENERO 2025 | H3: 45705
A4: No CUENTA | C4: CUENTA | D4: SALDO INICIAL | E4: DEBE | G4: HABER | H4: SALDO FINAL | J4: IMPUESTOS | K4: DIFERENCIA
A5: 102 | B5: D | C5: Bancos | D5: 9859012.4 | E5: 29338688 | G5: 19694593 | H5: 19503108
A6: 102-01 | B6: D | C6: Bancos nacionales | D6: 653554.3 | E6: 10985873 | G6: 8880571.3 | H6: 2758856.3
A7: 102-01-001 | B7: D | C7: BANAMEX CTA 1227167 | D7: 653554.3 | E7: 10985873 | G7: 8880571.3 | H7: 2758856.3
A8: 102-02 | B8: D | C8: Bancos extranjeros | D8: 9205458.1 | E8: 18352815 | G8: 10814022 | H8: 16744251
A9: 102-02-004 | B9: D | C9: BANAMEX DLLS | D9: -24261077 | E9: 1699513.4 | G9: 504157.25 | H9: -23065721
A10: 102-02-005 | B10: D | C10: COMPL BANAMEX DLLS | D10: 33873928 | E10: 16653302 | G10: 10309865 | H10: 40217365
A11: 102-02-010 | B11: D | C11: MONEX USD COMPLEMENTARIA | D11: -407392.5 | E11: 0 | G11: 0 | H11: -407392.5
A12: 105 | B12: D | C12: Clientes | D12: 1.008266e+08 | E12: 26615384 | G12: 14014247 | H12: 1.1342773e+08
A13: 105-01 | B13: D | C13: Clientes nacionales | D13: 1.0086144e+08 | E13: ='BAL2'!G577 -> 122080 | G13: 14014247 | H13: 1.1346257e+08
A14: 105-01-001 | B14: D | C14: Clientes nacionales | D14: 0.01 | E14: 0 | G14: 0 | H14: 0.01
A15: 105-01-005 | B15: D | C15: CLIENTES VARIOS | D15: 56868.55 | E15: 0 | G15: 0 | H15: 56868.55
A16: 105-01-026 | B16: D | C16: EA LOGISTICA SA DE CV DLLS | D16: 0.01 | E16: 0 | G16: 0 | H16: 0.01
A17: 105-01-042 | B17: D | C17: FIT LOGISTICS SA DE CV DLLS | D17: 0.08 | E17: 0 | G17: 0 | H17: 0.08
A18: 105-01-068 | B18: D | C18: CLIENTES VARIOS DLLS | D18: 30603.64 | E18: 0 | G18: 0 | H18: 30603.64
A19: 105-01-070 | B19: D | C19: IE TRADE COMERCIAL S DE RL DE CV DLLS | D19: -41233.53 | E19: 0 | G19: 14165.41 | H19: -55398.94
A20: 105-01-107 | B20: D | C20: GRUPO LOGISTICO MEXICANO DEL NORESTE SA DE CV DLLS | D20: 28308.03 | E20: 0 | G20: 0 | H20: 28308.03
A21: 105-01-109 | B21: D | C21: ELECTRONICA CLARION SA DE CV DLLS | D21: 921902.03 | E21: 0 | G21: 552218.03 | H21: 369684
A22: 105-01-129 | B22: D | C22: EXO TRANSPORT SA DE CV DLLS | D22: 23422.47 | E22: 0 | G22: 0 | H22: 23422.47
A23: 105-01-143 | B23: D | C23: CEVA FREIGHT MANAGEMENT MEXICO SA DE CV | D23: 2065130 | E23: 1123344 | G23: 0 | H23: 3188474
A24: 105-01-147 | B24: D | C24: JABIL CIRCUIT DE CHIHUAHUA S DE RL DE CV | D24: -2498.39 | E24: 0 | G24: 0 | H24: -2498.39
A25: 105-01-148 | B25: D | C25: JABIL CIRCUIT DE MEXICO S DE RL DE CV | D25: 1013571.6 | E25: 0 | G25: 0 | H25: 1013571.6
... A112: 105-02-002 | B112: D | C112: AIRTEMP DE MEXICO SA DE CV | D112: -34839.4 | E112: 0 | G112: 0 | H112: -34839.4
A113: 107 | B113: D | C113: Deudores diversos | D113: -7947570.3 | E113: 52192.9 | G113: 5.27 | H113: -7895382.7
A114: 107-01-001 | B114: D | C114: Milan Expedited Services | D114: 9800 | E114: 0 | G114: 0 | H114: 9800
A115: 107-01-002 | B115: D | C115: KASAI | D115: -420549.84 | E115: 0 | G115: 0 | H115: -420549.84
A116: 107-02 | B116: D | C116: Socios y accionistas | D116: 45000 | E116: 0 | G116: 0 | H116: 45000
A117: 107-05 | B117: D | C117: Otros deudores diversos | D117: -7619699.2 | E117: 52192.9 | G117: 5.27 | H117: -7567511.6
A118: 107-05-004 | B118: D | C118: DEUDORES VARIOS | D118: -5125955 | E118: 0 | G118: 0 | H118: -5125955
A119: 107-05-006 | B119: D | C119: BERNABE SANCHEZ TABOADA | D119: 5000 | E119: 0 | G119: 0 | H119: 5000
A120: 107-05-008 | B120: D | C120: MAURICIO GARCIA ESTRADA | D120: 85959.06 | E120: 0 | G120: 0 | H120: 85959.06
A121: 107-05-010 | B121: D | C121: GASTOS POR COMPROBAR/VIATICOS | D121: 232425.84 | E121: 52192.9 | G121: 0 | H121: 284618.74
A122: 107-05-011 | B122: D | C122: PAGOS PENDIENTES DE FACTURAR O DEVOLVER | D122: 75538.85 | E122: 0 | G122: 0 | H122: 75538.85
A123: 107-05-012 | B123: D | C123: BRUNO TORRES | D123: 20000 | E123: 0 | G123: 0 | H123: 20000
A124: 107-05-013 | B124: D | C124: EXPEDITED INFINITY MY S DE RL DE CV | D124: 136012 | E124: 0 | G124: 0 | H124: 136012
A125: 107-05-014 | B125: D | C125: JORGE CHALITA | D125: 910 | E125: 0 | G125: 0 | H125: 910
... A138: 107-05-025 | B138: D | C138: HUGO ENRIQUE CAVAZOS GUERRA | D138: 37878.76 | E138: 0 | G138: 0 | H138: 37878.76
A139: 113 | B139: D | C139: Impuestos a favor | D139: 23424832 | E139: 453787.61 | G139: 437.5 | H139: 23878182
A140: 113-01 | B140: D | C140: IVA a favor | D140: 5156736.7 | E140: 453787.61 | G140: 0 | H140: 5610524.3
A141: 113-02 | B141: D | C141: ISR a favor | D141: 18013334 | E141: 0 | G141: 0 | H141: 18013334
A142: 113-06 | B142: D | C142: Subsidio al empleo | D142: 119.53 | E142: 0 | G142: 437.5 | H142: -317.97
A143: 113-08 | B143: D | C143: Otros impuestos a favor | D143: 254641.35 | E143: 0 | G143: 0 | H143: 254641.35
A144: 114 | B144: D | C144: Pagos provisionales | D144: 3240107 | E144: 0 | G144: 0 | H144: 3240107
A145: 114-01 | B145: D | C145: Pagos provisionales de ISR | D145: 3240107 | E145: 0 | G145: 0 | H145: 3240107
A146: 118 | B146: D | C146: Impuestos acreditables pagados | D146: 6733589.6 | E146: 752201.61 | G146: 752187.16 | H146: 6733604.1
A147: 118-01 | B147: D | C147: IVA acreditable pagado | D147: 6732644.8 | E147: 752187.16 | G147: 752187.16 | H147: 6732644.8
A148: 118-01-001 | B148: D | C148: IVA TASA 16% | D148: 6731067.3 | E148: 752187.16 | G148: 752187.16 | H148: 6731067.3
A149: 118-01-002 | B149: D | C149: IVA TASA 8% FRONTERA | D149: 1577.54 | E149: 0 | G149: 0 | H149: 1577.54
A150: 118-03 | B150: D | C150: IEPS acreditable pagado | D150: 944.81 | E150: 14.45 | G150: 0 | H150: 959.26
A151: 119 | B151: D | C151: Impuestos acreditables por pagar | D151: 1795404.6 | E151: 737823.29 | G151: 750176.02 | H151: 1783051.9
A152: 119-01 | B152: D | C152: IVA pendiente de pago | D152: 1795439 | E152: 737823.29 | G152: 750161.57 | H152: 1783100.8
A153: 119-03 | B153: D | C153: IEPS pendiente de pago | D153: -34.42 | E153: 0 | G153: 14.45 | H153: -48.87
A154: 120 | B154: D | C154: Anticipo a proveedores | D154: 297330.12 | E154: 0 | G154: 0 | H154: 297330.12
A155: 120-01 | B155: D | C155: Anticipo a proveedores nacional | D155: 277250.69 | E155: 0 | G155: 0 | H155: 277250.69
A156: 120-01-001 | B156: D | C156: JIMSA TRANSPORTES | D156: 2000 | E156: 0 | G156: 0 | H156: 2000
A157: 120-02 | B157: D | C157: Anticipo a proveedores extranjero | D157: 18079.43 | E157: 0 | G157: 0 | H157: 18079.43
A158: 155 | B158: D | C158: Mobiliario y equipo de oficina | D158: 793057.38 | E158: 0 | G158: 0 | H158: 793057.38
A159: 155-01 | B159: D | C159: Mobiliario y equipo de oficina | D159: 793057.38 | E159: 0 | G159: 0 | H159: 793057.38
A160: 155-01-001 | B160: D | C160: INVERSION 2016 | D160: 82182.21 | E160: 0 | G160: 0 | H160: 82182.21
A161: 155-01-002 | B161: D | C161: INVERSION 2017 | D161: 2241.38 | E161: 0 | G161: 0 | H161: 2241.38
A162: 155-01-003 | B162: D | C162: INVERSION 2018 | D162: 21989.65 | E162: 0 | G162: 0 | H162: 21989.65
A163: 155-01-004 | B163: D | C163: INVERSION 2019 | D163: 107211.47 | E163: 0 | G163: 0 | H163: 107211.47
A164: 155-01-005 | B164: D | C164: CAJONERA CON PAPELERO Y ARCHIVO CON CERRADURA | D164: 56910 | E164: 0 | G164: 0 | H164: 56910
A165: 155-01-006 | B165: D | C165: 9 SILLAS DE OFICINA METREX | D165: 19834.74 | E165: 0 | G165: 0 | H165: 19834.74
A166: 155-01-007 | B166: D | C166: ARCHIVERO_CREDENZA FA 6 AGO 2021 | D166: 11050 | E166: 0 | G166: 0 | H166: 11050
A167: 155-01-008 | B167: D | C167: RACKS DE ALMACENAJE QRO. FA/9 NOV 2021 | D167: 96000 | E167: 0 | G167: 0 | H167: 96000
A168: 155-01-009 | B168: D | C168: CAJONERA CON CERRADURA FA 04 MARZO 2022 | D168: 31700 | E168: 0 | G168: 0 | H168: 31700
A169: 155-01-010 | B169: D | C169: RACKS QUERETARO FA 17 MAYO 2022 | D169: 240337.93 | E169: 0 | G169: 0 | H169: 240337.93
A170: 155-01-011 | B170: D | C170: RACKS QUERETARIO FA 6 OCT 2022 | D170: 123600 | E170: 0 | G170: 0 | H170: 123600
A171: 156 | B171: D | C171: Equipo de cómputo | D171: 1354041.8 | E171: 0 | G171: 0 | H171: 1354041.8
A172: 156-01 | B172: D | C172: Equipo de cómputo | D172: 1354041.8 | E172: 0 | G172: 0 | H172: 1354041.8
A173: 156-01-001 | B173: D | C173: INVERSION 2016 | D173: 66377.58 | E173: 0 | G173: 0 | H173: 66377.58
A174: 156-01-002 | B174: D | C174: INVERSION 2017 | D174: 66956.89 | E174: 0 | G174: 0 | H174: 66956.89
A175: 156-01-003 | B175: D | C175: INVERSION 2018 | D175: 201253.42 | E175: 0 | G175: 0 | H175: 201253.42
A176: 156-01-004 | B176: D | C176: INVERSION 2019 | D176: 101107.75 | E176: 0 | G176: 0 | H176: 101107.75
A177: 156-01-005 | B177: D | C177: INVERSION 2020 | D177: 117827.59 | E177: 0 | G177: 0 | H177: 117827.59
A178: 156-01-006 | B178: D | C178: LAPTOP ACER A515-55-320U FA 13 NOVIEMBRE 2020 | D178: 13066.33 | E178: 0 | G178: 0 | H178: 13066.33
A179: 156-01-007 | B179: D | C179: LAPTOP DELL INSPIRON FA 22 FEB 2021 | D179: 12756.04 | E179: 0 | G179: 0 | H179: 12756.04
A180: 156-01-008 | B180: D | C180: EQUIPO DE COMPUTO FA 01 MARZO 2022 | D180: 441090.96 | E180: 0 | G180: 0 | H180: 441090.96
A181: 156-01-009 | B181: D | C181: EQUIPO DE COMPUTO FA 09 MAYO 2022 | D181: 14807.06 | E181: 0 | G181: 0 | H181: 14807.06
A182: 156-01-010 | B182: D | C182: DESKTOP DELL OPTIPLEX 3090 MFF INTEL FA 2 MAYO 22 | D182: 47983.14 | E182: 0 | G182: 0 | H182: 47983.14
A183: 156-01-011 | B183: D | C183: DELL VOSTRO 14 3000 3400 35.6CM(14") FA 17 MAY 22 | D183: 14912.15 | E183: 0 | G183: 0 | H183: 14912.15
... A189: 156-01-017 | B189: D | C189: Laptop Lenovo ThinkPad L14 Gen 4 | D189: 21723.28 | E189: 0 | G189: 0 | H189: 21723.28
A190: 171 | B190: A | C190: Depreciación acumulada de activos fijos | D190: 1333729.1 | E190: 0 | G190: 43985.3 | H190: 1377714.4
A191: 171-04 | B191: A | C191: Depreciación acumulada de mobiliario y equipo de oficina | D191: 350862.02 | E191: 0 | G191: 24299 | H191: 375161.02
A192: 171-04-001 | B192: A | C192: DEPN.ACUM. MOB. Y EQ. INVERSION 2016 | D192: 62053.57 | E192: 0 | G192: 553.15 | H192: 62606.72
A193: 171-04-002 | B193: A | C193: DEPN.ACUM. MOB. Y EQ. INVERSION 2017 | D193: 5119.99 | E193: 0 | G193: 557.97 | H193: 5677.96
A194: 171-04-003 | B194: A | C194: DEPN.ACUM. MOB. Y EQ. INVERSION 2018 | D194: 22950.98 | E194: 0 | G194: 1677.11 | H194: 24628.09
A195: 171-04-004 | B195: A | C195: DEPN.ACUM. MOB. Y EQ. INVERSION 2019 | D195: 50777.19 | E195: 0 | G195: 842.56 | H195: 51619.75
A196: 171-04-005 | B196: A | C196: DEPN.ACUM. MOB. Y EQ. INVERSION 2021 | D196: 36622.33 | E196: 0 | G196: 981.91 | H196: 37604.24
A197: 171-04-006 | B197: A | C197: DEPN.ACUM.MOB Y EQ. | D197: 173337.96 | E197: 0 | G197: 19686.3 | H197: 193024.26
A198: 171-05 | B198: A | C198: Depreciación acumulada de equipo de cómputo | D198: 982867.09 | E198: 0 | G198: 19686.3 | H198: 1002553.4
A199: 171-05-001 | B199: A | C199: DEPN.ACUM. EQ. COMPUTO INVERSION 2016 | D199: 72610.31 | E199: 0 | G199: 0 | H199: 72610.31
A200: 171-05-002 | B200: A | C200: DEPN.ACUM. EQ. COMPUTO INVERSION 2017 | D200: 66949.86 | E200: 0 | G200: 0 | H200: 66949.86
A201: 171-05-003 | B201: A | C201: DEPN.ACUM. EQ. COMPUTO INVERSION 2018 | D201: 225816.64 | E201: 0 | G201: 0 | H201: 225816.64
A202: 171-05-004 | B202: A | C202: DEPN.ACUM. EQ. COMPUTO INVERSION 2019 | D202: 101107.6 | E202: 0 | G202: 0 | H202: 101107.6
... A205: 171-05-007 | B205: A | C205: DEPN.ACUM.EQ.COMPUTO | D205: 380858.37 | E205: 0 | G205: 19367.4 | H205: 400225.77
...

Sheet BAL2
B2: FEBRERO
B3: No CUENTA | C3: NATURALEZA | D3: CUENTA | E3: SALDO INICIAL | F3: DEBE | G3: HABER | H3: SALDO FINAL
B4: 102 | C4: D | D4: Bancos | E4: 24841449 | F4: 34861573 | G4: 16571990 | H4: 43131032
B5: 102-01 | C5: D | D5: Bancos nacionales | E5: 4014261.7 | F5: 9637400.6 | G5: 9799826.6 | H5: 3851835.7
B6: 102-01-001 | C6: D | D6: BANAMEX CTA 1227167 | E6: 4014261.7 | F6: 9637400.6 | G6: 9799826.6 | H6: 3851835.7
B7: 102-02 | C7: D | D7: Bancos extranjeros | E7: 20827188 | F7: 25224172 | G7: 6772163.5 | H7: 39279196
B8: 102-02-004 | C8: D | D8: BANAMEX DLLS | E8: -22894884 | F8: 3254717.4 | G8: 315392.16 | H8: -19955559
B9: 102-02-005 | C9: D | D9: COMPL BANAMEX DLLS | E9: 44070665 | F9: 21969455 | G9: 6456771.4 | H9: 59583348
B10: 102-02-009 | C10: D | D10: MONEX USD | E10: 3000 | F10: 0 | G10: 0 | H10: 3000
B11: 102-02-010 | C11: D | D11: MONEX USD COMPLEMENTARIA | E11: -351593.1 | F11: 0 | G11: 0 | H11: -351593.1
B12: 105 | C12: D | D12: Clientes | E12: 1.3181517e+08 | F12: 8417736.7 | G12: 28542335 | H12: 1.1169057e+08
B13: 105-01 | C13: D | D13: Clientes nacionales | E13: 1.3185001e+08 | F13: 8417736.7 | G13: 28542335 | H13: 1.1172541e+08
B14: 105-01-001 | C14: D | D14: Clientes nacionales | E14: 0.01 | F14: 0 | G14: 0 | H14: 0.01
B15: 105-01-004 | C15: D | D15: NORGISTICS MEXICO SA DE CV | E15: 15755.7 | F15: 0 | G15: 0 | H15: 15755.7
... B785: 899-04 | C785: D | D785: Traspaso Bancario | E785: 0 | F785: 5557500 | G785: 5557500 | H785: 0
B786: TOTALES | F786: 70061335 | G786: 70061335

Sheet BAL3
B2: MARZO
B3: No CUENTA | C3: NATURALEZA | D3: CUENTA | E3: SALDO INICIAL | F3: DEBE | G3: HABER | H3: SALDO FINAL
B4: 102 | C4: D | D4: Bancos | E4: 43131032 | F4: 21474140 | G4: 17991513 | H4: 46613659
B5: 102-01 | C5: D | D5: Bancos nacionales | E5: 3851835.7 | F5: 8530709 | G5: 9809518.3 | H5: 2573026.4
B6: 102-01-001 | C6: D | D6: BANAMEX CTA 1227167 | E6: 3851835.7 | F6: 8530709 | G6: 9809518.3 | H6: 2573026.4
B7: 102-02 | C7: D | D7: Bancos extranjeros | E7: 39279196 | F7: 12943431 | G7: 8181994.9 | H7: 44040633
B8: 102-02-004 | C8: D | D8: BANAMEX DLLS | E8: -19955559 | F8: 627362.31 | G8: 407329.02 | H8: -19735526
B9: 102-02-005 | C9: D | D9: COMPL BANAMEX DLLS | E9: 59583348 | F9: 12316069 | G9: 7774665.9 | H9: 64124752
B10: 102-02-009 | C10: D | D10: MONEX USD | E10: 3000 | F10: 0 | G10: 0 | H10: 3000
B11: 102-02-010 | C11: D | D11: MONEX USD COMPLEMENTARIA | E11: -351593.1 | F11: 0 | G11: 0 | H11: -351593.1
B12: 105 | C12: D | D12: Clientes | E12: 1.1169057e+08 | F12: 9702176 | G12: 13789928 | H12: 1.0760282e+08
B13: 105-01 | C13: D | D13: Clientes nacionales | E13: 1.1172541e+08 | F13: 9702176 | G13: 13789928 | H13: 1.0763766e+08
B14: 105-01-001 | C14: D | D14: Clientes nacionales | E14: 0.01 | F14: 0 | G14: 0 | H14: 0.01
B15: 105-01-004 | C15: D | D15: NORGISTICS MEXICO SA DE CV | E15: 15755.7 | F15: 0 | G15: 0 | H15: 15755.7
... B166: 113 | C166: D | D166: Impuestos a favor | E166: 42278678 | F166: 398077.25 | G166: 223.78 | H166: 42676531
B167: 113-01 | C167: D | D167: IVA a favor | E167: 5997042 | F167: 396693.85 | G167: 0 | H167: 6393735.8 | I167: ='Resumen P.P.'!F64-'Resumen P.P.'!F63 -> 396693.86 | J167: =F167-I167 -> -0.0055064916
B168: 113-02 | C168: D | D168: ISR a favor | E168: 36026668 | F168: 0 | G168: 0 | H168: 36026668
B169: 113-06 | C169: D | D169: Subsidio al empleo | E169: 326.27 | F169: 0 | G169: 0 | H169: 326.27
B170: 113-08 | C170: D | D170: Otros impuestos a favor | E170: 254641.35 | F170: 1705.05 | G170: 223.78 | H170: 256122.62
B171: 114 | C171: D | D171: Pagos provisionales | E171: 7233513 | F171: 0 | G171: 0 | H171: 7233513
B172: 114-01 | C172: D | D172: Pagos provisionales de ISR | E172: 7233513 | F172: 0 | G172: 0 | H172: 7233513
B173: 118 | C173: D | D173: Impuestos acreditables pagados | E173: 6973886 | F173: 613498.86 | G173: 613498.86 | H173: 6973886
B174: 118-01 | C174: D | D174: IVA acreditable pagado | E174: 6972918 | F174: 613498.86 | G174: 613498.86 | H174: 6972918
B175: 118-01-001 | C175: D | D175: IVA TASA 16% | E175: 6969762.9 | F175: 612667.5 | G175: 612667.5 | H175: 6969762.9 | I175: ='Aux. egresos'!AH1001 -> 612667.5 | J175: =G175-I175 -> -0.00079149159
B176: 118-01-002 | C176: D | D176: IVA TASA 8% FRONTERA | E176: 3155.08 | F176: 831.36 | G176: 831.36 | H176: 3155.08 | I176: ='Aux. egresos'!AI1001 -> 831.35787 | J176: =G176-I176 -> 0.002132
B177: 118-03 | C177: D | D177: IEPS acreditable pagado | E177: 967.97 | F177: 0 | G177: 0 | H177: 967.97
B178: 119 | C178: D | D178: Impuestos acreditables por pagar | E178: 2628981.5 | F178: 601222.7 | G178: 613797.14 | H178: 2616407.1
B179: 119-01 | C179: D | D179: IVA pendiente de pago | E179: 2629039.1 | F179: 601219.29 | G179: 613797.14 | H179: 2616461.3
B180: 119-03 | C180: D | D180: IEPS pendiente de pago | E180: -57.58 | F180: 3.41 | G180: 0 | H180: -54.17
B181: 120 | C181: D | D181: Anticipo a proveedores | E181: 552020.89 | F181: 0 | G181: 0 | H181: 552020.89
B182: 120-01 | C182: D | D182: Anticipo a proveedores nacional | E182: 531941.46 | F182: 0 | G182: 0 | H182: 531941.46
B183: 120-01-001 | C183: D | D183: JIMSA TRANSPORTES | E183: 2000 | F183: 0 | G183: 0 | H183: 2000
B184: 120-02 | C184: D | D184: Anticipo a proveedores extranjero | E184: 18079.43 | F184: 0 | G184: 0 | H184: 18079.43
B185: 155 | C185: D | D185: Mobiliario y equipo de oficina | E185: 1586114.8 | F185: 0 | G185: 0 | H185: 1586114.8
B186: 155-01 | C186: D | D186: Mobiliario y equipo de oficina | E186: 1586114.8 | F186: 0 | G186: 0 | H186: 1586114.8
B187: 155-01-001 | C187: D | D187: INVERSION 2016 | E187: 164364.42 | F187: 0 | G187: 0 | H187: 164364.42
B188: 155-01-002 | C188: D | D188: INVERSION 2017 | E188: 4482.76 | F188: 0 | G188: 0 | H188: 4482.76
... B662: 208 | C662: A | D662: Impuestos trasladados cobrados | E662: 2836274.4 | F662: 217126.66 | G662: 216805.01 | H662: 2835952.7
B663: 208-01 | C663: A | D663: IVA trasladado cobrado | E663: 2836274.4 | F663: 216805.01 | G663: 216805.01 | H663: 2836274.3 | I663: ='Aux. ingresos'!AH1005 -> 216805 | J663: =F663-I663 -> 0.006847
B664: 209 | C664: A | D664: Impuestos trasladados no cobrados | E664: 3061310.8 | F664: 215282.33 | G664: 163726.94 | H664: 3009755.4
B665: 209-01 | C665: A | D665: IVA trasladado no cobrado | E665: 3061310.8 | F665: 215282.33 | G665: 163726.94 | H665: 3009755.4
B666: 210 | C666: A | D666: Provisión de sueldos y salarios por pagar | E666: 1887616.6 | F666: 2710743.8 | G666: 2710743.8 | H666: 1887616.6
B667: 210-01 | C667: A | D667: Provisión de sueldos y salarios por pagar | E667: 1887616.6 | F667: 2710743.8 | G667: 2710743.8 | H667: 1887616.6
B668: 211 | C668: A | D668: Provisión de contribuciones de seguridad social por pagar | E668: 685676.85 | F668: 670701.63 | G668: 34133.68 | H668: 49108.9
B669: 211-01 | C669: A | D669: Provisión de IMSS patronal por pagar | E669: -202207.03 | F669: 670701.63 | G669: 0 | H669: -872908.66
B670: 211-02 | C670: A | D670: Provisión de SAR por pagar | E670: 194288.63 | F670: 0 | G670: 0 | H670: 194288.63
B671: 211-03 | C671: A | D671: Provisión de infonavit por pagar | E671: 693595.25 | F671: 0 | G671: 34133.68 | H671: 727728.93
B672: 212 | C672: A | D672: Provisión de impuesto estatal sobre nómina por pagar | E672: 162846.16 | F672: 51465 | G672: 0 | H672: 111381.16
B673: 212-01 | C673: A | D673: Provisión de impuesto estatal sobre nómina por pagar | E673: 162846.16 | F673: 51465 | G673: 0 | H673: 111381.16
B674: 213 | C674: A | D674: Impuestos y derechos por pagar | E674: -121591 | F674: 199863 | G674: 0 | H674: -321454
B675: 213-01 | C675: A | D675: IVA por pagar | E675: -244 | F675: 0 | G675: 0 | H675: -244
... B711: 305-02-001 | C711: A | D711: RESULTADO EJERCICIO 2023 | E711: -20147025 | F711: 0 | G711: 0 | H711: -20147025
B712: 401 | C712: A | D712: Ingresos | E712: 33933781 | F712: 0 | G712: 9538449 | H712: 43472230 | I712: ='FACTURAS INGRESOS'!P719 -> 9538449 | J712: =G712-I712 -> 0.0099999979
B713: 401-01 | C713: A | D713: Ventas y/o servicios gravados a la tasa general | E713: 5705733.3 | F713: 0 | G713: 1023293.4 | H713: 6729026.7
B714: 401-04 | C714: A | D714: Ventas y/o servicios gravados al 0% | E714: 28025041 | F714: 0 | G714: 8515155.6 | H714: 36540197
B715: 401-38 | C715: A | D715: Otros ingresos propios | E715: 203006.37 | F715: 0 | G715: 0.01 | H715: 203006.38
B716: 403 | C716: A | D716: Otros ingresos | E716: 0 | F716: 0 | G716: 0.32 | H716: 0.32
B717: 403-01 | C717: A | D717: Otros Ingresos | E717: 0 | F717: 0 | G717: 0.32 | H717: 0.32
B718: 503 | C718: A | D718: Devoluciones, descuentos o bonificaciones sobre compras | E718: 380558.83 | F718: 0 | G718: 71052.9 | H718: 451611.73
B719: 503-01 | C719: A | D719: Devoluciones, descuentos o bonificaciones sobre compras | E719: 380558.83 | F719: 0 | G719: 71052.9 | H719: 451611.73
B720: 601 | C720: D | D720: Gastos generales | E720: 9046762.1 | F720: 4318529.2 | G720: 0 | H720: 13365291
B721: 601-01 | C721: D | D721: Sueldos y salarios | E721: 8.82 | F721: 3.44 | G721: 0 | H721: 12.26
B722: 601-13 | C722: D | D722: Indemnizaciones | E722: 316412.86 | F722: 410705.66 | G722: 0 | H722: 727118.52
B723: 601-15 | C723: D | D723: Despensa | E723: 0 | F723: 5280.09 | G723: 0 | H723: 5280.09
B724: 601-38 | C724: D | D724: Honorarios a personas morales residentes nacionales | E724: 57899 | F724: 40040 | G724: 0 | H724: 97939
... B789: 899-04 | C789: D | D789: Traspaso Bancario | E789: 0 | F789: 7456000 | G789: 7456000 | H789: 0

Sheet FACTURAS INGRESOS
B2: ENERO
B3: SUCURSAL | C3: AGENTE | D3: T. VENTA | E3: COD. CLIENTE | F3: CLIENTE | G3: COMPROBANTE | H3: FOLIO | I3: UUID | J3: F. EXP. | K3: ESTATUS | L3: METODO PAGO | M3: FORMA PAGO | N3: PLAZO | O3: VENCIMIENTO | P3: SUBTOTAL | Q3: DESCUENTO | R3: % | S3: T. IMPUESTOS | T3: TOTAL | U3: PAGADO | V3: MONEDA | W3: CONTABILIZADA | X3: IVA Tasa 0 | Y3: IVA Tasa 16.00 | Z3: IVA Tasa 0.000000
B4: ND | C4: ND | D4: ND | E4: MILLHOUSE LOGISTICS I.N.C. | F4: MILLHOUSE LOGISTICS I.N.C. | G4: INGRESO | H4: F4137 | I4: BB12FD56-C3FA-43F8-AEB1-F281FEFFDAAD | J4: 2025-01-06 | K4: Vigente | L4: PPD | M4: 99 Por definir | N4: CREDITO: | O4: 2025-01-06 | P4: 3103755 | Q4: 0 | R4: 0 | S4: 0 | T4: 3103755 | U4: 150000 | V4: USD | W4: SI | X4: 0 | Y4: 0 | Z4: 0
B5: ND | C5: ND | D5: ND | E5: BONANZA LOGISTICS | F5: BONANZA LOGISTICS | G5: INGRESO | H5: F4138 | I5: E595447A-7DA6-4613-BE3C-041FAC1C8027 | J5: 2025-01-06 | K5: Vigente | L5: PPD | M5: 99 Por definir | N5: CREDITO: | O5: 2025-01-06 | P5: 31037.55 | Q5: 0 | R5: 0 | S5: 0 | T5: 31037.55 | U5: 0 | V5: USD | W5: SI | X5: 0 | Y5: 0 | Z5: 0
B6: ND | C6: ND | D6: ND | E6: CEVA FREIGHT MANAGEMENT MEXICO | F6: CEVA FREIGHT MANAGEMENT MEXICO | G6: INGRESO | H6: F4139 | I6: 69BB96BF-BF61-4B3C-A69B-CA0DCF8E74C1 | J6: 2025-01-06 | K6: Vigente | L6: PPD | M6: 99 Por definir | N6: CREDITO: | O6: 2025-01-06 | P6: 53800 | Q6: 0 | R6: 0 | S6: 8608 | T6: 62408 | U6: 0 | V6: MXN | W6: SI | X6: 0 | Y6: 8608 | Z6: 0
B7: ND | C7: ND | D7: ND | E7: CEVA FREIGHT MANAGEMENT MEXICO | F7: CEVA FREIGHT MANAGEMENT MEXICO | G7: INGRESO | H7: F4140 | I7: 8269E833-7CFF-4F7D-B280-B858BA05FF90 | J7: 2025-01-06 | K7: Vigente | L7: PPD | M7: 99 Por definir | N7: CREDITO: | O7: 2025-01-06 | P7: 53800 | Q7: 0 | R7: 0 | S7: 8608 | T7: 62408 | U7: 0 | V7: MXN | W7: SI | X7: 0 | Y7: 8608 | Z7: 0
B8: ND | C8: ND | D8: ND | E8: CEVA FREIGHT MANAGEMENT MEXICO | F8: CEVA FREIGHT MANAGEMENT MEXICO | G8: INGRESO | H8: F4141 | I8: 1D173DF4-0AF8-45CF-96FF-57DC9EA6332F | J8: 2025-01-06 | K8: Vigente | L8: PPD | M8: 99 Por definir | N8: CREDITO: | O8: 2025-01-06 | P8: 53800 | Q8: 0 | R8: 0 | S8: 8608 | T8: 62408 | U8: 0 | V8: MXN | W8: SI | X8: 0 | Y8: 8608 | Z8: 0
B9: ND | C9: ND | D9: ND | E9: CHASE PLASTICS DE MEXICO | F9: CHASE PLASTICS DE MEXICO | G9: INGRESO | H9: F4142 | I9: B0824F95-A398-4BA0-A8CD-02140CDC8205 | J9: 2025-01-06 | K9: Vigente | L9: PPD | M9: 99 Por definir | N9: CREDITO: | O9: 2025-01-06 | P9: 9000 | Q9: 0 | R9: 0 | S9: 1440 | T9: 10440 | U9: 0 | V9: MXN | W9: SI | X9: 0 | Y9: 1440 | Z9: 0
B10: ND | C10: ND | D10: ND | E10: CHASE PLASTICS DE MEXICO | F10: CHASE PLASTICS DE MEXICO | G10: INGRESO | H10: F4143 | I10: 9498F893-C0D9-4FC6-A3CF-E944F880BABF | J10: 2025-01-06 | K10: Vigente | L10: PPD | M10: 99 Por definir | N10: CREDITO: | O10: 2025-01-06 | P10: 5000 | Q10: 0 | R10: 0 | S10: 800 | T10: 5800 | U10: 0 | V10: MXN | W10: SI | X10: 0 | Y10: 800 | Z10: 0
B11: ND | C11: ND | D11: ND | E11: DSV ROAD | F11: DSV ROAD | G11: INGRESO | H11: F4144 | I11: F3E7654E-A246-4E56-8E30-252B5EAB1A0E | J11: 2025-01-06 | K11: Vigente | L11: PPD | M11: 99 Por definir | N11: CREDITO: | O11: 2025-01-06 | P11: 70351.78 | Q11: 0 | R11: 0 | S11: 0 | T11: 70351.78 | U11: 0 | V11: USD | W11: SI | X11: 0 | Y11: 0 | Z11: 0
B12: ND | C12: ND | D12: ND | E12: DSV ROAD | F12: DSV ROAD | G12: INGRESO | H12: F4145 | I12: 67456DB2-C78D-48D4-8539-16BCBD26D588 | J12: 2025-01-06 | K12: Vigente | L12: PPD | M12: 99 Por definir | N12: CREDITO: | O12: 2025-01-06 | P12: 95595.65 | Q12: 0 | R12: 0 | S12: 0 | T12: 95595.65 | U12: 0 | V12: USD | W12: SI | X12: 0 | Y12: 0 | Z12: 0
B13: ND | C13: ND | D13: ND | E13: HELLA AUTOMOTIVE MEXICO | F13: HELLA AUTOMOTIVE MEXICO | G13: INGRESO | H13: F4146 | I13: D2846251-2683-494C-B1DC-1DA6617A1A3F | J13: 2025-01-06 | K13: Vigente | L13: PPD | M13: 99 Por definir | N13: CREDITO: | O13: 2025-01-06 | P13: 134496.05 | Q13: 0 | R13: 0 | S13: 0 | T13: 134496.05 | U13: 0 | V13: USD | W13: SI | X13: 0 | Y13: 0 | Z13: 0
B14: ND | C14: ND | D14: ND | E14: HELLA AUTOMOTIVE MEXICO | F14: HELLA AUTOMOTIVE MEXICO | G14: INGRESO | H14: F4147 | I14: 65F6910A-2D12-4DAE-A583-261C65A6482F | J14: 2025-01-06 | K14: Vigente | L14: PPD | M14: 99 Por definir | N14: CREDITO: | O14: 2025-01-06 | P14: 67454.94 | Q14: 0 | R14: 0 | S14: 0 | T14: 67454.94 | U14: 0 | V14: USD | W14: SI | X14: 0 | Y14: 0 | Z14: 0
B15: ND | C15: ND | D15: ND | E15: HELLA AUTOMOTIVE MEXICO | F15: HELLA AUTOMOTIVE MEXICO | G15: INGRESO | H15: F4148 | I15: A7FE29A4-9119-4A9B-B83F-FBB3173228A0 | J15: 2025-01-06 | K15: Vigente | L15: PPD | M15: 99 Por definir | N15: CREDITO: | O15: 2025-01-06 | P15: 64144.27 | Q15: 0 | R15: 0 | S15: 0 | T15: 64144.27 | U15: 0 | V15: USD | W15: SI | X15: 0 | Y15: 0 | Z15: 0
... B21: ND | C21: ND | D21: ND | E21: CLUB TURAVIA | F21: CLUB TURAVIA | G21: INGRESO | H21: F4155 | I21: 48CF9772-11E3-47E3-84A3-B383203A495D | J21: 2025-01-06 | K21: Vigente | L21: PPD | M21: 99 Por definir | N21: CREDITO: | O21: 2025-01-06 | P21: 3488.32 | Q21: 0 | R21: 0 | S21: 558.13 | T21: 4046.45 | U21: 4046.45 | V21: MXN | W21: SI | X21: 0 | Y21: 558.13 | Z21: 0
B22: ND | C22: ND | D22: ND | F22: KASAI MEXICANA | G22: INGRESO | H22: F4156 | I22: A95465C9-BF24-4A7B-97FF-58EE558C9F40 | J22: 2025-01-06 | K22: Vigente | L22: PPD | M22: 99 Por definir | N22: CREDITO: | O22: 2025-01-06 | P22: 97044.07 | Q22: 0 | R22: 0 | S22: 0 | T22: 97044.07 | U22: 0 | V22: USD | W22: SI | X22: 0 | Y22: 0 | Z22: 0
B23: ND | C23: ND | D23: ND | E23: KASAI MEXICANA | F23: KASAI MEXICANA | G23: INGRESO | H23: F4157 | I23: 2971DD0A-7CFD-4F08-96B9-E73348519FC2 | J23: 2025-01-06 | K23: Vigente | L23: PPD | M23: 99 Por definir | N23: CREDITO: | O23: 2025-01-06 | P23: 144014.23 | Q23: 0 | R23: 0 | S23: 0 | T23: 144014.23 | U23: 0 | V23: USD | W23: SI | X23: 0 | Y23: 0 | Z23: 0
B24: ND | C24: ND | D24: ND | F24: KASAI MEXICANA | G24: INGRESO | H24: F4158 | I24: 3D99EAE3-A43D-4194-8EFC-F799EA0EE985 | J24: 2025-01-06 | K24: Vigente | L24: PPD | M24: 99 Por definir | N24: CREDITO: | O24: 2025-01-06 | P24: 84836 | Q24: 0 | R24: 0 | S24: 13573.76 | T24: 98409.76 | U24: 0 | V24: MXN | W24: SI | X24: 0 | Y24: 13573.76 | Z24: 0
B25: ND | C25: ND | D25: ND | F25: KASAI MEXICANA | G25: INGRESO | H25: F4159 | I25: 7C40825D-3A7A-4AB9-BB0D-8538EAEF00FD | J25: 2025-01-06 | K25: Vigente | L25: PPD | M25: 99 Por definir | N25: CREDITO: | O25: 2025-01-06 | P25: 38500 | Q25: 0 | R25: 0 | S25: 6160 | T25: 44660 | U25: 0 | V25: MXN | W25: SI | X25: 0 | Y25: 6160 | Z25: 0
B26: ND | C26: ND | D26: ND | F26: KASAI MEXICANA | G26: INGRESO | H26: F4160 | I26: D9E85B46-95C3-46B5-AD74-0823C70CF6A8 | J26: 2025-01-06 | K26: Vigente | L26: PPD | M26: 99 Por definir | N26: CREDITO: | O26: 2025-01-06 | P26: 80000 | Q26: 0 | R26: 0 | S26: 12800 | T26: 92800 | U26: 0 | V26: MXN | W26: SI | X26: 0 | Y26: 12800 | Z26: 0
B27: ND | C27: ND | D27: ND | E27: MDE TRUCKING | F27: MDE TRUCKING | G27: INGRESO | H27: F4161 | I27: 9EC866F2-D799-4124-9ADC-4BB62482739F | J27: 2025-01-06 | K27: Vigente | L27: PPD | M27: 99 Por definir | N27: CREDITO: | O27: 2025-01-06 | P27: 95181.82 | Q27: 0 | R27: 0 | S27: 0 | T27: 95181.82 | U27: 0 | V27: USD | W27: SI | X27: 0 | Y27: 0 | Z27: 0
B28: ND | C28: ND | D28: ND | E28: MOLEX DE MEXICO GUADALAJARA 2 | F28: MOLEX DE MEXICO GUADALAJARA 2 | G28: INGRESO | H28: F4162 | I28: DC2B4351-B9E7-425B-8BE0-26FB6AE415D4 | J28: 2025-01-06 | K28: Vigente | L28: PPD | M28: 99 Por definir | N28: CREDITO: | O28: 2025-01-06 | P28: 18500 | Q28: 0 | R28: 0 | S28: 2960 | T28: 21460 | U28: 0 | V28: MXN | W28: SI | X28: 0 | Y28: 2960 | Z28: 0
B29: ND | C29: ND | D29: ND | E29: MOLEX DE MEXICO GUADALAJARA 2 | F29: MOLEX DE MEXICO GUADALAJARA 2 | G29: INGRESO | H29: F4163 | I29: D06CACF7-A2FD-41EE-A4CC-9BFAAFBCD206 | J29: 2025-01-06 | K29: Vigente | L29: PPD | M29: 99 Por definir | N29: CREDITO: | O29: 2025-01-06 | P29: 3000 | Q29: 0 | R29: 0 | S29: 480 | T29: 3480 | U29: 0 | V29: MXN | W29: SI | X29: 0 | Y29: 480 | Z29: 0
B30: ND | C30: ND | D30: ND | E30: MOLEX DE MEXICO GUADALAJARA 2 | F30: MOLEX DE MEXICO GUADALAJARA 2 | G30: INGRESO | H30: F4164 | I30: 852800C1-75DF-40E2-861B-B36F65E18099 | J30: 2025-01-06 | K30: Vigente | L30: PPD | M30: 99 Por definir | N30: CREDITO: | O30: 2025-01-06 | P30: 2200 | Q30: 0 | R30: 0 | S30: 352 | T30: 2552 | U30: 0 | V30: MXN | W30: SI | X30: 0 | Y30: 352 | Z30: 0
B31: ND | C31: ND | D31: ND | E31: MOLEX DE MEXICO GUADALAJARA 2 | F31: MOLEX DE MEXICO GUADALAJARA 2 | G31: INGRESO | H31: F4165 | I31: 8E4CDAB7-B4F2-46B7-BC73-FFDC5AEA8AC0 | J31: 2025-01-06 | K31: Vigente | L31: PPD | M31: 99 Por definir | N31: CREDITO: | O31: 2025-01-06 | P31: 25000 | Q31: 0 | R31: 0 | S31: 4000 | T31: 29000 | U31: 0 | V31: MXN | W31: SI | X31: 0 | Y31: 4000 | Z31: 0
B32: ND | C32: ND | D32: ND | E32: PCE PARAGON SOLUTIONS (MEXICO) | F32: PCE PARAGON SOLUTIONS (MEXICO) | G32: INGRESO | H32: F4166 | I32: 94F1DE06-C5B1-49A5-B980-CB63B3DB2097 | J32: 2025-01-06 | K32: Vigente | L32: PPD | M32: 99 Por definir | N32: CREDITO: | O32: 2025-01-06 | P32: 78525 | Q32: 0 | R32: 0 | S32: 0 | T32: 78525 | U32: 0 | V32: USD | W32: SI | X32: 0 | Y32: 0 | Z32: 0
B33: ND | C33: ND | D33: ND | E33: PCE PARAGON SOLUTIONS (MEXICO) | F33: PCE PARAGON SOLUTIONS (MEXICO) | G33: INGRESO | H33: F4167 | I33: 7B5C2AA3-0A9C-4F7E-9852-F77F40A72506 | J33: 2025-01-06 | K33: Vigente | L33: PPD | M33: 99 Por definir | N33: CREDITO: | O33: 2025-01-06 | P33: 78525 | Q33: 0 | R33: 0 | S33: 0 | T33: 78525 | U33: 0 | V33: USD | W33: SI | X33: 0 | Y33: 0 | Z33: 0
B34: ND | C34: ND | D34: ND | E34: PCE PARAGON SOLUTIONS (MEXICO) | F34: PCE PARAGON SOLUTIONS (MEXICO) | G34: INGRESO | H34: F4168 | I34: 79FC58C9-5F0E-4377-8975-BA8D799B3763 | J34: 2025-01-06 | K34: Vigente | L34: PPD | M34: 99 Por definir | N34: CREDITO: | O34: 2025-01-06 | P34: 78525 | Q34: 0 | R34: 0 | S34: 0 | T34: 78525 | U34: 0 | V34: USD | W34: SI | X34: 0 | Y34: 0 | Z34: 0
B35: ND | C35: ND | D35: ND | E35: PCE PARAGON SOLUTIONS (MEXICO) | F35: PCE PARAGON SOLUTIONS (MEXICO) | G35: INGRESO | H35: F4169 | I35: 82E0B2C3-DDE1-44DB-87F6-F57D761B14A5 | J35: 2025-01-06 | K35: Vigente | L35: PPD | M35: 99 Por definir | N35: CREDITO: | O35: 2025-01-06 | P35: 78525 | Q35: 0 | R35: 0 | S35: 0 | T35: 78525 | U35: 0 | V35: USD | W35: SI | X35: 0 | Y35: 0 | Z35: 0
B36: ND | C36: ND | D36: ND | E36: PCE PARAGON SOLUTIONS (MEXICO) | F36: PCE PARAGON SOLUTIONS (MEXICO) | G36: INGRESO | H36: F4170 | I36: C4CCEF46-A4E2-4149-8893-03DA186D0576 | J36: 2025-01-06 | K36: Vigente | L36: PPD | M36: 99 Por definir | N36: CREDITO: | O36: 2025-01-06 | P36: 78525 | Q36: 0 | R36: 0 | S36: 0 | T36: 78525 | U36: 0 | V36: USD | W36: SI | X36: 0 | Y36: 0 | Z36: 0
B37: ND | C37: ND | D37: ND | E37: PCE PARAGON SOLUTIONS (MEXICO) | F37: PCE PARAGON SOLUTIONS (MEXICO) | G37: INGRESO | H37: F4171 | I37: F84E79CF-95D1-437F-AD67-021B3AAF27F4 | J37: 2025-01-06 | K37: Vigente | L37: PPD | M37: 99 Por definir | N37: CREDITO: | O37: 2025-01-06 | P37: 78525 | Q37: 0 | R37: 0 | S37: 0 | T37: 78525 | U37: 0 | V37: USD | W37: SI | X37: 0 | Y37: 0 | Z37: 0
B38: ND | C38: ND | D38: ND | E38: PCE PARAGON SOLUTIONS (MEXICO) | F38: PCE PARAGON SOLUTIONS (MEXICO) | G38: INGRESO | H38: F4172 | I38: C1575204-335D-42C7-B329-0B298C5B392E | J38: 2025-01-06 | K38: Vigente | L38: PPD | M38: 99 Por definir | N38: CREDITO: | O38: 2025-01-06 | P38: 78525 | Q38: 0 | R38: 0 | S38: 0 | T38: 78525 | U38: 0 | V38: USD | W38: SI | X38: 0 | Y38: 0 | Z38: 0
B39: ND | C39: ND | D39: ND | E39: SEA CARGO LOGISTICS | F39: SEA CARGO LOGISTICS | G39: INGRESO | H39: F4173 | I39: 8DD3F855-232A-4D2C-BD59-061C5B547BC2 | J39: 2025-01-06 | K39: Vigente | L39: PPD | M39: 99 Por definir | N39: CREDITO: | O39: 2025-01-06 | P39: 11794.27 | Q39: 0 | R39: 0 | S39: 0 | T39: 11794.27 | U39: 570 | V39: USD | W39: SI | X39: 0 | Y39: 0 | Z39: 0
B40: ND | C40: ND | D40: ND | F40: SEA CARGO LOGISTICS | G40: INGRESO | H40: F4174 | I40: 57595518-C9BE-4C23-BBC0-6A985DFA2D17 | J40: 2025-01-06 | K40: Vigente | L40: PPD | M40: 99 Por definir | N40: CREDITO: | O40: 2025-01-06 | P40: 127253.96 | Q40: 0 | R40: 0 | S40: 0 | T40: 127253.96 | U40: 6150 | V40: USD | W40: SI | X40: 0 | Y40: 0 | Z40: 0
B41: ND | C41: ND | D41: ND | E41: SEA CARGO LOGISTICS | F41: SEA CARGO LOGISTICS | G41: INGRESO | H41: F4175 | I41: 2313AD56-2873-4162-ACDE-19B5FA31EA83 | J41: 2025-01-06 | K41: Vigente | L41: PPD | M41: 99 Por definir | N41: CREDITO: | O41: 2025-01-06 | P41: 194501.98 | Q41: 0 | R41: 0 | S41: 0 | T41: 194501.98 | U41: 0 | V41: USD | W41: SI | X41: 0 | Y41: 0 | Z41: 0
B42: ND | C42: ND | D42: ND | E42: SEA CARGO LOGISTICS | F42: SEA CARGO LOGISTICS | G42: INGRESO | H42: F4176 | I42: C0D0C4A0-AA0E-43A4-95F3-F3ACA9E1A793 | J42: 2025-01-06 | K42: Vigente | L42: PPD | M42: 99 Por definir | N42: CREDITO: | O42: 2025-01-06 | P42: 127253.96 | Q42: 0 | R42: 0 | S42: 0 | T42: 127253.96 | U42: 6150 | V42: USD | W42: SI | X42: 0 | Y42: 0 | Z42: 0
B43: ND | C43: ND | D43: ND | E43: SEA CARGO LOGISTICS | F43: SEA CARGO LOGISTICS | G43: INGRESO | H43: F4177 | I43: D01002B3-7BF2-44F5-A1F4-44D4A6ADDBD2 | J43: 2025-01-06 | K43: Vigente | L43: PPD | M43: 99 Por definir | N43: CREDITO: | O43: 2025-01-06 | P43: 127253.96 | Q43: 0 | R43: 0 | S43: 0 | T43: 127253.96 | U43: 0 | V43: USD | W43: SI | X43: 0 | Y43: 0 | Z43: 0
B44: ND | C44: ND | D44: ND | E44: SEA CARGO LOGISTICS | F44: SEA CARGO LOGISTICS | G44: INGRESO | H44: F4178 | I44: 5712BFD0-CE53-4C11-8395-9869A04D2530 | J44: 2025-01-06 | K44: Vigente | L44: PPD | M44: 99 Por definir | N44: CREDITO: | O44: 2025-01-06 | P44: 127253.96 | Q44: 0 | R44: 0 | S44: 0 | T44: 127253.96 | U44: 0 | V44: USD | W44: SI | X44: 0 | Y44: 0 | Z44: 0
B45: ND | C45: ND | D45: ND | E45: UNIVERSAL SCIENTIFIC INDUSTRIAL DE MEXICO | F45: UNIVERSAL SCIENTIFIC INDUSTRIAL DE MEXICO | G45: INGRESO | H45: F4179 | I45: 643B7E7F-5731-440F-BAAC-086BB766E1BE | J45: 2025-01-06 | K45: Vigente | L45: PPD | M45: 99 Por definir | N45: CREDITO: | O45: 2025-01-06 | P45: 129323.13 | Q45: 0 | R45: 0 | S45: 0 | T45: 129323.13 | U45: 0 | V45: USD | W45: SI | X45: 0 | Y45: 0 | Z45: 0
B46: ND | C46: ND | D46: ND | E46: CEVA FREIGHT MANAGEMENT MEXICO | F46: CEVA FREIGHT MANAGEMENT MEXICO | G46: INGRESO | H46: F4180 | I46: D73B390F-9290-480C-81BB-28DB64E05D9D | J46: 2025-01-06 | K46: Vigente | L46: PPD | M46: 99 Por definir | N46: CREDITO: | O46: 2025-01-06 | P46: 53800 | Q46: 0 | R46: 0 | S46: 8608 | T46: 62408 | U46: 0 | V46: MXN | W46: SI | X46: 0 | Y46: 8608 | Z46: 0
B47: ND | C47: ND | D47: ND | E47: CEVA FREIGHT MANAGEMENT MEXICO | F47: CEVA FREIGHT MANAGEMENT MEXICO | G47: INGRESO | H47: F4181 | I47: E9D08585-EEF8-47FB-984E-6E346A02D06C | J47: 2025-01-06 | K47: Vigente | L47: PPD | M47: 99 Por definir | N47: CREDITO: | O47: 2025-01-06 | P47: 53800 | Q47: 0 | R47: 0 | S47: 8608 | T47: 62408 | U47: 0 | V47: MXN | W47: SI | X47: 0 | Y47: 8608 | Z47: 0
B48: ND | C48: ND | D48: ND | E48: CEVA FREIGHT MANAGEMENT MEXICO | F48: CEVA FREIGHT MANAGEMENT MEXICO | G48: INGRESO | H48: F4182 | I48: 72CF9370-1A82-4690-80B8-804849EFD317 | J48: 2025-01-06 | K48: Vigente | L48: PPD | M48: 99 Por definir | N48: CREDITO: | O48: 2025-01-06 | P48: 53800 | Q48: 0 | R48: 0 | S48: 8608 | T48: 62408 | U48: 0 | V48: MXN | W48: SI | X48: 0 | Y48: 8608 | Z48: 0
B49: ND | C49: ND | D49: ND | E49: CHASE PLASTICS DE MEXICO | F49: CHASE PLASTICS DE MEXICO | G49: INGRESO | H49: F4183 | I49: 8F0E0C14-2960-4F8F-8DE7-A6C85A5FF911 | J49: 2025-01-06 | K49: Vigente | L49: PPD | M49: 99 Por definir | N49: CREDITO: | O49: 2025-01-06 | P49: 16000 | Q49: 0 | R49: 0 | S49: 2560 | T49: 18560 | U49: 0 | V49: MXN | W49: SI | X49: 0 | Y49: 2560 | Z49: 0
B50: ND | C50: ND | D50: ND | E50: CHASE PLASTICS DE MEXICO | F50: CHASE PLASTICS DE MEXICO | G50: INGRESO | H50: F4184 | I50: 08797CEC-C8B4-4E0A-ACAB-B20C2C5F6524 | J50: 2025-01-06 | K50: Vigente | L50: PPD | M50: 99 Por definir | N50: CREDITO: | O50: 2025-01-06 | P50: 16000 | Q50: 0 | R50: 0 | S50: 2560 | T50: 18560 | U50: 0 | V50: MXN | W50: SI | X50: 0 | Y50: 2560 | Z50: 0
B51: ND | C51: ND | D51: ND | E51: CONTINENTAL AUTOMOTIVE GUADALAJARA MEXICO | F51: CONTINENTAL AUTOMOTIVE GUADALAJARA MEXICO | G51: INGRESO | H51: F4185 | I51: 6D9E1E13-9336-436C-854F-AB2050F81416 | J51: 2025-01-06 | K51: Vigente | L51: PPD | M51: 99 Por definir | N51: CREDITO: | O51: 2025-01-06 | P51: 840 | Q51: 0 | R51: 0 | S51: 134.4 | T51: 974.4 | U51: 0 | V51: MXN | W51: SI | X51: 0 | Y51: 134.4 | Z51: 0
B52: ND | C52: ND | D52: ND | E52: CONTINENTAL AUTOMOTIVE GUADALAJARA MEXICO | F52: CONTINENTAL AUTOMOTIVE GUADALAJARA MEXICO | G52: INGRESO | H52: F4186 | I52: 203790C7-2F8C-4707-A01F-D3A114D48CE3 | J52: 2025-01-06 | K52: Vigente | L52: PPD | M52: 99 Por definir | N52: CREDITO: | O52: 2025-01-06 | P52: 340 | Q52: 0 | R52: 0 | S52: 54.4 | T52: 394.4 | U52: 0 | V52: MXN | W52: SI | X52: 0 | Y52: 54.4 | Z52: 0
... B155: ND | C155: ND | D155: ND | E155: FAURECIA SISTEMAS AUTOMOTRICES DE MEXICO | F155: FAURECIA SISTEMAS AUTOMOTRICES DE MEXICO | G155: INGRESO | H155: 770 | I155: 334F5072-FBA4-4D03-8591-52533CBC1089 | J155: 2025-01-14 | K155: Vigente | L155: PPD | M155: 99 Por definir | N155: CREDITO: | O155: 2025-01-14 | P155: 30021.52 | Q155: 0 | R155: 0 | S155: 0 | T155: 30021.52 | U155: 0 | V155: USD | W155: SI | X155: 0 | Y155: 0 | Z155: 0
B156: ND | C156: ND | D156: ND | F156: KASAI MEXICANA | G156: INGRESO | H156: F4232 | I156: 4C45C04E-EB66-4E86-8FEB-CDCBCA586282 | J156: 2025-01-17 | K156: Vigente | L156: PPD | M156: 99 Por definir | N156: CREDITO: | O156: 2025-01-17 | P156: 13890.53 | Q156: 0 | R156: 0 | S156: 0 | T156: 13890.53 | U156: 0 | V156: USD | W156: SI | X156: 0 | Y156: 0 | Z156: 0
B157: ND | C157: ND | D157: ND | E157: KASAI MEXICANA | F157: KASAI MEXICANA | G157: INGRESO | H157: F4233 | I157: E1A66B2B-01A1-4E1C-9C10-06D4E10F573C | J157: 2025-01-17 | K157: Vigente | L157: PPD | M157: 99 Por definir | N157: CREDITO: | O157: 2025-01-17 | P157: 97520.5 | Q157: 0 | R157: 0 | S157: 0 | T157: 97520.5 | U157: 0 | V157: USD | W157: SI | X157: 0 | Y157: 0 | Z157: 0
B158: ND | C158: ND | D158: ND | E158: KASAI MEXICANA | F158: KASAI MEXICANA | G158: INGRESO | H158: F4234 | I158: 4017AA82-74A9-4893-9498-1A00B6639948 | J158: 2025-01-17 | K158: Vigente | L158: PPD | M158: 99 Por definir | N158: CREDITO: | O158: 2025-01-17 | P158: 180290 | Q158: 0 | R158: 0 | S158: 0 | T158: 180290 | U158: 0 | V158: USD | W158: SI | X158: 0 | Y158: 0 | Z158: 0
B159: ND | C159: ND | D159: ND | E159: KASAI MEXICANA | F159: KASAI MEXICANA | G159: INGRESO | H159: F4235 | I159: 79EA5DEF-0223-4048-A751-6A61D357BFFA | J159: 2025-01-17 | K159: Vigente | L159: PPD | M159: 99 Por definir | N159: CREDITO: | O159: 2025-01-17 | P159: 180290 | Q159: 0 | R159: 0 | S159: 0 | T159: 180290 | U159: 0 | V159: USD | W159: SI | X159: 0 | Y159: 0 | Z159: 0
B160: ND | C160: ND | D160: ND | E160: KASAI MEXICANA | F160: KASAI MEXICANA | G160: INGRESO | H160: F4236 | I160: 369AE3C4-194A-4178-B40B-8D9A2C084350 | J160: 2025-01-17 | K160: Vigente | L160: PPD | M160: 99 Por definir | N160: CREDITO: | O160: 2025-01-17 | P160: 177831.5 | Q160: 0 | R160: 0 | S160: 0 | T160: 177831.5 | U160: 0 | V160: USD | W160: SI | X160: 0 | Y160: 0 | Z160: 0
B161: ND | C161: ND | D161: ND | E161: KASAI MEXICANA | F161: KASAI MEXICANA | G161: INGRESO | H161: F4237 | I161: 2E416BC0-31E2-4715-86D6-2299799BECEF | J161: 2025-01-17 | K161: Vigente | L161: PPD | M161: 99 Por definir | N161: CREDITO: | O161: 2025-01-17 | P161: 164104.88 | Q161: 0 | R161: 0 | S161: 0 | T161: 164104.88 | U161: 0 | V161: USD | W161: SI | X161: 0 | Y161: 0 | Z161: 0
B162: ND | C162: ND | D162: ND | E162: KASAI MEXICANA | F162: KASAI MEXICANA | G162: INGRESO | H162: F4238 | I162: 685AC22E-5956-419A-B074-5AC08937086A | J162: 2025-01-17 | K162: Vigente | L162: PPD | M162: 99 Por definir | N162: CREDITO: | O162: 2025-01-17 | P162: 144949.06 | Q162: 0 | R162: 0 | S162: 0 | T162: 144949.06 | U162: 0 | V162: USD | W162: SI | X162: 0 | Y162: 0 | Z162: 0
B163: ND | C163: ND | D163: ND | E163: KASAI MEXICANA | F163: KASAI MEXICANA | G163: INGRESO | H163: F4239 | I163: A32310BB-ED59-439F-AF56-45FB222247A5 | J163: 2025-01-17 | K163: Vigente | L163: PPD | M163: 99 Por definir | N163: CREDITO: | O163: 2025-01-17 | P163: 131529.75 | Q163: 0 | R163: 0 | S163: 0 | T163: 131529.75 | U163: 0 | V163: USD | W163: SI | X163: 0 | Y163: 0 | Z163: 0
B164: ND | C164: ND | D164: ND | E164: KASAI MEXICANA | F164: KASAI MEXICANA | G164: INGRESO | H164: F4240 | I164: E1FED16B-E0C0-419D-8FD0-0E1F2EED0FE8 | J164: 2025-01-17 | K164: Vigente | L164: PPD | M164: 99 Por definir | N164: CREDITO: | O164: 2025-01-17 | P164: 133271.19 | Q164: 0 | R164: 0 | S164: 0 | T164: 133271.19 | U164: 0 | V164: USD | W164: SI | X164: 0 | Y164: 0 | Z164: 0
B165: ND | C165: ND | D165: ND | E165: KASAI MEXICANA | F165: KASAI MEXICANA | G165: INGRESO | H165: F4241 | I165: 037F4507-E8F8-489D-AB93-42A7E365B0F0 | J165: 2025-01-17 | K165: Vigente | L165: PPD | M165: 99 Por definir | N165: CREDITO: | O165: 2025-01-17 | P165: 93218.13 | Q165: 0 | R165: 0 | S165: 0 | T165: 93218.13 | U165: 0 | V165: USD | W165: SI | X165: 0 | Y165: 0 | Z165: 0
B166: ND | C166: ND | D166: ND | E166: KASAI MEXICANA | F166: KASAI MEXICANA | G166: INGRESO | H166: F4242 | I166: 979AE270-9295-4873-A40C-6C9B7B334A3E | J166: 2025-01-17 | K166: Vigente | L166: PPD | M166: 99 Por definir | N166: CREDITO: | O166: 2025-01-17 | P166: 80925.63 | Q166: 0 | R166: 0 | S166: 0 | T166: 80925.63 | U166: 0 | V166: USD | W166: SI | X166: 0 | Y166: 0 | Z166: 0
B167: ND | C167: ND | D167: ND | E167: KASAI MEXICANA | F167: KASAI MEXICANA | G167: INGRESO | H167: F4243 | I167: 33ADBA7A-9584-460B-88DB-8874B2EE627A | J167: 2025-01-17 | K167: Vigente | L167: PPD | M167: 99 Por definir | N167: CREDITO: | O167: 2025-01-17 | P167: 46699.21 | Q167: 0 | R167: 0 | S167: 0 | T167: 46699.21 | U167: 0 | V167: USD | W167: SI | X167: 0 | Y167: 0 | Z167: 0
B168: ND | C168: ND | D168: ND | E168: KASAI MEXICANA | F168: KASAI MEXICANA | G168: INGRESO | H168: F4244 | I168: 7004B92C-444D-4923-BC85-16C00FAFF7CE | J168: 2025-01-17 | K168: Vigente | L168: PPD | M168: 99 Por definir | N168: CREDITO: | O168: 2025-01-17 | P168: 88403.56 | Q168: 0 | R168: 0 | S168: 0 | T168: 88403.56 | U168: 0 | V168: USD | W168: SI | X168: 0 | Y168: 0 | Z168: 0
... B184: ND | C184: ND | D184: ND | E184: KASAI MEXICANA | F184: KASAI MEXICANA | G184: INGRESO | H184: F4261 | I184: 0D00D9AB-B825-4351-AF47-9AD9D30ACC85 | J184: 2025-01-20 | K184: Vigente | L184: PPD | M184: 99 Por definir | N184: CREDITO: | O184: 2025-01-20 | P184: 116329.92 | Q184: 0 | R184: 0 | S184: 0 | T184: 116329.92 | U184: 0 | V184: USD | W184: SI | X184: 0 | Y184: 0 | Z184: 0
B185: ND | C185: ND | D185: ND | F185: SEA CARGO LOGISTICS | G185: INGRESO | H185: F4263 | I185: BB83FA48-94C1-42A2-9FC1-9730F2AAAC0B | J185: 2025-01-20 | K185: Vigente | L185: PPD | M185: 99 Por definir | N185: CREDITO: | O185: 2025-01-20 | P185: 125324.72 | Q185: 0 | R185: 0 | S185: 0 | T185: 125324.72 | U185: 0 | V185: USD | W185: SI | X185: 0 | Y185: 0 | Z185: 0
B186: ND | C186: ND | D186: ND | F186: SEA CARGO LOGISTICS | G186: INGRESO | H186: F4264 | I186: 72846C1A-D8A7-4D45-AFE3-6F02AAAC1895 | J186: 2025-01-20 | K186: Vigente | L186: PPD | M186: 99 Por definir | N186: CREDITO: | O186: 2025-01-20 | P186: 125324.72 | Q186: 0 | R186: 0 | S186: 0 | T186: 125324.72 | U186: 0 | V186: USD | W186: SI | X186: 0 | Y186: 0 | Z186: 0
B187: ND | C187: ND | D187: ND | E187: KASAI MEXICANA | F187: KASAI MEXICANA | G187: INGRESO | H187: F4265 | I187: CB5989DE-DB42-4AA6-9D4C-4EDD5DA77D5E | J187: 2025-01-21 | K187: Vigente | L187: PPD | M187: 99 Por definir | N187: CREDITO: | O187: 2025-01-21 | P187: 61428.87 | Q187: 0 | R187: 0 | S187: 0 | T187: 61428.87 | U187: 0 | V187: USD | W187: SI | X187: 0 | Y187: 0 | Z187: 0
B188: ND | C188: ND | D188: ND | E188: BONANZA LOGISTICS | F188: BONANZA LOGISTICS | G188: INGRESO | H188: F4266 | I188: 3DBAF1DF-5CC6-49C6-A072-811C1402D4D9 | J188: 2025-01-21 | K188: Vigente | L188: PPD | M188: 99 Por definir | N188: CREDITO: | O188: 2025-01-21 | P188: 42471.9 | Q188: 0 | R188: 0 | S188: 0 | T188: 42471.9 | U188: 0 | V188: USD | W188: SI | X188: 0 | Y188: 0 | Z188: 0
B189: ND | C189: ND | D189: ND | E189: CHASE PLASTICS DE MEXICO | F189: CHASE PLASTICS DE MEXICO | G189: INGRESO | H189: F4267 | I189: E62B0FF4-E207-43BF-A85C-F35767F8AC4F | J189: 2025-01-21 | K189: Vigente | L189: PPD | M189: 99 Por definir | N189: CREDITO: | O189: 2025-01-21 | P189: 26000 | Q189: 0 | R189: 0 | S189: 4160 | T189: 30160 | U189: 0 | V189: MXN | W189: SI | X189: 0 | Y189: 4160 | Z189: 0
B190: ND | C190: ND | D190: ND | E190: CHASE PLASTICS DE MEXICO | F190: CHASE PLASTICS DE MEXICO | G190: INGRESO | H190: F4268 | I190: AE0D0CC0-D306-4614-8CC2-639892585FC4 | J190: 2025-01-21 | K190: Vigente | L190: PPD | M190: 99 Por definir | N190: CREDITO: | O190: 2025-01-21 | P190: 15900 | Q190: 0 | R190: 0 | S190: 2544 | T190: 18444 | U190: 0 | V190: MXN | W190: SI | X190: 0 | Y190: 2544 | Z190: 0
B191: ND | C191: ND | D191: ND | E191: CHASE PLASTICS DE MEXICO | F191: CHASE PLASTICS DE MEXICO | G191: INGRESO | H191: F4269 | I191: 9A75440E-727C-46D3-A559-13D1597B526A | J191: 2025-01-21 | K191: Vigente | L191: PPD | M191: 99 Por definir | N191: CREDITO: | O191: 2025-01-21 | P191: 13500 | Q191: 0 | R191: 0 | S191: 2160 | T191: 15660 | U191: 0 | V191: MXN | W191: SI | X191: 0 | Y191: 2160 | Z191: 0
B192: ND | C192: ND | D192: ND | E192: DESCOMAR | F192: DESCOMAR | G192: INGRESO | H192: F4270 | I192: 9274C59F-6262-4206-954F-160D8BC00970 | J192: 2025-01-21 | K192: Vigente | L192: PPD | M192: 99 Por definir | N192: CREDITO: | O192: 2025-01-21 | P192: 128451.6 | Q192: 0 | R192: 0 | S192: 0 | T192: 128451.6 | U192: 0 | V192: USD | W192: SI | X192: 0 | Y192: 0 | Z192: 0
B193: ND | C193: ND | D193: ND | E193: PCE PARAGON SOLUTIONS (MEXICO) | F193: PCE PARAGON SOLUTIONS (MEXICO) | G193: INGRESO | H193: F4271 | I193: 805296F8-370B-4802-BF4A-B841B629637D | J193: 2025-01-21 | K193: Vigente | L193: PPD | M193: 99 Por definir | N193: CREDITO: | O193: 2025-01-21 | P193: 78624.81 | Q193: 0 | R193: 0 | S193: 0 | T193: 78624.81 | U193: 0 | V193: USD | W193: SI | X193: 0 | Y193: 0 | Z193: 0
B194: ND | C194: ND | D194: ND | F194: SEA CARGO LOGISTICS | G194: INGRESO | H194: F4272 | I194: 3906A3FC-0E9D-48E5-AEA9-08E70BF32836 | J194: 2025-01-21 | K194: Vigente | L194: PPD | M194: 99 Por definir | N194: CREDITO: | O194: 2025-01-21 | P194: 124991.69 | Q194: 0 | R194: 0 | S194: 0 | T194: 124991.69 | U194: 0 | V194: USD | W194: SI | X194: 0 | Y194: 0 | Z194: 0
B195: ND | C195: ND | D195: ND | E195: CHASE PLASTICS DE MEXICO | F195: CHASE PLASTICS DE MEXICO | G195: INGRESO | H195: F4273 | I195: 72FAD197-F8FC-4BFC-BB7C-761B1CF1C0F9 | J195: 2025-01-22 | K195: Vigente | L195: PPD | M195: 99 Por definir | N195: CREDITO: | O195: 2025-01-22 | P195: 16000 | Q195: 0 | R195: 0 | S195: 2560 | T195: 18560 | U195: 0 | V195: MXN | W195: SI | X195: 0 | Y195: 2560 | Z195: 0
B196: ND | C196: ND | D196: ND | E196: CHASE PLASTICS DE MEXICO | F196: CHASE PLASTICS DE MEXICO | G196: INGRESO | H196: F4274 | I196: 70674272-6CA0-431A-8928-7615F07903BD | J196: 2025-01-22 | K196: Vigente | L196: PPD | M196: 99 Por definir | N196: CREDITO: | O196: 2025-01-22 | P196: 16000 | Q196: 0 | R196: 0 | S196: 2560 | T196: 18560 | U196: 0 | V196: MXN | W196: SI | X196: 0 | Y196: 2560 | Z196: 0
B197: ND | C197: ND | D197: ND | E197: JABIL EMS SWITZERLAND | F197: JABIL EMS SWITZERLAND | G197: INGRESO | H197: F4275 | I197: C8FD5F9E-5C79-4CF6-BFDE-5F3C003BD5E9 | J197: 2025-01-22 | K197: Vigente | L197: PPD | M197: 99 Por definir | N197: CREDITO: | O197: 2025-01-22 | P197: 2684970.1 | Q197: 0 | R197: 0 | S197: 0 | T197: 2684970.1 | U197: 0 | V197: USD | W197: SI | X197: 0 | Y197: 0 | Z197: 0
B198: ND | C198: ND | D198: ND | E198: KASAI MEXICANA | F198: KASAI MEXICANA | G198: INGRESO | H198: F4276 | I198: 7844067C-18BC-46EC-BF1B-7467173C35B7 | J198: 2025-01-22 | K198: Vigente | L198: PPD | M198: 99 Por definir | N198: CREDITO: | O198: 2025-01-22 | P198: 63683.3 | Q198: 0 | R198: 0 | S198: 0 | T198: 63683.3 | U198: 0 | V198: USD | W198: SI | X198: 0 | Y198: 0 | Z198: 0
B199: ND | C199: ND | D199: ND | E199: KASAI MEXICANA | F199: KASAI MEXICANA | G199: INGRESO | H199: F4277 | I199: 58236422-D427-4889-ABCC-E1658CEBC7B6 | J199: 2025-01-22 | K199: Vigente | L199: PPD | M199: 99 Por definir | N199: CREDITO: | O199: 2025-01-22 | P199: 38500 | Q199: 0 | R199: 0 | S199: 6160 | T199: 44660 | U199: 0 | V199: MXN | W199: SI | X199: 0 | Y199: 6160 | Z199: 0
B200: ND | C200: ND | D200: ND | E200: MOLEX DE MEXICO GUADALAJARA 2 | F200: MOLEX DE MEXICO GUADALAJARA 2 | G200: INGRESO | H200: F4278 | I200: 46D0A1FE-ABAC-4BA3-A156-BA4D3CF3EBA5 | J200: 2025-01-22 | K200: Vigente | L200: PPD | M200: 99 Por definir | N200: CREDITO: | O200: 2025-01-22 | P200: 3500 | Q200: 0 | R200: 0 | S200: 560 | T200: 4060 | U200: 0 | V200: MXN | W200: SI | X200: 0 | Y200: 560 | Z200: 0
B201: ND | C201: ND | D201: ND | E201: MOLEX DE MEXICO GUADALAJARA 2 | F201: MOLEX DE MEXICO GUADALAJARA 2 | G201: INGRESO | H201: F4279 | I201: 49D99892-C7D0-403D-9ADC-A4C28EC91994 | J201: 2025-01-22 | K201: Vigente | L201: PPD | M201: 99 Por definir | N201: CREDITO: | O201: 2025-01-22 | P201: 25000 | Q201: 0 | R201: 0 | S201: 4000 | T201: 29000 | U201: 0 | V201: MXN | W201: SI | X201: 0 | Y201: 4000 | Z201: 0
B202: ND | C202: ND | D202: ND | E202: SEA CARGO LOGISTICS | F202: SEA CARGO LOGISTICS | G202: INGRESO | H202: F4281 | I202: 7307C5C3-B910-4BA3-AD24-2A4877EB588B | J202: 2025-01-22 | K202: Vigente | L202: PPD | M202: 99 Por definir | N202: CREDITO: | O202: 2025-01-22 | P202: 123935.92 | Q202: 0 | R202: 0 | S202: 0 | T202: 123935.92 | U202: 0 | V202: USD | W202: SI | X202: 0 | Y202: 0 | Z202: 0
B203: ND | C203: ND | D203: ND | F203: SEA CARGO LOGISTICS | G203: INGRESO | H203: F4282 | I203: 5CEBBF84-E0CD-48FB-850D-688BEF4BA73F | J203: 2025-01-22 | K203: Vigente | L203: PPD | M203: 99 Por definir | N203: CREDITO: | O203: 2025-01-22 | P203: 123935.92 | Q203: 0 | R203: 0 | S203: 0 | T203: 123935.92 | U203: 0 | V203: USD | W203: SI | X203: 0 | Y203: 0 | Z203: 0
B204: ND | C204: ND | D204: ND | F204: SEA CARGO LOGISTICS | G204: INGRESO | H204: F4283 | I204: 226E7E1F-1741-4066-98D5-E2F261755263 | J204: 2025-01-22 | K204: Vigente | L204: PPD | M204: 99 Por definir | N204: CREDITO: | O204: 2025-01-22 | P204: 123935.92 | Q204: 0 | R204: 0 | S204: 0 | T204: 123935.92 | U204: 0 | V204: USD | W204: SI | X204: 0 | Y204: 0 | Z204: 0
B205: ND | C205: ND | D205: ND | F205: SEA CARGO LOGISTICS | G205: INGRESO | H205: F4284 | I205: A417ED2F-454E-4CDC-8334-FF72DAF8A86F | J205: 2025-01-22 | K205: Vigente | L205: PPD | M205: 99 Por definir | N205: CREDITO: | O205: 2025-01-22 | P205: 123935.92 | Q205: 0 | R205: 0 | S205: 0 | T205: 123935.92 | U205: 0 | V205: USD | W205: SI | X205: 0 | Y205: 0 | Z205: 0
B206: ND | C206: ND | D206: ND | F206: SEA CARGO LOGISTICS | G206: INGRESO | H206: F4285 | I206: E48EF40A-0207-416E-B09E-76FD8240F20F | J206: 2025-01-22 | K206: Vigente | L206: PPD | M206: 99 Por definir | N206: CREDITO: | O206: 2025-01-22 | P206: 88334.9 | Q206: 0 | R206: 0 | S206: 0 | T206: 88334.9 | U206: 0 | V206: USD | W206: SI | X206: 0 | Y206: 0 | Z206: 0
B207: ND | C207: ND | D207: ND | E207: CEVA FREIGHT MANAGEMENT MEXICO | F207: CEVA FREIGHT MANAGEMENT MEXICO | G207: INGRESO | H207: F4287 | I207: FFC9DAA4-12D2-4AEB-9AAC-F93C05D895C7 | J207: 2025-01-24 | K207: Vigente | L207: PPD | M207: 99 Por definir | N207: CREDITO: | O207: 2025-01-24 | P207: 53800 | Q207: 0 | R207: 0 | S207: 8608 | T207: 62408 | U207: 0 | V207: MXN | W207: SI | X207: 0 | Y207: 8608 | Z207: 0
B208: ND | C208: ND | D208: ND | E208: CEVA FREIGHT MANAGEMENT MEXICO | F208: CEVA FREIGHT MANAGEMENT MEXICO | G208: INGRESO | H208: F4288 | I208: 4FDD653F-91E4-4EDD-8D8F-DD354644765F | J208: 2025-01-24 | K208: Vigente | L208: PPD | M208: 99 Por definir | N208: CREDITO: | O208: 2025-01-24 | P208: 53800 | Q208: 0 | R208: 0 | S208: 8608 | T208: 62408 | U208: 0 | V208: MXN | W208: SI | X208: 0 | Y208: 8608 | Z208: 0
B209: ND | C209: ND | D209: ND | E209: CEVA FREIGHT MANAGEMENT MEXICO | F209: CEVA FREIGHT MANAGEMENT MEXICO | G209: INGRESO | H209: F4289 | I209: 46048474-3DBA-447A-95A6-E98A5FC1AB89 | J209: 2025-01-24 | K209: Vigente | L209: PPD | M209: 99 Por definir | N209: CREDITO: | O209: 2025-01-24 | P209: 53800 | Q209: 0 | R209: 0 | S209: 8608 | T209: 62408 | U209: 0 | V209: MXN | W209: SI | X209: 0 | Y209: 8608 | Z209: 0
B210: ND | C210: ND | D210: ND | E210: KASAI MEXICANA | F210: KASAI MEXICANA | G210: INGRESO | H210: F4290 | I210: 0FAB5FE0-7BCE-4D67-9EFF-09412F5C5B75 | J210: 2025-01-24 | K210: Vigente | L210: PPD | M210: 99 Por definir | N210: CREDITO: | O210: 2025-01-24 | P210: 34917.49 | Q210: 0 | R210: 0 | S210: 0 | T210: 34917.49 | U210: 0 | V210: USD | W210: SI | X210: 0 | Y210: 0 | Z210: 0
B211: ND | C211: ND | D211: ND | E211: KASAI MEXICANA | F211: KASAI MEXICANA | G211: INGRESO | H211: F4291 | I211: 4CA13981-4771-484F-A423-85B57F7E750E | J211: 2025-01-24 | K211: Vigente | L211: PPD | M211: 99 Por definir | N211: CREDITO: | O211: 2025-01-24 | P211: 63673.07 | Q211: 0 | R211: 0 | S211: 0 | T211: 63673.07 | U211: 0 | V211: USD | W211: SI | X211: 0 | Y211: 0 | Z211: 0
B212: ND | C212: ND | D212: ND | E212: KASAI MEXICANA | F212: KASAI MEXICANA | G212: INGRESO | H212: F4292 | I212: E1789A23-DEE2-4775-8F85-CD02753CA297 | J212: 2025-01-24 | K212: Vigente | L212: PPD | M212: 99 Por definir | N212: CREDITO: | O212: 2025-01-24 | P212: 1845089.5 | Q212: 0 | R212: 0 | S212: 295214.23 | T212: 2140303.7 | U212: 0 | V212: USD | W212: SI | X212: 0 | Y212: 14372.86 | Z212: 0
B213: ND | C213: ND | D213: ND | F213: SEA CARGO LOGISTICS | G213: INGRESO | H213: F4293 | I213: ED85300C-FDB5-48AC-B2BB-E0F33F20C1D9 | J213: 2025-01-24 | K213: Vigente | L213: PPD | M213: 99 Por definir | N213: CREDITO: | O213: 2025-01-24 | P213: 128845.54 | Q213: 0 | R213: 0 | S213: 0 | T213: 128845.54 | U213: 0 | V213: USD | W213: SI | X213: 0 | Y213: 0 | Z213: 0
B214: ND | C214: ND | D214: ND | E214: MONRO LOGISTIC GROUP | F214: MONRO LOGISTIC GROUP | G214: INGRESO | H214: F4294 | I214: FD6DB83A-ECCD-45D0-BE6B-20CCFF85C602 | J214: 2025-01-28 | K214: Vigente | L214: PPD | M214: 99 Por definir | N214: CREDITO: | O214: 2025-01-28 | P214: 66235 | Q214: 0 | R214: 0 | S214: 0 | T214: 66235 | U214: 0 | V214: MXN | W214: SI | X214: 0 | Y214: 0 | Z214: 0
B215: ND | C215: ND | D215: ND | E215: BONANZA LOGISTICS | F215: BONANZA LOGISTICS | G215: INGRESO | H215: F4295 | I215: 4169161D-5AC8-464F-873A-28162036AB11 | J215: 2025-01-28 | K215: Vigente | L215: PPD | M215: 99 Por definir | N215: CREDITO: | O215: 2025-01-28 | P215: 42473.55 | Q215: 0 | R215: 0 | S215: 0 | T215: 42473.55 | U215: 0 | V215: USD | W215: SI | X215: 0 | Y215: 0 | Z215: 0
B216: ND | C216: ND | D216: ND | E216: CEVA FREIGHT MANAGEMENT MEXICO | F216: CEVA FREIGHT MANAGEMENT MEXICO | G216: INGRESO | H216: F4296 | I216: E2BB7D91-C9E9-41DC-8A1B-76275EF3DF2C | J216: 2025-01-28 | K216: Vigente | L216: PPD | M216: 99 Por definir | N216: CREDITO: | O216: 2025-01-28 | P216: 53800 | Q216: 0 | R216: 0 | S216: 8608 | T216: 62408 | U216: 0 | V216: MXN | W216: SI | X216: 0 | Y216: 8608 | Z216: 0
B217: ND | C217: ND | D217: ND | E217: CHASE PLASTICS DE MEXICO | F217: CHASE PLASTICS DE MEXICO | G217: INGRESO | H217: F4297 | I217: 01347678-0656-4CDD-AE81-FC4505B8974A | J217: 2025-01-28 | K217: Vigente | L217: PPD | M217: 99 Por definir | N217: CREDITO: | O217: 2025-01-28 | P217: 8500 | Q217: 0 | R217: 0 | S217: 1360 | T217: 9860 | U217: 0 | V217: MXN | W217: SI | X217: 0 | Y217: 1360 | Z217: 0
B218: ND | C218: ND | D218: ND | E218: DSV ROAD | F218: DSV ROAD | G218: INGRESO | H218: F4298 | I218: 78D6D49F-8742-41C5-824C-FD5AB68DA5B3 | J218: 2025-01-28 | K218: Vigente | L218: PPD | M218: 99 Por definir | N218: CREDITO: | O218: 2025-01-28 | P218: 74227.59 | Q218: 0 | R218: 0 | S218: 0 | T218: 74227.59 | U218: 0 | V218: USD | W218: SI | X218: 0 | Y218: 0 | Z218: 0
B219: ND | C219: ND | D219: ND | E219: DSV ROAD | F219: DSV ROAD | G219: INGRESO | H219: F4299 | I219: 6E08F5A5-1A7A-4573-9DF9-D683C45A0E1E | J219: 2025-01-28 | K219: Vigente | L219: PPD | M219: 99 Por definir | N219: CREDITO: | O219: 2025-01-28 | P219: 95464.36 | Q219: 0 | R219: 0 | S219: 0 | T219: 95464.36 | U219: 0 | V219: USD | W219: SI | X219: 0 | Y219: 0 | Z219: 0
B220: ND | C220: ND | D220: ND | E220: DSV ROAD | F220: DSV ROAD | G220: INGRESO | H220: F4300 | I220: 383ACF47-7EE9-48DE-AB05-CFB4BBAB823C | J220: 2025-01-28 | K220: Vigente | L220: PPD | M220: 99 Por definir | N220: CREDITO: | O220: 2025-01-28 | P220: 71193.76 | Q220: 0 | R220: 0 | S220: 0 | T220: 71193.76 | U220: 0 | V220: USD | W220: SI | X220: 0 | Y220: 0 | Z220: 0
B221: ND | C221: ND | D221: ND | E221: DSV ROAD | F221: DSV ROAD | G221: INGRESO | H221: F4301 | I221: 72A090F1-D897-42A7-8E3B-0E5F4B78C607 | J221: 2025-01-28 | K221: Vigente | L221: PPD | M221: 99 Por definir | N221: CREDITO: | O221: 2025-01-28 | P221: 67148.66 | Q221: 0 | R221: 0 | S221: 0 | T221: 67148.66 | U221: 0 | V221: USD | W221: SI | X221: 0 | Y221: 0 | Z221: 0
B222: ND | C222: ND | D222: ND | E222: NO USAR 1 | F222: JABIL EMS SWITZERLAND | G222: INGRESO | H222: F4302 | I222: 982048A0-B48F-4239-A4C1-1A2045A0FD79 | J222: 2025-01-28 | K222: Vigente | L222: PPD | M222: 99 Por definir | N222: CREDITO: | O222: 2025-01-28 | P222: 95069.96 | Q222: 0 | R222: 0 | S222: 0 | T222: 95069.96 | U222: 0 | V222: USD | W222: SI | X222: 0 | Y222: 0 | Z222: 0
B223: ND | C223: ND | D223: ND | E223: KASAI MEXICANA | F223: KASAI MEXICANA | G223: INGRESO | H223: F4303 | I223: 8E70AF74-37CF-4915-BEBA-DF23ADFB5391 | J223: 2025-01-28 | K223: Vigente | L223: PPD | M223: 99 Por definir | N223: CREDITO: | O223: 2025-01-28 | P223: 30338.25 | Q223: 0 | R223: 0 | S223: 0 | T223: 30338.25 | U223: 0 | V223: USD | W223: SI | X223: 0 | Y223: 0 | Z223: 0
...

Sheet ING.MIADMIN
A1: Verificado o Asoc | B1: Estado SAT | C1: CfdiRelacionados | D1: UUID | E1: Serie | F1: Folio | G1: Version | H1: TipoComprobante | I1: FechaTimbradoXML | J1: FechaEmisionXML | K1: LugarDeExpedicion | L1: RFC Emisor | M1: Nombre Emisor | N1: RegimenFiscal | O1: RFC Receptor | P1: Nombre Receptor | Q1: UsoCFDI | R1: RegimenFiscalReceptor | S1: DomicilioFiscalReceptor | T1: FormaDePago | U1: Metodo de Pago | V1: Complementos comprobante | W1: Conceptos | X1: Complementos conceptos | Y1: SubTotal | Z1: Descuento | AA1: Total Trasladados | AB1: Total Retenidos | AC1: Total | AG1: Moneda | AH1: TipoCambio | AI1: IVA Exento | AJ1: IVA Exento Base | AK1: IVA Cero Base | AL1: IVA 8 Importe | AM1: IVA 16 Importe | AN1: ISR Retenido | AO1: IVA Retenido | AP1: IEPS Retenido | AQ1: Ret ISR 1.25 Importe | AR1: Ret IVA 10.6667 Importe | AS1: Ret IVA 8 Importe | AT1: Ret IVA 6 Importe | AU1: Ret IVA 16 Importe | AV1: No Certificado SAT | AW1: No Certificado Emisor | AX1: Archivo XML
D2: 05BF2ED7-0CE4-42C0-B1D6-D2CDCEE44E75 | E2: F | F2: F4473 | G2: 4 | H2: I - Ingreso | I2: 2025-03-04T10:37:38 | J2: 2025-03-04T10:35:39 | K2: 66260 | L2: MME1507071ZA | M2: MILLHOUSE MEXICO | N2: 601 - General de Ley Personas Morales | O2: BLO1508261JA | P2: BONANZA LOGISTICS | Q2: G03 - Gastos en general | R2: 601 - General de Ley Personas Morales | S2: 6700 | T2: 99 - Por definir | U2: PPD | W2: SERVICIO LOGISTICO: TERRESTRE ORIGEN: CHARLOTTE, NC DESTINO: LAREDO, TX PRO NUMBER: 1118542 OBSERVACIONES: BL25-497 | Y2: 1500 | Z2: 0 | AA2: 0 | AC2: 1500 | AD2: =(Y2*AH2) -> 30762 | AE2: =VLOOKUP(D2,'FACTURAS INGRESOS'!$I$487:$P$718,8,0) -> 30762 | AF2: =AD2-AE2 -> 0 | AG2: USD | AH2: 20.508 | AK2: 1500 | AV2: 1.0000007e+15 | AW2: 1.0000007e+15 | AX2: C:\AdminXML\BovedaCFDi\MME1507071ZA\Emitidas\2025\03\05BF2ED7-0CE4-42C0-B1D6-D2CDCEE44E75@0000000000XX0.xml
D3: 122F9E84-EE04-4C0E-8144-680B4265004C | E3: F | F3: F4474 | G3: 4 | H3: I - Ingreso | I3: 2025-03-04T10:39:17 | J3: 2025-03-04T10:38:10 | K3: 66260 | L3: MME1507071ZA | M3: MILLHOUSE MEXICO | N3: 601 - General de Ley Personas Morales | O3: CPM1604014I1 | P3: CHASE PLASTICS DE MEXICO | Q3: G03 - Gastos en general | R3: 601 - General de Ley Personas Morales | S3: 6500 | T3: 99 - Por definir | U3: PPD | W3: SERVICIO LOGISTICO: TERRESTRE ORIGEN: EL MARQUÉS, QA DESTINO: SAN LUIS POTOSÍ, SL PRO NUMBER: 1119262 OBSERVACIONES: 2536225 / A. Raymond / 1477670 | Y3: 14000 | Z3: 0 | AA3: 2240 | AC3: 16240 | AD3: =Y3*AH3 -> 14000 | AE3: =VLOOKUP(D3,'FACTURAS INGRESOS'!$I$487:$P$718,8,0) -> 14000 | AF3: =AD3-AE3 -> 0 | AG3: MXN | AH3: 1 | AM3: 2240 | AV3: 1.0000007e+15 | AW3: 1.0000007e+15 | AX3: C:\AdminXML\BovedaCFDi\MME1507071ZA\Emitidas\2025\03\122F9E84-EE04-4C0E-8144-680B4265004C@0000000000XX0.xml
D4: FC252273-884E-4ADB-BE50-A2D6333E40F3 | E4: F | F4: F4475 | G4: 4 | H4: I - Ingreso | I4: 2025-03-04T10:40:47 | J4: 2025-03-04T10:39:40 | K4: 66260 | L4: MME1507071ZA | M4: MILLHOUSE MEXICO | N4: 601 - General de Ley Personas Morales | O4: CPM1604014I1 | P4: CHASE PLASTICS DE MEXICO | Q4: G03 - Gastos en general | R4: 601 - General de Ley Personas Morales | S4: 6500 | T4: 99 - Por definir | U4: PPD | W4: SERVICIO LOGISTICO: TERRESTRE ORIGEN: EL MARQUÉS, QA DESTINO: SILAO CENTRO, GJ PRO NUMBER: 1119654 OBSERVACIONES: 2536351 / Technimark / 1466030 | Y4: 16500 | Z4: 0 | AA4: 2640 | AC4: 19140 | AD4: =Y4*AH4 -> 16500 | AE4: =VLOOKUP(D4,'FACTURAS INGRESOS'!$I$487:$P$718,8,0) -> 16500 | AF4: =AD4-AE4 -> 0 | AG4: MXN | AH4: 1 | AM4: 2640 | AV4: 1.0000007e+15 | AW4: 1.0000007e+15 | AX4: C:\AdminXML\BovedaCFDi\MME1507071ZA\Emitidas\2025\03\FC252273-884E-4ADB-BE50-A2D6333E40F3@0000000000XX0.xml
D5: E6BA7F42-1BBC-4756-8688-B4A4AA7313EE | E5: F | F5: F4476 | G5: 4 | H5: I - Ingreso | I5: 2025-03-04T10:42:25 | J5: 2025-03-04T10:41:14 | K5: 66260 | L5: MME1507071ZA | M5: MILLHOUSE MEXICO | N5: 601 - General de Ley Personas Morales | O5: CPM1604014I1 | P5: CHASE PLASTICS DE MEXICO | Q5: G03 - Gastos en general | R5: 601 - General de Ley Personas Morales | S5: 6500 | T5: 99 - Por definir | U5: PPD | W5: SERVICIO LOGISTICO: TERRESTRE ORIGEN: EL MARQUÉS, QA DESTINO: COLONIA MÉXICO, QA PRO NUMBER: 1119659 OBSERVACIONES: 2536350 / GLN / 1479923 | Y5: 5000 | Z5: 0 | AA5: 800 | AC5: 5800 | AD5: =Y5*AH5 -> 5000 | AE5: =VLOOKUP(D5,'FACTURAS INGRESOS'!$I$487:$P$718,8,0) -> 5000 | AF5: =AD5-AE5 -> 0 | AG5: MXN | AH5: 1 | AM5: 800 | AV5: 1.0000007e+15 | AW5: 1.0000007e+15 | AX5: C:\AdminXML\BovedaCFDi\MME1507071ZA\Emitidas\2025\03\E6BA7F42-1BBC-4756-8688-B4A4AA7313EE@0000000000XX0.xml
D6: B2F3D698-A2FE-4186-97A7-C7808DDCFA8E | E6: F | F6: F4477 | G6: 4 | H6: I - Ingreso | I6: 2025-03-04T10:43:54 | J6: 2025-03-04T10:42:52 | K6: 66260 | L6: MME1507071ZA | M6: MILLHOUSE MEXICO | N6: 601 - General de Ley Personas Morales | O6: CPM1604014I1 | P6: CHASE PLASTICS DE MEXICO | Q6: G03 - Gastos en general | R6: 601 - General de Ley Personas Morales | S6: 6500 | T6: 99 - Por definir | U6: PPD | W6: SERVICIO LOGISTICO: TERRESTRE ORIGEN: APODACA CENTRO, NX DESTINO: EL MARQUÉS, QA PRO NUMBER: 1119663 OBSERVACIONES: BOL#: 2505200051 / PO# 5175007 | Y6: 27000 | Z6: 0 | AA6: 4320 | AC6: 31320 | AD6: =Y6*AH6 -> 27000 | AE6: =VLOOKUP(D6,'FACTURAS INGRESOS'!$I$487:$P$718,8,0) -> 27000 | AF6: =AD6-AE6 -> 0 | AG6: MXN | AH6: 1 | AM6: 4320 | AV6: 1.0000007e+15 | AW6: 1.0000007e+15 | AX6: C:\AdminXML\BovedaCFDi\MME1507071ZA\Emitidas\2025\03\B2F3D698-A2FE-4186-97A7-C7808DDCFA8E@0000000000XX0.xml
D7: 853575CE-C4D9-4A42-B717-1F773030BE2C | E7: F | F7: F4478 | G7: 4 | H7: I - Ingreso | I7: 2025-03-04T10:45:55 | J7: 2025-03-04T10:44:22 | K7: 66260 | L7: MME1507071ZA | M7: MILLHOUSE MEXICO | N7: 601 - General de Ley Personas Morales | O7: CPM1604014I1 | P7: CHASE PLASTICS DE MEXICO | Q7: G03 - Gastos en general | R7: 601 - General de Ley Personas Morales | S7: 6500 | T7: 99 - Por definir | U7: PPD | W7: SERVICIO LOGISTICO: TERRESTRE ORIGEN: EL MARQUÉS, QA DESTINO: BENITO JUÁREZ, QA PRO NUMBER: 1120270 OBSERVACIONES: Folio: OSQRO-6564 | Y7: 6000 | Z7: 0 | AA7: 960 | AC7: 6960 | AD7: =Y7*AH7 -> 6000 | AE7: =VLOOKUP(D7,'FACTURAS INGRESOS'!$I$487:$P$718,8,0) -> 6000 | AF7: =AD7-AE7 -> 0 | AG7: MXN | AH7: 1 | AM7: 960 | AV7: 1.0000007e+15 | AW7: 1.0000007e+15 | AX7: C:\AdminXML\BovedaCFDi\MME1507071ZA\Emitidas\2025\03\853575CE-C4D9-4A42-B717-1F773030BE2C@0000000000XX0.xml
D8: AB32F709-6BD6-4490-8602-AAE700F13CF4 | E8: F | F8: F4479 | G8: 4 | H8: I - Ingreso | I8: 2025-03-04T10:57:18 | J8: 2025-03-04T10:55:20 | K8: 66260 | L8: MME1507071ZA | M8: MILLHOUSE MEXICO | N8: 601 - General de Ley Personas Morales | O8: IMG860612JKA | P8: INGENIERIA Y MAQUINARIA DE GUADALUPE | Q8: G03 - Gastos en general | R8: 601 - General de Ley Personas Morales | S8: 25870 | T8: 99 - Por definir | U8: PPD | W8: SERVICIO LOGISTICO: MARITIMO ORIGEN: DENAMARK, XX DESTINO: CASTAÑOS CENTRO, CU PRO NUMBER: 1060077 OBSERVACIONES: OC2024007401A | Y8: 1642 | Z8: 0 | AA8: 0 | AC8: 1642 | AD8: =Y8*AH8 -> 33674.136 | AE8: =VLOOKUP(D8,'FACTURAS INGRESOS'!$I$487:$P$718,8,0) -> #N/A | AF8: =AD8-AE8 -> #N/A | AG8: USD | AH8: 20.508 | AK8: 1642 | AV8: 1.0000007e+15 | AW8: 1.0000007e+15 | AX8: C:\AdminXML\BovedaCFDi\MME1507071ZA\Emitidas\2025\03\AB32F709-6BD6-4490-8602-AAE700F13CF4@0000000000XX0.xml
D9: 615BD083-D710-42B0-A80F-767A81B049DB | E9: F | F9: F4480 | G9: 4 | H9: I - Ingreso | I9: 2025-03-04T11:02:18 | J9: 2025-03-04T11:01:14 | K9: 66260 | L9: MME1507071ZA | M9: MILLHOUSE MEXICO | N9: 601 - General de Ley Personas Morales | O9: CFM970129RG7 | P9: CEVA FREIGHT MANAGEMENT MEXICO | Q9: G03 - Gastos en general | R9: 601 - General de Ley Personas Morales | S9: 3720 | T9: 99 - Por definir | U9: PPD | W9: SERVICIO LOGISTICO: TERRESTRE ORIGEN: MANZANILLO, CL DESTINO: CHIHUAHUA, CI PRO NUMBER: 1120844 OBSERVACIONES: 1443820009816 | Y9: 53800 | Z9: 0 | AA9: 8608 | AC9: 62408 | AD9: =Y9*AH9 -> 53800 | AE9: =VLOOKUP(D9,'FACTURAS INGRESOS'!$I$487:$P$718,8,0) -> 53800 | AF9: =AD9-AE9 -> 0 | AG9: MXN | AH9: 1 | AM9: 8608 | AV9: 1.0000007e+15 | AW9: 1.0000007e+15 | AX9: C:\AdminXML\BovedaCFDi\MME1507071ZA\Emitidas\2025\03\615BD083-D710-42B0-A80F-767A81B049DB@0000000000XX0.xml
D10: 7F70E0F5-E3B5-41D8-A85E-4CECD2BBBC49 | E10: F | F10: F4481 | G10: 4 | H10: I - Ingreso | I10: 2025-03-04T11:03:54 | J10: 2025-03-04T11:02:47 | K10: 66260 | L10: MME1507071ZA | M10: MILLHOUSE MEXICO | N10: 601 - General de Ley Personas Morales | O10: CPM1604014I1 | P10: CHASE PLASTICS DE MEXICO | Q10: G03 - Gastos en general | R10: 601 - General de Ley Personas Morales | S10: 6500 | T10: 99 - Por definir | U10: PPD | W10: SERVICIO LOGISTICO: TERRESTRE ORIGEN: APODACA CENTRO, NX DESTINO: IZTAPALAPA, DF PRO NUMBER: 1120300 OBSERVACIONES: 1476984 / Vinoplastic / OCQ10426 | Y10: 21000 | Z10: 0 | AA10: 3360 | AC10: 24360 | AD10: =Y10*AH10 -> 21000 | AE10: =VLOOKUP(D10,'FACTURAS INGRESOS'!$I$487:$P$718,8,0) -> 21000 | AF10: =AD10-AE10 -> 0 | AG10: MXN | AH10: 1 | AM10: 3360 | AV10: 1.0000007e+15 | AW10: 1.0000007e+15 | AX10: C:\AdminXML\BovedaCFDi\MME1507071ZA\Emitidas\2025\03\7F70E0F5-E3B5-41D8-A85E-4CECD2BBBC49@0000000000XX0.xml
D11: E2045665-7B12-4CC7-9B28-9502DE3C6DC2 | E11: F | F11: F4482 | G11: 4 | H11: I - Ingreso | I11: 2025-03-04T11:05:12 | J11: 2025-03-04T11:04:18 | K11: 66260 | L11: MME1507071ZA | M11: MILLHOUSE MEXICO | N11: 601 - General de Ley Personas Morales | O11: CTU940107CK8 | P11: CLUB TURAVIA | Q11: G03 - Gastos en general | R11: 601 - General de Ley Personas Morales | S11: 77500 | T11: 99 - Por definir | U11: PPD | W11: REPORTE DE COMISIONES ORIGEN: NA DESTINO: NA PRO NUMBER: NA OBSERVACIONES: NA | Y11: 1198.21 | Z11: 0 | AA11: 191.71 | AC11: 1389.92 | AD11: =Y11*AH11 -> 1198.21 | AE11: =VLOOKUP(D11,'FACTURAS INGRESOS'!$I$487:$P$718,8,0) -> 1198.21 | AF11: =AD11-AE11 -> 0 | AG11: MXN | AH11: 1 | AM11: 191.71 | AV11: 1.0000007e+15 | AW11: 1.0000007e+15 | AX11: C:\AdminXML\BovedaCFDi\MME1507071ZA\Emitidas\2025\03\E2045665-7B12-4CC7-9B28-9502DE3C6DC2@0000000000XX0.xml
D12: F42C0258-7A71-4B46-9FFC-CF3B76082FD6 | E12: F | F12: F4483 | G12: 4 | H12: I - Ingreso | I12: 2025-03-04T11:06:32 | J12: 2025-03-04T11:05:38 | K12: 66260 | L12: MME1507071ZA | M12: MILLHOUSE MEXICO | N12: 601 - General de Ley Personas Morales | O12: CFO030723285 | P12: CONTINENTE FORWARDING | Q12: G03 - Gastos en general | R12: 601 - General de Ley Personas Morales | S12: 66260 | T12: 99 - Por definir | U12: PPD | W12: SERVICIO LOGISTICO: TERRESTRE ORIGEN: ERIE, PA DESTINO: LAREDO, TX PRO NUMBER: 1120864 OBSERVACIONES: C45695 | Y12: 1925 | Z12: 0 | AA12: 0 | AC12: 1925 | AD12: =Y12*AH12 -> 39477.9 | AE12: =VLOOKUP(D12,'FACTURAS INGRESOS'!$I$487:$P$718,8,0) -> 39477.9 | AF12: =AD12-AE12 -> 0 | AG12: USD | AH12: 20.508 | AK12: 1925 | AV12: 1.0000007e+15 | AW12: 1.0000007e+15 | AX12: C:\AdminXML\BovedaCFDi\MME1507071ZA\Emitidas\2025\03\F42C0258-7A71-4B46-9FFC-CF3B76082FD6@0000000000XX0.xml
D13: 2C44C0D2-DD27-4586-98BB-481DF28AC6A4 | E13: F | F13: F4484 | G13: 4 | H13: I - Ingreso | I13: 2025-03-04T11:08:27 | J13: 2025-03-04T11:07:27 | K13: 66260 | L13: MME1507071ZA | M13: MILLHOUSE MEXICO | N13: 601 - General de Ley Personas Morales | O13: CFO030723285 | P13: CONTINENTE FORWARDING | Q13: G03 - Gastos en general | R13: 601 - General de Ley Personas Morales | S13: 66260 | T13: 99 - Por definir | U13: PPD | W13: SERVICIO LOGISTICO: TERRESTRE ORIGEN: MILWAUKEE, WI DESTINO: MILWAUKEE, WI PRO NUMBER: 1120945 OBSERVACIONES: C45726 | Y13: 1700 | Z13: 0 | AA13: 0 | AC13: 1700 | AD13: =Y13*AH13 -> 34863.6 | AE13: =VLOOKUP(D13,'FACTURAS INGRESOS'!$I$487:$P$718,8,0) -> 34863.6 | AF13: =AD13-AE13 -> 0 | AG13: USD | AH13: 20.508 | AK13: 1700 | AV13: 1.0000007e+15 | AW13: 1.0000007e+15 | AX13: C:\AdminXML\BovedaCFDi\MME1507071ZA\Emitidas\2025\03\2C44C0D2-DD27-4586-98BB-481DF28AC6A4@0000000000XX0.xml
D14: 4CB15B85-AA36-438E-A682-B415221F97F9 | E14: F | F14: F4485 | G14: 4 | H14: I - Ingreso | I14: 2025-03-04T11:09:49 | J14: 2025-03-04T11:08:55 | K14: 66260 | L14: MME1507071ZA | M14: MILLHOUSE MEXICO | N14: 601 - General de Ley Personas Morales | O14: CFO030723285 | P14: CONTINENTE FORWARDING | Q14: G03 - Gastos en general | R14: 601 - General de Ley Personas Morales | S14: 66260 | T14: 99 - Por definir | U14: PPD | W14: SERVICIO LOGISTICO: TERRESTRE ORIGEN: CANTON, MI DESTINO: LAREDO, TX PRO NUMBER: 1121033 OBSERVACIONES: C45798 | Y14: 1765 | Z14: 0 | AA14: 0 | AC14: 1765 | AD14: =Y14*AH14 -> 36196.62 | AE14: =VLOOKUP(D14,'FACTURAS INGRESOS'!$I$487:$P$718,8,0) -> 36196.62 | AF14: =AD14-AE14 -> 0 | AG14: USD | AH14: 20.508 | AK14: 1765 | AV14: 1.0000007e+15 | AW14: 1.0000007e+15 | AX14: C:\AdminXML\BovedaCFDi\MME1507071ZA\Emitidas\2025\03\4CB15B85-AA36-438E-A682-B415221F97F9@0000000000XX0.xml
D15: 1F09ADD4-9324-402D-A563-DC96C6A82D58 | E15: F | F15: F4486 | G15: 4 | H15: I - Ingreso | I15: 2025-03-04T11:11:18 | J15: 2025-03-04T11:10:24 | K15: 66260 | L15: MME1507071ZA | M15: MILLHOUSE MEXICO | N15: 601 - General de Ley Personas Morales | O15: DRO190903817 | P15: DSV ROAD | Q15: G03 - Gastos en general | R15: 601 - General de Ley Personas Morales | S15: 3740 | T15: 99 - Por definir | U15: PPD | W15: SERVICIO LOGISTICO: TERRESTRE ORIGEN: LAREDO, TX DESTINO: HOLLAND, MI PRO NUMBER: 1114633 OBSERVACIONES: SG9L0012735 | Y15: 4100 | Z15: 0 | AA15: 0 | AC15: 4100 | AD15: =Y15*AH15 -> 84082.8 | AE15: =VLOOKUP(D15,'FACTURAS INGRESOS'!$I$487:$P$718,8,0) -> 84082.8 | AF15: =AD15-AE15 -> 0 | AG15: USD | AH15: 20.508 | AK15: 4100 | AV15: 1.0000007e+15 | AW15: 1.0000007e+15 | AX15: C:\AdminXML\BovedaCFDi\MME1507071ZA\Emitidas\2025\03\1F09ADD4-9324-402D-A563-DC96C6A82D58@0000000000XX0.xml
D16: 419487D6-0FE2-4ACF-9CB3-125EF76520D0 | E16: F | F16: F4487 | G16: 4 | H16: I - Ingreso | I16: 2025-03-04T11:12:51 | J16: 2025-03-04T11:11:58 | K16: 66260 | L16: MME1507071ZA | M16: MILLHOUSE MEXICO | N16: 601 - General de Ley Personas Morales | O16: EOP640608I13 | P16: HELLA AUTOMOTIVE MEXICO | Q16: G03 - Gastos en general | R16: 601 - General de Ley Personas Morales | S16: 45601 | T16: 99 - Por definir | U16: PPD | W16: SERVICIO LOGISTICO: TERRESTRE ORIGEN: EL PASO, TX DESTINO: ÁLVAREZ DEL CASTILLO, JA PRO NUMBER: 1117914 OBSERVACIONES: PL6-OV25-INCA1-00408-2753-573040-USD | Y16: 2400 | Z16: 0 | AA16: 0 | AC16: 2400 | AD16: =Y16*AH16 -> 49219.2 | AE16: =VLOOKUP(D16,'FACTURAS INGRESOS'!$I$487:$P$718,8,0) -> 49219.2 | AF16: =AD16-AE16 -> 0 | AG16: USD | AH16: 20.508 | AK16: 2400 | AV16: 1.0000007e+15 | AW16: 1.0000007e+15 | AX16: C:\AdminXML\BovedaCFDi\MME1507071ZA\Emitidas\2025\03\419487D6-0FE2-4ACF-9CB3-125EF76520D0@0000000000XX0.xml
D17: ACF554AC-0EAF-4B25-8F4C-59BF2E7B24E3 | E17: F | F17: F4488 | G17: 4 | H17: I - Ingreso | I17: 2025-03-04T11:14:14 | J17: 2025-03-04T11:13:21 | K17: 66260 | L17: MME1507071ZA | M17: MILLHOUSE MEXICO | N17: 601 - General de Ley Personas Morales | O17: EOP640608I13 | P17: HELLA AUTOMOTIVE MEXICO | Q17: G03 - Gastos en general | R17: 601 - General de Ley Personas Morales | S17: 45601 | T17: 99 - Por definir | U17: PPD | W17: SERVICIO LOGISTICO: TERRESTRE ORIGEN: LAREDO, TX DESTINO: VANCE, AL PRO NUMBER: 1120614 OBSERVACIONES: PL7-OV25-OUTC1-00354-4514-639208-USD | Y17: 3100 | Z17: 0 | AA17: 0 | AC17: 3100 | AD17: =Y17*AH17 -> 63574.8 | AE17: =VLOOKUP(D17,'FACTURAS INGRESOS'!$I$487:$P$718,8,0) -> 63574.8 | AF17: =AD17-AE17 -> 0 | AG17: USD | AH17: 20.508 | AK17: 3100 | AV17: 1.0000007e+15 | AW17: 1.0000007e+15 | AX17: C:\AdminXML\BovedaCFDi\MME1507071ZA\Emitidas\2025\03\ACF554AC-0EAF-4B25-8F4C-59BF2E7B24E3@0000000000XX0.xml
D18: 97AEEC1D-1740-437C-8D88-5C1D90549868 | E18: F | F18: F4489 | G18: 4 | H18: I - Ingreso | I18: 2025-03-04T11:16:15 | J18: 2025-03-04T11:14:42 | K18: 66260 | L18: MME1507071ZA | M18: MILLHOUSE MEXICO | N18: 601 - General de Ley Personas Morales | O18: EOP640608I13 | P18: HELLA AUTOMOTIVE MEXICO | Q18: G03 - Gastos en general | R18: 601 - General de Ley Personas Morales | S18: 45601 | T18: 99 - Por definir | U18: PPD | W18: SERVICIO LOGISTICO: TERRESTRE ORIGEN: LAREDO, TX DESTINO: VANCE, AL PRO NUMBER: 1120845 OBSERVACIONES: PL7-OV25-OUTC1-00355-4514-639208-USD | Y18: 3340 | Z18: 0 | AA18: 0 | AC18: 3340 | AD18: =Y18*AH18 -> 68496.72 | AE18: =VLOOKUP(D18,'FACTURAS INGRESOS'!$I$487:$P$718,8,0) -> 68496.72 | AF18: =AD18-AE18 -> 0 | AG18: USD | AH18: 20.508 | AK18: 3340 | AV18: 1.0000007e+15 | AW18: 1.0000007e+15 | AX18: C:\AdminXML\BovedaCFDi\MME1507071ZA\Emitidas\2025\03\97AEEC1D-1740-437C-8D88-5C1D90549868@0000000000XX0.xml
D19: 038797DA-EA4A-4834-8534-863FE9E645A9 | E19: F | F19: F4490 | G19: 4 | H19: I - Ingreso | I19: 2025-03-04T11:18:12 | J19: 2025-03-04T11:17:19 | K19: 66260 | L19: MME1507071ZA | M19: MILLHOUSE MEXICO | N19: 601 - General de Ley Personas Morales | O19: EOP640608I13 | P19: HELLA AUTOMOTIVE MEXICO | Q19: G03 - Gastos en general | R19: 601 - General de Ley Personas Morales | S19: 45601 | T19: 99 - Por definir | U19: PPD | W19: SERVICIO LOGISTICO: TERRESTRE ORIGEN: LAREDO, TX DESTINO: NASHVILLE, IL PRO NUMBER: 1121021 OBSERVACIONES: PL6-OV25-OUTA1-00415-2694-639208-USD | Y19: 2800 | Z19: 0 | AA19: 0 | AC19: 2800 | AD19: =Y19*AH19 -> 57422.4 | AE19: =VLOOKUP(D19,'FACTURAS INGRESOS'!$I$487:$P$718,8,0) -> 57422.4 | AF19: =AD19-AE19 -> 0 | AG19: USD | AH19: 20.508 | AK19: 2800 | AV19: 1.0000007e+15 | AW19: 1.0000007e+15 | AX19: C:\AdminXML\BovedaCFDi\MME1507071ZA\Emitidas\2025\03\038797DA-EA4A-4834-8534-863FE9E645A9@0000000000XX0.xml
D20: EB6EAD7D-7E0F-4D44-8A86-9B3C4CD00EF9 | E20: F | F20: F4491 | G20: 4 | H20: I - Ingreso | I20: 2025-03-04T11:19:39 | J20: 2025-03-04T11:18:38 | K20: 66260 | L20: MME1507071ZA | M20: MILLHOUSE MEXICO | N20: 601 - General de Ley Personas Morales | O20: EOP640608I13 | P20: HELLA AUTOMOTIVE MEXICO | Q20: G03 - Gastos en general | R20: 601 - General de Ley Personas Morales | S20: 45601 | T20: 99 - Por definir | U20: PPD | W20: SERVICIO LOGISTICO: TERRESTRE ORIGEN: EL PASO, TX DESTINO: EL SABINO, JA PRO NUMBER: 1121354 OBSERVACIONES: PL6-OV25-INCA1-00416-2753-573040-USD | Y20: 2530 | Z20: 0 | AA20: 0 | AC20: 2530 | AD20: =Y20*AH20 -> 51885.24 | AE20: =VLOOKUP(D20,'FACTURAS INGRESOS'!$I$487:$P$718,8,0) -> 51885.24 | AF20: =AD20-AE20 -> 0 | AG20: USD | AH20: 20.508 | AK20: 2530 | AV20: 1.0000007e+15 | AW20: 1.0000007e+15 | AX20: C:\AdminXML\BovedaCFDi\MME1507071ZA\Emitidas\2025\03\EB6EAD7D-7E0F-4D44-8A86-9B3C4CD00EF9@0000000000XX0.xml
D21: E6DE8F62-9C4C-4CF6-BA02-9D0BFCC8C568 | E21: F | F21: F4492 | G21: 4 | H21: I - Ingreso | I21: 2025-03-04T12:33:53 | J21: 2025-03-04T12:32:54 | K21: 66260 | L21: MME1507071ZA | M21: MILLHOUSE MEXICO | N21: 601 - General de Ley Personas Morales | O21: HAS120702332 | P21: HITACHI ASTEMO MEXICO | Q21: G03 - Gastos en general | R21: 601 - General de Ley Personas Morales | S21: 76220 | T21: 99 - Por definir | U21: PPD | W21: SERVICIO LOGISTICO: TERRESTRE ORIGEN: LAREDO, TX DESTINO: LEWIS CENTER, OH PRO NUMBER: 1120921 OBSERVACIONES: 1120921 | Y21: 3500 | Z21: 0 | AA21: 0 | AC21: 3500 | AD21: =Y21*AH21 -> 71778 | AE21: =VLOOKUP(D21,'FACTURAS INGRESOS'!$I$487:$P$718,8,0) -> 71778 | AF21: =AD21-AE21 -> 0 | AG21: USD | AH21: 20.508 | AK21: 3500 | AV21: 1.0000007e+15 | AW21: 1.0000007e+15 | AX21: C:\AdminXML\BovedaCFDi\MME1507071ZA\Emitidas\2025\03\E6DE8F62-9C4C-4CF6-BA02-9D0BFCC8C568@0000000000XX0.xml
D22: 629AF137-1DA0-410A-86DF-4768A78FD908 | E22: F | F22: F4493 | G22: 4 | H22: I - Ingreso | I22: 2025-03-04T14:48:10 | J22: 2025-03-04T14:47:04 | K22: 66260 | L22: MME1507071ZA | M22: MILLHOUSE MEXICO | N22: 601 - General de Ley Personas Morales | O22: ITC140429H19 | P22: IE TRADE COMERCIAL | Q22: G03 - Gastos en general | R22: 601 - General de Ley Personas Morales | S22: 32300 | T22: 99 - Por definir | U22: PPD | W22: SERVICIO LOGISTICO: TERRESTRE ORIGEN: LAREDO, TX DESTINO: LA LOMA ALTA, GJ PRO NUMBER: 1121321 OBSERVACIONES: IET-2025-8243 | Y22: 1450 | Z22: 0 | AA22: 0 | AC22: 1450 | AD22: =Y22*AH22 -> 29736.6 | AE22: =VLOOKUP(D22,'FACTURAS INGRESOS'!$I$487:$P$718,8,0) -> 29736.6 | AF22: =AD22-AE22 -> 0 | AG22: USD | AH22: 20.508 | AK22: 1450 | AV22: 1.0000007e+15 | AW22: 1.0000007e+15 | AX22: C:\AdminXML\BovedaCFDi\MME1507071ZA\Emitidas\2025\03\629AF137-1DA0-410A-86DF-4768A78FD908@0000000000XX0.xml
D23: 3E04AF63-DF8D-41F7-9B7D-41C13B60C591 | E23: F | F23: F4494 | G23: 4 | H23: I - Ingreso | I23: 2025-03-04T14:49:47 | J23: 2025-03-04T14:48:42 | K23: 66260 | L23: MME1507071ZA | M23: MILLHOUSE MEXICO | N23: 601 - General de Ley Personas Morales | O23: KME9705088B5 | P23: KASAI MEXICANA | Q23: G03 - Gastos en general | R23: 601 - General de Ley Personas Morales | S23: 37564 | T23: 99 - Por definir | U23: PPD | W23: SERVICIO LOGISTICO: TERRESTRE ORIGEN: CIUDAD JUÁREZ, CI DESTINO: CIUDAD INDUSTRIAL, GJ PRO NUMBER: 1118699 OBSERVACIONES: 71660 | Y23: 94587.2 | Z23: 0 | AA23: 15133.95 | AC23: 109721.15 | AD23: =Y23*AH23 -> 94587.2 | AE23: =VLOOKUP(D23,'FACTURAS INGRESOS'!$I$487:$P$718,8,0) -> 94587.2 | AF23: =AD23-AE23 -> 0 | AG23: MXN | AH23: 1 | AM23: 15133.95 | AV23: 1.0000007e+15 | AW23: 1.0000007e+15 | AX23: C:\AdminXML\BovedaCFDi\MME1507071ZA\Emitidas\2025\03\3E04AF63-DF8D-41F7-9B7D-41C13B60C591@0000000000XX0.xml
D24: 1FAD089F-45C0-4184-B3B7-841E6E595200 | E24: F | F24: F4495 | G24: 4 | H24: I - Ingreso | I24: 2025-03-04T14:51:55 | J24: 2025-03-04T14:50:42 | K24: 66260 | L24: MME1507071ZA | M24: MILLHOUSE MEXICO | N24: 601 - General de Ley Personas Morales | O24: KME9705088B5 | P24: KASAI MEXICANA | Q24: G03 - Gastos en general | R24: 601 - General de Ley Personas Morales | S24: 37564 | T24: 99 - Por definir | U24: PPD | W24: SERVICIO LOGISTICO: TERRESTRE ORIGEN: CIUDAD JUÁREZ, CI DESTINO: CIUDAD INDUSTRIAL, GJ PRO NUMBER: 1120388 OBSERVACIONES: 71661 | Y24: 80000 | Z24: 0 | AA24: 12800 | AC24: 92800 | AD24: =Y24*AH24 -> 80000 | AE24: =VLOOKUP(D24,'FACTURAS INGRESOS'!$I$487:$P$718,8,0) -> 80000 | AF24: =AD24-AE24 -> 0 | AG24: MXN | AH24: 1 | AM24: 12800 | AV24: 1.0000007e+15 | AW24: 1.0000007e+15 | AX24: C:\AdminXML\BovedaCFDi\MME1507071ZA\Emitidas\2025\03\1FAD089F-45C0-4184-B3B7-841E6E595200@0000000000XX0.xml
D25: 9E340036-6D13-42E6-B8E5-7AE658DA7FCA | E25: F | F25: F4496 | G25: 4 | H25: I - Ingreso | I25: 2025-03-04T14:53:23 | J25: 2025-03-04T14:52:27 | K25: 66260 | L25: MME1507071ZA | M25: MILLHOUSE MEXICO | N25: 601 - General de Ley Personas Morales | O25: KME9705088B5 | P25: KASAI MEXICANA | Q25: G03 - Gastos en general | R25: 601 - General de Ley Personas Morales | S25: 37564 | T25: 99 - Por definir | U25: PPD | W25: SERVICIO LOGISTICO: TERRESTRE ORIGEN: CHIHUAHUA, CI DESTINO: CIUDAD INDUSTRIAL, GJ PRO NUMBER: 1120837 OBSERVACIONES: 71662 | Y25: 38500 | Z25: 0 | AA25: 6160 | AC25: 44660 | AD25: =Y25*AH25 -> 38500 | AE25: =VLOOKUP(D25,'FACTURAS INGRESOS'!$I$487:$P$718,8,0) -> 38500 | AF25: =AD25-AE25 -> 0 | AG25: MXN | AH25: 1 | AM25: 6160 | AV25: 1.0000007e+15 | AW25: 1.0000007e+15 | AX25: C:\AdminXML\BovedaCFDi\MME1507071ZA\Emitidas\2025\03\9E340036-6D13-42E6-B8E5-7AE658DA7FCA@0000000000XX0.xml
D26: 72C178CC-6AFA-4405-A96B-49CBF4E830F3 | E26: F | F26: F4497 | G26: 4 | H26: I - Ingreso | I26: 2025-03-04T14:55:13 | J26: 2025-03-04T14:54:18 | K26: 66260 | L26: MME1507071ZA | M26: MILLHOUSE MEXICO | N26: 601 - General de Ley Personas Morales | O26: MMG201001LG5 | P26: MOLEX DE MEXICO GUADALAJARA 2 | Q26: G03 - Gastos en general | R26: 601 - General de Ley Personas Morales | S26: 45777 | T26: 99 - Por definir | U26: PPD | W26: SERVICIO LOGISTICO: TERRESTRE ORIGEN: EL MARQUÉS, QA DESTINO: ZAPOPAN, JA PRO NUMBER: 1121268 OBSERVACIONES: 1121268 | Y26: 23600 | Z26: 0 | AA26: 3776 | AC26: 27376 | AD26: =Y26*AH26 -> 23600 | AE26: =VLOOKUP(D26,'FACTURAS INGRESOS'!$I$487:$P$718,8,0) -> 23600 | AF26: =AD26-AE26 -> 0 | AG26: MXN | AH26: 1 | AM26: 3776 | AV26: 1.0000007e+15 | AW26: 1.0000007e+15 | AX26: C:\AdminXML\BovedaCFDi\MME1507071ZA\Emitidas\2025\03\72C178CC-6AFA-4405-A96B-49CBF4E830F3@0000000000XX0.xml
D27: 9AB7148A-6D57-4358-81B7-A44336E11C9F | E27: F | F27: F4498 | G27: 4 | H27: I - Ingreso | I27: 2025-03-04T14:58:38 | J27: 2025-03-04T14:57:32 | K27: 66260 | L27: MME1507071ZA | M27: MILLHOUSE MEXICO | N27: 601 - General de Ley Personas Morales | O27: USI970903M23 | P27: UNIVERSAL SCIENTIFIC INDUSTRIAL DE MEXICO | Q27: G03 - Gastos en general | R27: 601 - General de Ley Personas Morales | S27: 44300 | T27: 99 - Por definir | U27: PPD | W27: SERVICIO LOGISTICO: TERRESTRE ORIGEN: JARDINES DE SANTA ISABEL, JA DESTINO: PULASKI, TN PRO NUMBER: 1119738 OBSERVACIONES: 1119738 | Y27: 4750 | Z27: 0 | AA27: 0 | AC27: 4750 | AD27: =Y27*AH27 -> 97413 | AE27: =VLOOKUP(D27,'FACTURAS INGRESOS'!$I$487:$P$718,8,0) -> 97413 | AF27: =AD27-AE27 -> 0 | AG27: USD | AH27: 20.508 | AK27: 4750 | AV27: 1.0000007e+15 | AW27: 1.0000007e+15 | AX27: C:\AdminXML\BovedaCFDi\MME1507071ZA\Emitidas\2025\03\9AB7148A-6D57-4358-81B7-A44336E11C9F@0000000000XX0.xml
D28: BBB8A4DF-10C4-444B-B71D-0CA874F5AEB5 | E28: F | F28: F4499 | G28: 4 | H28: I - Ingreso | I28: 2025-03-04T15:08:05 | J28: 2025-03-04T15:06:43 | K28: 66260 | L28: MME1507071ZA | M28: MILLHOUSE MEXICO | N28: 601 - General de Ley Personas Morales | O28: CFO030723285 | P28: CONTINENTE FORWARDING | Q28: G03 - Gastos en general | R28: 601 - General de Ley Personas Morales | S28: 66260 | T28: 99 - Por definir | U28: PPD | W28: SERVICIO LOGISTICO: TERRESTRE ORIGEN: PEACHTREE CITY, GA DESTINO: LAREDO, TX PRO NUMBER: 1120863 OBSERVACIONES: C45656 | Y28: 1125 | Z28: 0 | AA28: 0 | AC28: 1125 | AD28: =Y28*AH28 -> 23071.5 | AE28: =VLOOKUP(D28,'FACTURAS INGRESOS'!$I$487:$P$718,8,0) -> 23071.5 | AF28: =AD28-AE28 -> 0 | AG28: USD | AH28: 20.508 | AK28: 1125 | AV28: 1.0000007e+15 | AW28: 1.0000007e+15 | AX28: C:\AdminXML\BovedaCFDi\MME1507071ZA\Emitidas\2025\03\BBB8A4DF-10C4-444B-B71D-0CA874F5AEB5@0000000000XX0.xml
D29: 85542B66-CB30-430B-8BB2-5FB8E86DB240 | E29: F | F29: F4500 | G29: 4 | H29: I - Ingreso | I29: 2025-03-05T20:00:25 | J29: 2025-03-05T19:58:57 | K29: 66260 | L29: MME1507071ZA | M29: MILLHOUSE MEXICO | N29: 601 - General de Ley Personas Morales | O29: CFO030723285 | P29: CONTINENTE FORWARDING | Q29: G03 - Gastos en general | R29: 601 - General de Ley Personas Morales | S29: 66260 | T29: 99 - Por definir | U29: PPD | W29: SERVICIO LOGISTICO: TERRESTRE ORIGEN: SAINT LOUIS, MO DESTINO: LAREDO, TX PRO NUMBER: 1120807 OBSERVACIONES: C45653 | Y29: 1125 | Z29: 0 | AA29: 0 | AC29: 1125 | AD29: =Y29*AH29 -> 22987.462 | AE29: =VLOOKUP(D29,'FACTURAS INGRESOS'!$I$487:$P$718,8,0) -> 22987.46 | AF29: =AD29-AE29 -> 0.0025 | AG29: USD | AH29: 20.4333 | AK29: 1125 | AV29: 1.0000007e+15 | AW29: 1.0000007e+15 | AX29: C:\AdminXML\BovedaCFDi\MME1507071ZA\Emitidas\2025\03\85542B66-CB30-430B-8BB2-5FB8E86DB240@0000000000XX0.xml
D30: 66FB4D0C-EFB1-4F1B-9C5E-29CC9B49FFBA | E30: F | F30: F4501 | G30: 4 | H30: I - Ingreso | I30: 2025-03-05T20:02:10 | J30: 2025-03-05T20:00:59 | K30: 66260 | L30: MME1507071ZA | M30: MILLHOUSE MEXICO | N30: 601 - General de Ley Personas Morales | O30: CPM1604014I1 | P30: CHASE PLASTICS DE MEXICO | Q30: G03 - Gastos en general | R30: 601 - General de Ley Personas Morales | S30: 6500 | T30: 99 - Por definir | U30: PPD | W30: Servicio de almacenaje ORIGEN: NA DESTINO: NA PRO NUMBER: February 01 to February 28 2025 OBSERVACIONES: Apodaca Warehouse | Y30: 859.94 | Z30: 0 | AA30: 137.59 | AC30: 997.53 | AD30: =Y30*AH30 -> 17571.412 | AE30: =VLOOKUP(D30,'FACTURAS INGRESOS'!$I$487:$P$718,8,0) -> 17571.41 | AF30: =AD30-AE30 -> 0.002002 | AG30: USD | AH30: 20.4333 | AM30: 137.59 | AV30: 1.0000007e+15 | AW30: 1.0000007e+15 | AX30: C:\AdminXML\BovedaCFDi\MME1507071ZA\Emitidas\2025\03\66FB4D0C-EFB1-4F1B-9C5E-29CC9B49FFBA@0000000000XX0.xml
D31: CD9E0B2D-E90B-41CD-BD0C-E089F385E272 | E31: FC | F31: 890 | G31: 4 | H31: I - Ingreso | I31: 2025-03-05T20:19:38 | J31: 2025-03-05T20:19:37 | K31: 66260 | L31: MME1507071ZA | M31: MILLHOUSE MEXICO | N31: 601 - General de Ley Personas Morales | O31: FSA980318AL3 | P31: FAURECIA SISTEMAS AUTOMOTRICES DE MEXICO | Q31: G03 - Gastos en general | R31: 601 - General de Ley Personas Morales | S31: 72710 | T31: 99 - Por definir | U31: PPD | W31: SERVICIO LOGISTICO: TERRESTRE ORIGEN: COLUMBUS, IN DESTINO: FORT WAYNE, IN PRO NUMBER: 1110285 OBSERVACIONES: ID2501G5D5 / 7100169354 / 8200091138 | Y31: 1300 | AA31: 0 | AC31: 1300 | AD31: =Y31*AH31 -> 26563.29 | AE31: =VLOOKUP(D31,'FACTURAS INGRESOS'!$I$487:$P$718,8,0) -> 26563.29 | AF31: =AD31-AE31 -> 0 | AG31: USD | AH31: 20.4333 | AK31: 1300 | AV31: 1.0000007e+15 | AW31: 1.0000007e+15 | AX31: C:\AdminXML\BovedaCFDi\MME1507071ZA\Emitidas\2025\03\CD9E0B2D-E90B-41CD-BD0C-E089F385E272@0000000000XX0.xml
D32: CF28D303-C041-415F-A115-213D32EA7516 | E32: FC | F32: 891 | G32: 4 | H32: I - Ingreso | I32: 2025-03-05T20:21:44 | J32: 2025-03-05T20:21:43 | K32: 66260 | L32: MME1507071ZA | M32: MILLHOUSE MEXICO | N32: 601 - General de Ley Personas Morales | O32: FSA980318AL3 | P32: FAURECIA SISTEMAS AUTOMOTRICES DE MEXICO | Q32: G03 - Gastos en general | R32: 601 - General de Ley Personas Morales | S32: 72710 | T32: 99 - Por definir | U32: PPD | W32: SERVICIO LOGISTICO: TERRESTRE ORIGEN: LAREDO, TX DESTINO: CUAUTLANCINGO CORREDOR EMPRESARIAL, PU PRO NUMBER: 1114207 OBSERVACIONES: ID2501J11G / 7100171126 / 8200092594 | Y32: 1600 | AA32: 0 | AC32: 1600 | AD32: =Y32*AH32 -> 32693.28 | AE32: =VLOOKUP(D32,'FACTURAS INGRESOS'!$I$487:$P$718,8,0) -> 32693.28 | AF32: =AD32-AE32 -> 0 | AG32: USD | AH32: 20.4333 | AK32: 1600 | AV32: 1.0000007e+15 | AW32: 1.0000007e+15 | AX32: C:\AdminXML\BovedaCFDi\MME1507071ZA\Emitidas\2025\03\CF28D303-C041-415F-A115-213D32EA7516@0000000000XX0.xml
D33: 5C50D98E-6BA8-4C16-A233-14E393B64F7D | E33: FC | F33: 892 | G33: 4 | H33: I - Ingreso | I33: 2025-03-05T20:23:13 | J33: 2025-03-05T20:23:12 | K33: 66260 | L33: MME1507071ZA | M33: MILLHOUSE MEXICO | N33: 601 - General de Ley Personas Morales | O33: FSA980318AL3 | P33: FAURECIA SISTEMAS AUTOMOTRICES DE MEXICO | Q33: G03 - Gastos en general | R33: 601 - General de Ley Personas Morales | S33: 72710 | T33: 99 - Por definir | U33: PPD | W33: SERVICIO LOGISTICO: TERRESTRE ORIGEN: QUERÉTARO (ING FERNANDO ESPINOZA GTZ), QA DESTINO: DEXTER, MO PRO NUMBER: 1115731 OBSERVACIONES: ID2502K83B / 7100171980 / 8200093528 | Y33: 5700 | AA33: 0 | AC33: 5700 | AD33: =Y33*AH33 -> 116469.81 | AE33: =VLOOKUP(D33,'FACTURAS INGRESOS'!$I$487:$P$718,8,0) -> 116469.81 | AF33: =AD33-AE33 -> 0 | AG33: USD | AH33: 20.4333 | AK33: 5700 | AV33: 1.0000007e+15 | AW33: 1.0000007e+15 | AX33: C:\AdminXML\BovedaCFDi\MME1507071ZA\Emitidas\2025\03\5C50D98E-6BA8-4C16-A233-14E393B64F7D@0000000000XX0.xml
D34: E11C9632-F01D-4CA9-8CE3-2AF76E033C9D | E34: FC | F34: 893 | G34: 4 | H34: I - Ingreso | I34: 2025-03-05T20:24:43 | J34: 2025-03-05T20:24:42 | K34: 66260 | L34: MME1507071ZA | M34: MILLHOUSE MEXICO | N34: 601 - General de Ley Personas Morales | O34: FSA980318AL3 | P34: FAURECIA SISTEMAS AUTOMOTRICES DE MEXICO | Q34: G03 - Gastos en general | R34: 601 - General de Ley Personas Morales | S34: 72710 | T34: 99 - Por definir | U34: PPD | W34: SERVICIO LOGISTICO: TERRESTRE ORIGEN: AMPLIACIÓN MONTE DEL COECILLO, GJ DESTINO: FORT WAYNE, IN PRO NUMBER: 1116302 OBSERVACIONES: XF2502KH38 / 7100172242 / 8200095918 | Y34: 5940 | AA34: 0 | AC34: 5940 | AD34: =Y34*AH34 -> 121373.8 | AE34: =VLOOKUP(D34,'FACTURAS INGRESOS'!$I$487:$P$718,8,0) -> 121373.8 | AF34: =AD34-AE34 -> 0.002 | AG34: USD | AH34: 20.4333 | AK34: 5940 | AV34: 1.0000007e+15 | AW34: 1.0000007e+15 | AX34: C:\AdminXML\BovedaCFDi\MME1507071ZA\Emitidas\2025\03\E11C9632-F01D-4CA9-8CE3-2AF76E033C9D@0000000000XX0.xml
D35: D17CCEC2-75A1-442B-B61E-911140F7E667 | E35: FC | F35: 894 | G35: 4 | H35: I - Ingreso | I35: 2025-03-05T20:25:58 | J35: 2025-03-05T20:25:57 | K35: 66260 | L35: MME1507071ZA | M35: MILLHOUSE MEXICO | N35: 601 - General de Ley Personas Morales | O35: FSA980318AL3 | P35: FAURECIA SISTEMAS AUTOMOTRICES DE MEXICO | Q35: G03 - Gastos en general | R35: 601 - General de Ley Personas Morales | S35: 72710 | T35: 99 - Por definir | U35: PPD | W35: SERVICIO LOGISTICO: TERRESTRE ORIGEN: AUBURN HILLS, MI DESTINO: CUARTO, PU PRO NUMBER: 1116306 OBSERVACIONES: XF2502KH9N / 7100172269 / 8200093765 | Y35: 4800 | AA35: 0 | AC35: 4800 | AD35: =Y35*AH35 -> 98079.84 | AE35: =VLOOKUP(D35,'FACTURAS INGRESOS'!$I$487:$P$718,8,0) -> 98079.84 | AF35: =AD35-AE35 -> 0 | AG35: USD | AH35: 20.4333 | AK35: 4800 | AV35: 1.0000007e+15 | AW35: 1.0000007e+15 | AX35: C:\AdminXML\BovedaCFDi\MME1507071ZA\Emitidas\2025\03\D17CCEC2-75A1-442B-B61E-911140F7E667@0000000000XX0.xml
D36: 91A751DB-0F15-4B91-8F6B-CB8E85FF7F5B | E36: FC | F36: 895 | G36: 4 | H36: I - Ingreso | I36: 2025-03-05T20:27:13 | J36: 2025-03-05T20:27:12 | K36: 66260 | L36: MME1507071ZA | M36: MILLHOUSE MEXICO | N36: 601 - General de Ley Personas Morales | O36: FSA980318AL3 | P36: FAURECIA SISTEMAS AUTOMOTRICES DE MEXICO | Q36: G03 - Gastos en general | R36: 601 - General de Ley Personas Morales | S36: 72710 | T36: 99 - Por definir | U36: PPD | W36: SERVICIO LOGISTICO: TERRESTRE ORIGEN: CUAUTLANCINGO CORREDOR EMPRESARIAL, PU DESTINO: TOLUCA, EM PRO NUMBER: 1116339 OBSERVACIONES: ID2502KI8M / 7100172313 / 8200093801 | Y36: 980 | AA36: 0 | AC36: 980 | AD36: =Y36*AH36 -> 20024.634 | AE36: =VLOOKUP(D36,'FACTURAS INGRESOS'!$I$487:$P$718,8,0) -> 20024.63 | AF36: =AD36-AE36 -> 0.004 | AG36: USD | AH36: 20.4333 | AK36: 980 | AV36: 1.0000007e+15 | AW36: 1.0000007e+15 | AX36: C:\AdminXML\BovedaCFDi\MME1507071ZA\Emitidas\2025\03\91A751DB-0F15-4B91-8F6B-CB8E85FF7F5B@0000000000XX0.xml
D37: 372E1343-2D6B-4BBB-AF9F-29A9124D25C5 | E37: FC | F37: 896 | G37: 4 | H37: I - Ingreso | I37: 2025-03-05T20:28:42 | J37: 2025-03-05T20:28:41 | K37: 66260 | L37: MME1507071ZA | M37: MILLHOUSE MEXICO | N37: 601 - General de Ley Personas Morales | O37: FSA980318AL3 | P37: FAURECIA SISTEMAS AUTOMOTRICES DE MEXICO | Q37: G03 - Gastos en general | R37: 601 - General de Ley Personas Morales | S37: 72710 | T37: 99 - Por definir | U37: PPD | W37: SERVICIO LOGISTICO: TERRESTRE ORIGEN: FRANKLIN, OH DESTINO: LOUISVILLE, KY PRO NUMBER: 1118772 OBSERVACIONES: XF2502ML86 / 7100174610 / 8200095236 | Y37: 980 | AA37: 0 | AC37: 980 | AD37: =Y37*AH37 -> 20024.634 | AE37: =VLOOKUP(D37,'FACTURAS INGRESOS'!$I$487:$P$718,8,0) -> 20024.63 | AF37: =AD37-AE37 -> 0.004 | AG37: USD | AH37: 20.4333 | AK37: 980 | AV37: 1.0000007e+15 | AW37: 1.0000007e+15 | AX37: C:\AdminXML\BovedaCFDi\MME1507071ZA\Emitidas\2025\03\372E1343-2D6B-4BBB-AF9F-29A9124D25C5@0000000000XX0.xml
D38: 62C8C3A2-39FF-466C-9A38-4CE277C3AE85 | E38: FC | F38: 897 | G38: 4 | H38: I - Ingreso | I38: 2025-03-05T20:31:22 | J38: 2025-03-05T20:31:18 | K38: 66260 | L38: MME1507071ZA | M38: MILLHOUSE MEXICO | N38: 601 - General de Ley Personas Morales | O38: FSA980318AL3 | P38: FAURECIA SISTEMAS AUTOMOTRICES DE MEXICO | Q38: G03 - Gastos en general | R38: 601 - General de Ley Personas Morales | S38: 72710 | T38: 99 - Por definir | U38: PPD | W38: SERVICIO LOGISTICO: TERRESTRE ORIGEN: JACKSON, MI DESTINO: FRANKLIN, OH PRO NUMBER: 1119360 OBSERVACIONES: ID2502NBKD / 7100173957 / 8200095561 | Y38: 400 | AA38: 0 | AC38: 400 | AD38: =Y38*AH38 -> 8173.32 | AE38: =VLOOKUP(D38,'FACTURAS INGRESOS'!$I$487:$P$718,8,0) -> 8173.32 | AF38: =AD38-AE38 -> 0 | AG38: USD | AH38: 20.4333 | AK38: 400 | AV38: 1.0000007e+15 | AW38: 1.0000007e+15 | AX38: C:\AdminXML\BovedaCFDi\MME1507071ZA\Emitidas\2025\03\62C8C3A2-39FF-466C-9A38-4CE277C3AE85@0000000000XX0.xml
D39: 525572EE-0573-4F99-B544-13FEE972F46D | E39: FC | F39: 898 | G39: 4 | H39: I - Ingreso | I39: 2025-03-05T20:32:30 | J39: 2025-03-05T20:32:29 | K39: 66260 | L39: MME1507071ZA | M39: MILLHOUSE MEXICO | N39: 601 - General de Ley Personas Morales | O39: FSA980318AL3 | P39: FAURECIA SISTEMAS AUTOMOTRICES DE MEXICO | Q39: G03 - Gastos en general | R39: 601 - General de Ley Personas Morales | S39: 72710 | T39: 99 - Por definir | U39: PPD | W39: SERVICIO LOGISTICO: TERRESTRE ORIGEN: EDINBURGH, IN DESTINO: TOLEDO, OH PRO NUMBER: 1119513 OBSERVACIONES: ID2502ND8J / 7100174108 / 8200094685 | Y39: 800 | AA39: 0 | AC39: 800 | AD39: =Y39*AH39 -> 16346.64 | AE39: =VLOOKUP(D39,'FACTURAS INGRESOS'!$I$487:$P$718,8,0) -> 16346.64 | AF39: =AD39-AE39 -> 0 | AG39: USD | AH39: 20.4333 | AK39: 800 | AV39: 1.0000007e+15 | AW39: 1.0000007e+15 | AX39: C:\AdminXML\BovedaCFDi\MME1507071ZA\Emitidas\2025\03\525572EE-0573-4F99-B544-13FEE972F46D@0000000000XX0.xml
D40: 7E076868-F5F9-4DEF-BB1F-DB439CBCB398 | E40: FC | F40: 899 | G40: 4 | H40: I - Ingreso | I40: 2025-03-05T20:33:42 | J40: 2025-03-05T20:33:41 | K40: 66260 | L40: MME1507071ZA | M40: MILLHOUSE MEXICO | N40: 601 - General de Ley Personas Morales | O40: FSA980318AL3 | P40: FAURECIA SISTEMAS AUTOMOTRICES DE MEXICO | Q40: G03 - Gastos en general | R40: 601 - General de Ley Personas Morales | S40: 72710 | T40: 99 - Por definir | U40: PPD | W40: SERVICIO LOGISTICO: TERRESTRE ORIGEN: ROCHESTER, MI DESTINO: LAREDO, TX PRO NUMBER: 1119782 OBSERVACIONES: ID2502NJCH / 7100174159 / 8200095783 | Y40: 1800 | AA40: 0 | AC40: 1800 | AD40: =Y40*AH40 -> 36779.94 | AE40: =VLOOKUP(D40,'FACTURAS INGRESOS'!$I$487:$P$718,8,0) -> 36779.94 | AF40: =AD40-AE40 -> 0 | AG40: USD | AH40: 20.4333 | AK40: 1800 | AV40: 1.0000007e+15 | AW40: 1.0000007e+15 | AX40: C:\AdminXML\BovedaCFDi\MME1507071ZA\Emitidas\2025\03\7E076868-F5F9-4DEF-BB1F-DB439CBCB398@0000000000XX0.xml
D41: 03205FE7-9532-4732-B1F9-EFEC56231945 | E41: FC | F41: 900 | G41: 4 | H41: I - Ingreso | I41: 2025-03-05T20:35:04 | J41: 2025-03-05T20:35:03 | K41: 66260 | L41: MME1507071ZA | M41: MILLHOUSE MEXICO | N41: 601 - General de Ley Personas Morales | O41: FSA980318AL3 | P41: FAURECIA SISTEMAS AUTOMOTRICES DE MEXICO | Q41: G03 - Gastos en general | R41: 601 - General de Ley Personas Morales | S41: 72710 | T41: 99 - Por definir | U41: PPD | W41: SERVICIO LOGISTICO: TERRESTRE ORIGEN: FRANKLIN, OH DESTINO: DEXTER, MO PRO NUMBER: 1120176 OBSERVACIONES: XF25020387 / 7100174365 / 8200095917 | Y41: 1250 | AA41: 0 | AC41: 1250 | AD41: =Y41*AH41 -> 25541.625 | AE41: =VLOOKUP(D41,'FACTURAS INGRESOS'!$I$487:$P$718,8,0) -> 25541.63 | AF41: =AD41-AE41 -> -0.005 | AG41: USD | AH41: 20.4333 | AK41: 1250 | AV41: 1.0000007e+15 | AW41: 1.0000007e+15 | AX41: C:\AdminXML\BovedaCFDi\MME1507071ZA\Emitidas\2025\03\03205FE7-9532-4732-B1F9-EFEC56231945@0000000000XX0.xml
D42: ACCBE841-2EF4-4B2A-AC46-336C20D9DE8D | E42: FC | F42: 901 | G42: 4 | H42: I - Ingreso | I42: 2025-03-05T20:36:40 | J42: 2025-03-05T20:36:37 | K42: 66260 | L42: MME1507071ZA | M42: MILLHOUSE MEXICO | N42: 601 - General de Ley Personas Morales | O42: FSA980318AL3 | P42: FAURECIA SISTEMAS AUTOMOTRICES DE MEXICO | Q42: G03 - Gastos en general | R42: 601 - General de Ley Personas Morales | S42: 72710 | T42: 99 - Por definir | U42: PPD | W42: SERVICIO LOGISTICO: TERRESTRE ORIGEN: COLUMBUS, IN DESTINO: LAREDO, TX PRO NUMBER: 1045988 OBSERVACIONES: ID2406ME5J / 7100142882 / 8200088286 | Y42: 50 | AA42: 0 | AC42: 50 | AD42: =Y42*AH42 -> 1021.665 | AE42: =VLOOKUP(D42,'FACTURAS INGRESOS'!$I$487:$P$718,8,0) -> 1021.67 | AF42: =AD42-AE42 -> -0.005 | AG42: USD | AH42: 20.4333 | AK42: 50 | AV42: 1.0000007e+15 | AW42: 1.0000007e+15 | AX42: C:\AdminXML\BovedaCFDi\MME1507071ZA\Emitidas\2025\03\ACCBE841-2EF4-4B2A-AC46-336C20D9DE8D@0000000000XX0.xml
... D77: 8F179BB6-6521-4BFB-8003-83B0C1548C5C | E77: FC | F77: 936 | G77: 4 | H77: I - Ingreso | I77: 2025-03-05T21:42:15 | J77: 2025-03-05T21:42:14 | K77: 66260 | L77: MME1507071ZA | M77: MILLHOUSE MEXICO | N77: 601 - General de Ley Personas Morales | O77: XEXX010101000 | P77: FAURECIA INTERIOR SYSTEMS INC, US17 | Q77: S01 - Sin efectos fiscales | R77: 616 - Sin obligaciones fiscales | S77: 66260 | T77: 99 - Por definir | U77: PPD | W77: SERVICIO LOGISTICO: TERRESTRE ORIGEN: CEDAR SPRINGS, MI DESTINO: SPRING HILL, TN PRO NUMBER: 1117700 OBSERVACIONES: XF2502LN9N / 7100173877 / 8200094661 | Y77: 1250 | AA77: 0 | AC77: 1250 | AD77: =Y77*AH77 -> 25541.625 | AE77: =VLOOKUP(D77,'FACTURAS INGRESOS'!$I$487:$P$718,8,0) -> 25541.63 | AF77: =AD77-AE77 -> -0.005 | AG77: USD | AH77: 20.4333 | AK77: 1250 | AV77: 1.0000007e+15 | AW77: 1.0000007e+15 | AX77: C:\AdminXML\BovedaCFDi\MME1507071ZA\Emitidas\2025\03\8F179BB6-6521-4BFB-8003-83B0C1548C5C@0000000000XX0.xml
D78: 8B0897B8-4996-4209-B01E-26ECCAE3FE15 | E78: F | F78: F4502 | G78: 4 | H78: I - Ingreso | I78: 2025-03-06T16:44:04 | J78: 2025-03-06T16:43:05 | K78: 66260 | L78: MME1507071ZA | M78: MILLHOUSE MEXICO | N78: 601 - General de Ley Personas Morales | O78: CFO030723285 | P78: CONTINENTE FORWARDING | Q78: G03 - Gastos en general | R78: 601 - General de Ley Personas Morales | S78: 66260 | T78: 99 - Por definir | U78: PPD | W78: SERVICIO LOGISTICO: TERRESTRE ORIGEN: LAREDO, TX DESTINO: FORT WORTH, TX PRO NUMBER: 1121531 OBSERVACIONES: C45659 | Y78: 1480 | Z78: 0 | AA78: 0 | AC78: 1480 | AD78: =Y78*AH78 -> 30860.664 | AE78: =VLOOKUP(D78,'FACTURAS INGRESOS'!$I$487:$P$718,8,0) -> 30860.66 | AF78: =AD78-AE78 -> 0.004 | AG78: USD | AH78: 20.8518 | AK78: 1480 | AV78: 1.0000007e+15 | AW78: 1.0000007e+15 | AX78: C:\AdminXML\BovedaCFDi\MME1507071ZA\Emitidas\2025\03\8B0897B8-4996-4209-B01E-26ECCAE3FE15@0000000000XX0.xml
D79: C357E9D8-C224-456E-8F38-761E1AEB479A | E79: F | F79: F4503 | G79: 4 | H79: I - Ingreso | I79: 2025-03-06T16:45:47 | J79: 2025-03-06T16:44:36 | K79: 66260 | L79: MME1507071ZA | M79: MILLHOUSE MEXICO | N79: 601 - General de Ley Personas Morales | O79: XEXX010101000 | P79: JABIL EMS SWITZERLAND | Q79: S01 - Sin efectos fiscales | R79: 616 - Sin obligaciones fiscales | S79: 66260 | T79: 99 - Por definir | U79: PPD | W79: SERVICIO LOGISTICO: AEREO ORIGEN: MORGAN HILL, CA DESTINO: BELLAVISTA, JA PRO NUMBER: 1121616 OBSERVACIONES: HANDCARRY NPI 3/3 | Y79: 1595 | Z79: 0 | AA79: 0 | AC79: 1595 | AD79: =Y79*AH79 -> 33258.621 | AE79: =VLOOKUP(D79,'FACTURAS INGRESOS'!$I$487:$P$718,8,0) -> 33258.62 | AF79: =AD79-AE79 -> 0.001 | AG79: USD | AH79: 20.8518 | AK79: 1595 | AV79: 1.0000007e+15 | AW79: 1.0000007e+15 | AX79: C:\AdminXML\BovedaCFDi\MME1507071ZA\Emitidas\2025\03\C357E9D8-C224-456E-8F38-761E1AEB479A@0000000000XX0.xml
D80: 6A21B7C3-AA54-4DD2-8DF1-104B30231708 | E80: F | F80: F4504 | G80: 4 | H80: I - Ingreso | I80: 2025-03-06T16:47:22 | J80: 2025-03-06T16:46:22 | K80: 66260 | L80: MME1507071ZA | M80: MILLHOUSE MEXICO | N80: 601 - General de Ley Personas Morales | O80: USI970903M23 | P80: UNIVERSAL SCIENTIFIC INDUSTRIAL DE MEXICO | Q80: G03 - Gastos en general | R80: 601 - General de Ley Personas Morales | S80: 44300 | T80: 99 - Por definir | U80: PPD | W80: SERVICIO LOGISTICO: TERRESTRE ORIGEN: JARDINES DE SANTA ISABEL, JA DESTINO: ELK GROVE VILLAGE, IL PRO NUMBER: 1121167 OBSERVACIONES: 1121167 | Y80: 7750 | Z80: 0 | AA80: 0 | AC80: 7750 | AD80: =Y80*AH80 -> 161601.45 | AE80: =VLOOKUP(D80,'FACTURAS INGRESOS'!$I$487:$P$718,8,0) -> 161601.45 | AF80: =AD80-AE80 -> 0 | AG80: USD | AH80: 20.8518 | AK80: 7750 | AV80: 1.0000007e+15 | AW80: 1.0000007e+15 | AX80: C:\AdminXML\BovedaCFDi\MME1507071ZA\Emitidas\2025\03\6A21B7C3-AA54-4DD2-8DF1-104B30231708@0000000000XX0.xml
D81: 79509601-E377-495B-A105-E78021BF8DF8 | E81: F | F81: F4505 | G81: 4 | H81: I - Ingreso | I81: 2025-03-07T22:35:56 | J81: 2025-03-07T22:34:21 | K81: 66260 | L81: MME1507071ZA | M81: MILLHOUSE MEXICO | N81: 601 - General de Ley Personas Morales | O81: CFM970129RG7 | P81: CEVA FREIGHT MANAGEMENT MEXICO | Q81: G03 - Gastos en general | R81: 601 - General de Ley Personas Morales | S81: 3720 | T81: 99 - Por definir | U81: PPD | W81: SERVICIO LOGISTICO: TERRESTRE ORIGEN: MANZANILLO, CL DESTINO: CHIHUAHUA, CI PRO NUMBER: 1122141 OBSERVACIONES: 1443820009825 | Y81: 53800 | Z81: 0 | AA81: 8608 | AC81: 62408 | AD81: =Y81*AH81 -> 53800 | AE81: =VLOOKUP(D81,'FACTURAS INGRESOS'!$I$487:$P$718,8,0) -> 53800 | AF81: =AD81-AE81 -> 0 | AG81: MXN | AH81: 1 | AM81: 8608 | AV81: 1.0000007e+15 | AW81: 1.0000007e+15 | AX81: C:\AdminXML\BovedaCFDi\MME1507071ZA\Emitidas\2025\03\79509601-E377-495B-A105-E78021BF8DF8@0000000000XX0.xml
D82: 90ED0FE1-DCD7-4E75-983C-A1FB8FDBD441 | E82: F | F82: F4506 | G82: 4 | H82: I - Ingreso | I82: 2025-03-07T22:37:41 | J82: 2025-03-07T22:36:39 | K82: 66260 | L82: MME1507071ZA | M82: MILLHOUSE MEXICO | N82: 601 - General de Ley Personas Morales | O82: CFO030723285 | P82: CONTINENTE FORWARDING | Q82: G03 - Gastos en general | R82: 601 - General de Ley Personas Morales | S82: 66260 | T82: 99 - Por definir | U82: PPD | W82: SERVICIO LOGISTICO: TERRESTRE ORIGEN: SAINT LOUIS, MO DESTINO: LAREDO, TX PRO NUMBER: 1121796 OBSERVACIONES: C46010 | Y82: 2250 | Z82: 0 | AA82: 0 | AC82: 2250 | AD82: =Y82*AH82 -> 45875.925 | AE82: =VLOOKUP(D82,'FACTURAS INGRESOS'!$I$487:$P$718,8,0) -> 45875.92 | AF82: =AD82-AE82 -> 0.005 | AG82: USD | AH82: 20.3893 | AK82: 2250 | AV82: 1.0000007e+15 | AW82: 1.0000007e+15 | AX82: C:\AdminXML\BovedaCFDi\MME1507071ZA\Emitidas\2025\03\90ED0FE1-DCD7-4E75-983C-A1FB8FDBD441@0000000000XX0.xml
D83: 736C44D5-03CA-41CA-AE8E-69E51831EF16 | E83: F | F83: F4507 | G83: 4 | H83: I - Ingreso | I83: 2025-03-07T22:58:47 | J83: 2025-03-07T22:52:08 | K83: 66260 | L83: MME1507071ZA | M83: MILLHOUSE MEXICO | N83: 601 - General de Ley Personas Morales | O83: IMG860612JKA | P83: INGENIERIA Y MAQUINARIA DE GUADALUPE | Q83: G03 - Gastos en general | R83: 601 - General de Ley Personas Morales | S83: 25870 | T83: 99 - Por definir | U83: PPD | W83: SERVICIO LOGISTICO: MARITIMO ORIGEN: DENAMARK, XX DESTINO: CASTAÑOS CENTRO, CU PRO NUMBER: 1060077 OBSERVACIONES: OC2024007401A / FLETE MARITIMO | SERVICIO LOGISTICO: MARITIMO ORIGEN: DENAMARK, XX DESTINO: CASTAÑOS CENTRO, CU PRO NUMBER: 1060077 OBSERVACIONES: TRANSPORTE DE ORIGEN | SERVICIO LOGISTICO: MARITIMO ORIGEN: DENAMARK, XX DESTINO: CASTAÑOS CENTRO, CU PRO NUMBER: 1060077 OBSERVACIONES: GASTOS DE ORIGEN | SERVICIO LOGISTICO: MARITIMO ORIGEN: DENAMARK, XX DESTINO: CASTAÑOS CENTRO, CU PRO NUMBER: 1060077 OBSERVACIONES: GASTOS DE DESTINO | Y83: 1642 | Z83: 0 | AA83: 0 | AC83: 1642 | AD83: =Y83*AH83 -> 33479.231 | AE83: =VLOOKUP(D83,'FACTURAS INGRESOS'!$I$487:$P$718,8,0) -> 33479.23 | AF83: =AD83-AE83 -> 0.00059999999 | AG83: USD | AH83: 20.3893 | AK83: 1642 | AV83: 1.0000007e+15 | AW83: 1.0000007e+15 | AX83: C:\AdminXML\BovedaCFDi\MME1507071ZA\Emitidas\2025\03\736C44D5-03CA-41CA-AE8E-69E51831EF16@0000000000XX0.xml
D84: 7D729255-2B9F-4B99-95C0-133D2930E360 | E84: F | F84: F4508 | G84: 4 | H84: I - Ingreso | I84: 2025-03-07T23:13:21 | J84: 2025-03-07T23:01:11 | K84: 66260 | L84: MME1507071ZA | M84: MILLHOUSE MEXICO | N84: 601 - General de Ley Personas Morales | O84: CFO030723285 | P84: CONTINENTE FORWARDING | Q84: G03 - Gastos en general | R84: 601 - General de Ley Personas Morales | S84: 66260 | T84: 99 - Por definir | U84: PPD | W84: SERVICIO LOGISTICO: TERRESTRE ORIGEN: HARRISON, OH DESTINO: LAREDO, TX PRO NUMBER: 1121406 OBSERVACIONES: C45923 | Y84: 2400 | Z84: 0 | AA84: 0 | AC84: 2400 | AD84: =Y84*AH84 -> 48934.32 | AE84: =VLOOKUP(D84,'FACTURAS INGRESOS'!$I$487:$P$718,8,0) -> 48934.32 | AF84: =AD84-AE84 -> 0 | AG84: USD | AH84: 20.3893 | AK84: 2400 | AV84: 1.0000007e+15 | AW84: 1.0000007e+15 | AX84: C:\AdminXML\BovedaCFDi\MME1507071ZA\Emitidas\2025\03\7D729255-2B9F-4B99-95C0-133D2930E360@0000000000XX0.xml
D85: 0EA2A574-EACB-4271-81CD-F04C20A9E40A | E85: FC | F85: 937 | G85: 4 | H85: I - Ingreso | I85: 2025-03-07T23:03:03 | J85: 2025-03-07T23:02:39 | K85: 66260 | L85: MME1507071ZA | M85: MILLHOUSE MEXICO | N85: 601 - General de Ley Personas Morales | O85: FSA980318AL3 | P85: FAURECIA SISTEMAS AUTOMOTRICES DE MEXICO | Q85: G03 - Gastos en general | R85: 601 - General de Ley Personas Morales | S85: 72710 | T85: 99 - Por definir | U85: PPD | W85: SERVICIO LOGISTICO: TERRESTRE ORIGEN: INDIANAPOLIS, IN DESTINO: FRANKLIN, OH PRO NUMBER: 1029834 OBSERVACIONES: XF2405DF21 / 7100173765 / 8200095997 | Y85: 850 | AA85: 0 | AC85: 850 | AD85: =Y85*AH85 -> 17330.905 | AE85: =VLOOKUP(D85,'FACTURAS INGRESOS'!$I$487:$P$718,8,0) -> 17330.91 | AF85: =AD85-AE85 -> -0.005 | AG85: USD | AH85: 20.3893 | AK85: 850 | AV85: 1.0000007e+15 | AW85: 1.0000007e+15 | AX85: C:\AdminXML\BovedaCFDi\MME1507071ZA\Emitidas\2025\03\0EA2A574-EACB-4271-81CD-F04C20A9E40A@0000000000XX0.xml
D86: D6C75A04-D86A-4BCE-984D-DD88361442A5 | E86: FC | F86: 938 | G86: 4 | H86: I - Ingreso | I86: 2025-03-07T23:04:32 | J86: 2025-03-07T23:04:29 | K86: 66260 | L86: MME1507071ZA | M86: MILLHOUSE MEXICO | N86: 601 - General de Ley Personas Morales | O86: FSA980318AL3 | P86: FAURECIA SISTEMAS AUTOMOTRICES DE MEXICO | Q86: G03 - Gastos en general | R86: 601 - General de Ley Personas Morales | S86: 72710 | T86: 99 - Por definir | U86: PPD | W86: SERVICIO LOGISTICO: TERRESTRE ORIGEN: COLUMBUS, IN DESTINO: FRANKLIN, OH PRO NUMBER: 1035259 OBSERVACIONES: XF2405GAMJ / 7100173719 / 8200096006 | Y86: 720 | AA86: 0 | AC86: 720 | AD86: =Y86*AH86 -> 14680.296 | AE86: =VLOOKUP(D86,'FACTURAS INGRESOS'!$I$487:$P$718,8,0) -> 14680.3 | AF86: =AD86-AE86 -> -0.004 | AG86: USD | AH86: 20.3893 | AK86: 720 | AV86: 1.0000007e+15 | AW86: 1.0000007e+15 | AX86: C:\AdminXML\BovedaCFDi\MME1507071ZA\Emitidas\2025\03\D6C75A04-D86A-4BCE-984D-DD88361442A5@0000000000XX0.xml
D87: 8E9321B0-2E77-43F0-9020-E5163D68BF7E | E87: FC | F87: 939 | G87: 4 | H87: I - Ingreso | I87: 2025-03-07T23:06:33 | J87: 2025-03-07T23:06:09 | K87: 66260 | L87: MME1507071ZA | M87: MILLHOUSE MEXICO | N87: 601 - General de Ley Personas Morales | O87: FSA980318AL3 | P87: FAURECIA SISTEMAS AUTOMOTRICES DE MEXICO | Q87: G03 - Gastos en general | R87: 601 - General de Ley Personas Morales | S87: 72710 | T87: 99 - Por definir | U87: PPD | W87: SERVICIO LOGISTICO: TERRESTRE ORIGEN: QUERÉTARO, QA DESTINO: FORT WAYNE, IN PRO NUMBER: 1042756 OBSERVACIONES: XF2406K9M0 / 7100173834 / 8200096000 | Y87: 6400 | AA87: 0 | AC87: 6400 | AD87: =Y87*AH87 -> 130491.52 | AE87: =VLOOKUP(D87,'FACTURAS INGRESOS'!$I$487:$P$718,8,0) -> 130491.52 | AF87: =AD87-AE87 -> 0 | AG87: USD | AH87: 20.3893 | AK87: 6400 | AV87: 1.0000007e+15 | AW87: 1.0000007e+15 | AX87: C:\AdminXML\BovedaCFDi\MME1507071ZA\Emitidas\2025\03\8E9321B0-2E77-43F0-9020-E5163D68BF7E@0000000000XX0.xml
D88: 7763C5EC-D4C3-477F-BA56-80AD6379D73B | E88: FC | F88: 940 | G88: 4 | H88: I - Ingreso | I88: 2025-03-07T23:08:02 | J88: 2025-03-07T23:07:59 | K88: 66260 | L88: MME1507071ZA | M88: MILLHOUSE MEXICO | N88: 601 - General de Ley Personas Morales | O88: FSA980318AL3 | P88: FAURECIA SISTEMAS AUTOMOTRICES DE MEXICO | Q88: G03 - Gastos en general | R88: 601 - General de Ley Personas Morales | S88: 72710 | T88: 99 - Por definir | U88: PPD | W88: SERVICIO LOGISTICO: TERRESTRE ORIGEN: FORT LORAMIE, OH DESTINO: FRANKLIN, OH PRO NUMBER: 1080354 OBSERVACIONES: ID2409I9CN / 7100155678 / 8200095954 | Y88: 300 | AA88: 0 | AC88: 300 | AD88: =Y88*AH88 -> 6116.79 | AE88: =VLOOKUP(D88,'FACTURAS INGRESOS'!$I$487:$P$718,8,0) -> 6116.79 | AF88: =AD88-AE88 -> 0 | AG88: USD | AH88: 20.3893 | AK88: 300 | AV88: 1.0000007e+15 | AW88: 1.0000007e+15 | AX88: C:\AdminXML\BovedaCFDi\MME1507071ZA\Emitidas\2025\03\7763C5EC-D4C3-477F-BA56-80AD6379D73B@0000000000XX0.xml
D89: 04F6B336-D24A-4759-996F-C83F5E4FA77A | E89: FC | F89: 941 | G89: 4 | H89: I - Ingreso | I89: 2025-03-07T23:09:26 | J89: 2025-03-07T23:09:23 | K89: 66260 | L89: MME1507071ZA | M89: MILLHOUSE MEXICO | N89: 601 - General de Ley Personas Morales | O89: FSA980318AL3 | P89: FAURECIA SISTEMAS AUTOMOTRICES DE MEXICO | Q89: G03 - Gastos en general | R89: 601 - General de Ley Personas Morales | S89: 72710 | T89: 99 - Por definir | U89: PPD | W89: SERVICIO LOGISTICO: TERRESTRE ORIGEN: LEXINGTON, MI DESTINO: LEXINGTON, MI PRO NUMBER: 1068489 OBSERVACIONES: XF24089A7C / 7100152962 / 8200077783 | Y89: 1862 | AA89: 0 | AC89: 1862 | AD89: =Y89*AH89 -> 37964.877 | AE89: =VLOOKUP(D89,'FACTURAS INGRESOS'!$I$487:$P$718,8,0) -> 37964.88 | AF89: =AD89-AE89 -> -0.0034 | AG89: USD | AH89: 20.3893 | AK89: 1862 | AV89: 1.0000007e+15 | AW89: 1.0000007e+15 | AX89: C:\AdminXML\BovedaCFDi\MME1507071ZA\Emitidas\2025\03\04F6B336-D24A-4759-996F-C83F5E4FA77A@0000000000XX0.xml
D90: 78C3AE4F-4B20-406D-893D-5E8DDB505060 | E90: FC | F90: 942 | G90: 4 | H90: I - Ingreso | I90: 2025-03-07T23:11:33 | J90: 2025-03-07T23:11:09 | K90: 66260 | L90: MME1507071ZA | M90: MILLHOUSE MEXICO | N90: 601 - General de Ley Personas Morales | O90: FSA980318AL3 | P90: FAURECIA SISTEMAS AUTOMOTRICES DE MEXICO | Q90: G03 - Gastos en general | R90: 601 - General de Ley Personas Morales | S90: 72710 | T90: 99 - Por definir | U90: PPD | W90: SERVICIO LOGISTICO: TERRESTRE ORIGEN: AUBURN HILLS, MI DESTINO: CUARTO, PU PRO NUMBER: 1116306 OBSERVACIONES: XF2502KH9N / 7100172269 / 8200095909 | Y90: 160 | AA90: 0 | AC90: 160 | AD90: =Y90*AH90 -> 3262.288 | AE90: =VLOOKUP(D90,'FACTURAS INGRESOS'!$I$487:$P$718,8,0) -> 3262.29 | AF90: =AD90-AE90 -> -0.002 | AG90: USD | AH90: 20.3893 | AK90: 160 | AV90: 1.0000007e+15 | AW90: 1.0000007e+15 | AX90: C:\AdminXML\BovedaCFDi\MME1507071ZA\Emitidas\2025\03\78C3AE4F-4B20-406D-893D-5E8DDB505060@0000000000XX0.xml
D91: 88D9DE8D-0B63-4BB8-B941-26C3C7E97FB0 | E91: F | F91: F4509 | G91: 4 | H91: I - Ingreso | I91: 2025-03-07T23:14:58 | J91: 2025-03-07T23:14:03 | K91: 66260 | L91: MME1507071ZA | M91: MILLHOUSE MEXICO | N91: 601 - General de Ley Personas Morales | O91: CFO030723285 | P91: CONTINENTE FORWARDING | Q91: G03 - Gastos en general | R91: 601 - General de Ley Personas Morales | S91: 66260 | T91: 99 - Por definir | U91: PPD | W91: SERVICIO LOGISTICO: TERRESTRE ORIGEN: CHINO, CA DESTINO: MCALLEN, TX PRO NUMBER: 1121745 OBSERVACIONES: C45849 | Y91: 2500 | Z91: 0 | AA91: 0 | AC91: 2500 | AD91: =Y91*AH91 -> 50973.25 | AE91: =VLOOKUP(D91,'FACTURAS INGRESOS'!$I$487:$P$718,8,0) -> 50973.25 | AF91: =AD91-AE91 -> 0 | AG91: USD | AH91: 20.3893 | AK91: 2500 | AV91: 1.0000007e+15 | AW91: 1.0000007e+15 | AX91: C:\AdminXML\BovedaCFDi\MME1507071ZA\Emitidas\2025\03\88D9DE8D-0B63-4BB8-B941-26C3C7E97FB0@0000000000XX0.xml
D92: 62FA74E2-69B3-44DA-8F24-55A3F193D021 | E92: F | F92: F4510 | G92: 4 | H92: I - Ingreso | I92: 2025-03-07T23:16:50 | J92: 2025-03-07T23:15:45 | K92: 66260 | L92: MME1507071ZA | M92: MILLHOUSE MEXICO | N92: 601 - General de Ley Personas Morales | O92: EOP640608I13 | P92: HELLA AUTOMOTIVE MEXICO | Q92: G03 - Gastos en general | R92: 601 - General de Ley Personas Morales | S92: 45601 | T92: 99 - Por definir | U92: PPD | W92: SERVICIO LOGISTICO: AEREO ORIGEN: WEMBACH, XX DESTINO: EL SALTO CENTRO, JA PRO NUMBER: 1121443 OBSERVACIONES: PL6-AIR25-INC1-0039-1621-573040USD-573042MXN | Y92: 7422 | Z92: 0 | AA92: 0 | AC92: 7422 | AD92: =Y92*AH92 -> 151329.38 | AE92: =VLOOKUP(D92,'FACTURAS INGRESOS'!$I$487:$P$718,8,0) -> 151329.38 | AF92: =AD92-AE92 -> 0.0046 | AG92: USD | AH92: 20.3893 | AK92: 7422 | AV92: 1.0000007e+15 | AW92: 1.0000007e+15 | AX92: C:\AdminXML\BovedaCFDi\MME1507071ZA\Emitidas\2025\03\62FA74E2-69B3-44DA-8F24-55A3F193D021@0000000000XX0.xml
D93: BEE0C0E0-A604-4180-AD3E-E68D815AE601 | E93: F | F93: F4511 | G93: 4 | H93: I - Ingreso | I93: 2025-03-07T23:18:14 | J93: 2025-03-07T23:17:20 | K93: 66260 | L93: MME1507071ZA | M93: MILLHOUSE MEXICO | N93: 601 - General de Ley Personas Morales | O93: EOP640608I13 | P93: HELLA AUTOMOTIVE MEXICO | Q93: G03 - Gastos en general | R93: 601 - General de Ley Personas Morales | S93: 45601 | T93: 99 - Por definir | U93: PPD | W93: SERVICIO LOGISTICO: TERRESTRE ORIGEN: LAREDO, TX DESTINO: VANCE, AL PRO NUMBER: 1121500 OBSERVACIONES: PL7-OV25-OUTC1-00357-4514-639208-USD | Y93: 3260 | Z93: 0 | AA93: 0 | AC93: 3260 | AD93: =Y93*AH93 -> 66469.118 | AE93: =VLOOKUP(D93,'FACTURAS INGRESOS'!$I$487:$P$718,8,0) -> 66469.12 | AF93: =AD93-AE93 -> -0.002 | AG93: USD | AH93: 20.3893 | AK93: 3260 | AV93: 1.0000007e+15 | AW93: 1.0000007e+15 | AX93: C:\AdminXML\BovedaCFDi\MME1507071ZA\Emitidas\2025\03\BEE0C0E0-A604-4180-AD3E-E68D815AE601@0000000000XX0.xml
D94: BEB4B58D-7852-407A-8AE3-1C3A7FA34374 | E94: F | F94: F4512 | G94: 4 | H94: I - Ingreso | I94: 2025-03-07T23:19:42 | J94: 2025-03-07T23:18:42 | K94: 66260 | L94: MME1507071ZA | M94: MILLHOUSE MEXICO | N94: 601 - General de Ley Personas Morales | O94: EOP640608I13 | P94: HELLA AUTOMOTIVE MEXICO | Q94: G03 - Gastos en general | R94: 601 - General de Ley Personas Morales | S94: 45601 | T94: 99 - Por definir | U94: PPD | W94: SERVICIO LOGISTICO: TERRESTRE ORIGEN: LAREDO, TX DESTINO: VANCE, AL PRO NUMBER: 1121502 OBSERVACIONES: PL7-OV25-OUTC1-00358-4514-639208-USD | Y94: 3180 | Z94: 0 | AA94: 0 | AC94: 3180 | AD94: =Y94*AH94 -> 64837.974 | AE94: =VLOOKUP(D94,'FACTURAS INGRESOS'!$I$487:$P$718,8,0) -> 64837.97 | AF94: =AD94-AE94 -> 0.004 | AG94: USD | AH94: 20.3893 | AK94: 3180 | AV94: 1.0000007e+15 | AW94: 1.0000007e+15 | AX94: C:\AdminXML\BovedaCFDi\MME1507071ZA\Emitidas\2025\03\BEB4B58D-7852-407A-8AE3-1C3A7FA34374@0000000000XX0.xml
D95: C734B122-9879-49D4-947D-C4C5C0C9959B | E95: F | F95: F4513 | G95: 4 | H95: I - Ingreso | I95: 2025-03-07T23:21:17 | J95: 2025-03-07T23:20:24 | K95: 66260 | L95: MME1507071ZA | M95: MILLHOUSE MEXICO | N95: 601 - General de Ley Personas Morales | O95: EOP640608I13 | P95: HELLA AUTOMOTIVE MEXICO | Q95: G03 - Gastos en general | R95: 601 - General de Ley Personas Morales | S95: 45601 | T95: 99 - Por definir | U95: PPD | W95: SERVICIO LOGISTICO: TERRESTRE ORIGEN: LAREDO, TX DESTINO: VANCE, AL PRO NUMBER: 1121503 OBSERVACIONES: PL7-OV25-OUTC1-00365-4514-639208-USD | Y95: 3340 | Z95: 0 | AA95: 0 | AC95: 3340 | AD95: =Y95*AH95 -> 68100.262 | AE95: =VLOOKUP(D95,'FACTURAS INGRESOS'!$I$487:$P$718,8,0) -> 68100.26 | AF95: =AD95-AE95 -> 0.002 | AG95: USD | AH95: 20.3893 | AK95: 3340 | AV95: 1.0000007e+15 | AW95: 1.0000007e+15 | AX95: C:\AdminXML\BovedaCFDi\MME1507071ZA\Emitidas\2025\03\C734B122-9879-49D4-947D-C4C5C0C9959B@0000000000XX0.xml
D96: 32AA2A84-F517-41A3-B006-898B3C01436E | E96: F | F96: F4514 | G96: 4 | H96: I - Ingreso | I96: 2025-03-07T23:23:03 | J96: 2025-03-07T23:21:54 | K96: 66260 | L96: MME1507071ZA | M96: MILLHOUSE MEXICO | N96: 601 - General de Ley Personas Morales | O96: EOP640608I13 | P96: HELLA AUTOMOTIVE MEXICO | Q96: G03 - Gastos en general | R96: 601 - General de Ley Personas Morales | S96: 45601 | T96: 99 - Por definir | U96: PPD | W96: SERVICIO LOGISTICO: TERRESTRE ORIGEN: LAREDO, TX DESTINO: VANCE, AL PRO NUMBER: 1121504 OBSERVACIONES: PL7-OV25-OUTC1-00366-4514-639208-USD | Y96: 3340 | Z96: 0 | AA96: 0 | AC96: 3340 | AD96: =Y96*AH96 -> 68100.262 | AE96: =VLOOKUP(D96,'FACTURAS INGRESOS'!$I$487:$P$718,8,0) -> 68100.26 | AF96: =AD96-AE96 -> 0.002 | AG96: USD | AH96: 20.3893 | AK96: 3340 | AV96: 1.0000007e+15 | AW96: 1.0000007e+15 | AX96: C:\AdminXML\BovedaCFDi\MME1507071ZA\Emitidas\2025\03\32AA2A84-F517-41A3-B006-898B3C01436E@0000000000XX0.xml
D97: E2FD7311-BDC3-40B5-8550-EB093063958D | E97: F | F97: F4515 | G97: 4 | H97: I - Ingreso | I97: 2025-03-07T23:24:23 | J97: 2025-03-07T23:23:30 | K97: 66260 | L97: MME1507071ZA | M97: MILLHOUSE MEXICO | N97: 601 - General de Ley Personas Morales | O97: EOP640608I13 | P97: HELLA AUTOMOTIVE MEXICO | Q97: G03 - Gastos en general | R97: 601 - General de Ley Personas Morales | S97: 45601 | T97: 99 - Por definir | U97: PPD | W97: SERVICIO LOGISTICO: TERRESTRE ORIGEN: LAREDO, TX DESTINO: VANCE, AL PRO NUMBER: 1122360 OBSERVACIONES: PL7-OV25-OUTC1-00367-4514-639208-USD | Y97: 3740 | Z97: 0 | AA97: 0 | AC97: 3740 | AD97: =Y97*AH97 -> 76255.982 | AE97: =VLOOKUP(D97,'FACTURAS INGRESOS'!$I$487:$P$718,8,0) -> 76255.98 | AF97: =AD97-AE97 -> 0.002 | AG97: USD | AH97: 20.3893 | AK97: 3740 | AV97: 1.0000007e+15 | AW97: 1.0000007e+15 | AX97: C:\AdminXML\BovedaCFDi\MME1507071ZA\Emitidas\2025\03\E2FD7311-BDC3-40B5-8550-EB093063958D@0000000000XX0.xml
D98: 8C90DF91-B3D5-43EC-8271-3D8FB939C456 | E98: F | F98: F4516 | G98: 4 | H98: I - Ingreso | I98: 2025-03-07T23:25:56 | J98: 2025-03-07T23:24:55 | K98: 66260 | L98: MME1507071ZA | M98: MILLHOUSE MEXICO | N98: 601 - General de Ley Personas Morales | O98: XEXX010101000 | P98: JABIL EMS SWITZERLAND | Q98: S01 - Sin efectos fiscales | R98: 616 - Sin obligaciones fiscales | S98: 66260 | T98: 99 - Por definir | U98: PPD | W98: SERVICIO LOGISTICO: AEREO ORIGEN: SHENZHEN, XX DESTINO: BOSQUES VALLARTA, JA PRO NUMBER: 1118693 OBSERVACIONES: SKY250143 | Y98: 7760 | Z98: 0 | AA98: 0 | AC98: 7760 | AD98: =Y98*AH98 -> 158220.97 | AE98: =VLOOKUP(D98,'FACTURAS INGRESOS'!$I$487:$P$718,8,0) -> 158220.97 | AF98: =AD98-AE98 -> -0.002 | AG98: USD | AH98: 20.3893 | AK98: 7760 | AV98: 1.0000007e+15 | AW98: 1.0000007e+15 | AX98: C:\AdminXML\BovedaCFDi\MME1507071ZA\Emitidas\2025\03\8C90DF91-B3D5-43EC-8271-3D8FB939C456@0000000000XX0.xml
D99: 0D7A98C9-3275-40F1-ABE7-F3A102FF2982 | E99: F | F99: F4517 | G99: 4 | H99: I - Ingreso | I99: 2025-03-07T23:27:52 | J99: 2025-03-07T23:26:29 | K99: 66260 | L99: MME1507071ZA | M99: MILLHOUSE MEXICO | N99: 601 - General de Ley Personas Morales | O99: KME9705088B5 | P99: KASAI MEXICANA | Q99: G03 - Gastos en general | R99: 601 - General de Ley Personas Morales | S99: 37564 | T99: 99 - Por definir | U99: PPD | W99: SERVICIO LOGISTICO: MARITIMO ORIGEN: DAVIDSONVILLE, MD DESTINO: ARBOLEDAS, TM PRO NUMBER: 1109358 OBSERVACIONES: A0019913298 | Y99: 1634 | Z99: 0 | AA99: 0 | AC99: 1634 | AD99: =Y99*AH99 -> 33316.116 | AE99: =VLOOKUP(D99,'FACTURAS INGRESOS'!$I$487:$P$718,8,0) -> 33316.12 | AF99: =AD99-AE99 -> -0.0038 | AG99: USD | AH99: 20.3893 | AK99: 1634 | AV99: 1.0000007e+15 | AW99: 1.0000007e+15 | AX99: C:\AdminXML\BovedaCFDi\MME1507071ZA\Emitidas\2025\03\0D7A98C9-3275-40F1-ABE7-F3A102FF2982@0000000000XX0.xml
D100: A583A5F0-E290-4EEC-BBEA-9B0111BF78C7 | E100: F | F100: F4518 | G100: 4 | H100: I - Ingreso | I100: 2025-03-10T17:07:49 | J100: 2025-03-10T17:06:49 | K100: 66260 | L100: MME1507071ZA | M100: MILLHOUSE MEXICO | N100: 601 - General de Ley Personas Morales | O100: CFM970129RG7 | P100: CEVA FREIGHT MANAGEMENT MEXICO | Q100: G03 - Gastos en general | R100: 601 - General de Ley Personas Morales | S100: 3720 | T100: 99 - Por definir | U100: PPD | W100: SERVICIO LOGISTICO: TERRESTRE ORIGEN: MANZANILLO, CL DESTINO: CHIHUAHUA, CI PRO NUMBER: 1123124 OBSERVACIONES: 1443820009830 | Y100: 53800 | Z100: 0 | AA100: 8608 | AC100: 62408 | AD100: =Y100*AH100 -> 53800 | AE100: =VLOOKUP(D100,'FACTURAS INGRESOS'!$I$487:$P$718,8,0) -> 53800 | AF100: =AD100-AE100 -> 0 | AG100: MXN | AH100: 1 | AM100: 8608 | AV100: 1.0000007e+15 | AW100: 1.0000007e+15 | AX100: C:\AdminXML\BovedaCFDi\MME1507071ZA\Emitidas\2025\03\A583A5F0-E290-4EEC-BBEA-9B0111BF78C7@0000000000XX0.xml
D101: CCCB39C1-7079-41D9-B7D1-4D60DAA88BAD | E101: F | F101: F4519 | G101: 4 | H101: I - Ingreso | I101: 2025-03-10T17:10:23 | J101: 2025-03-10T17:09:09 | K101: 66260 | L101: MME1507071ZA | M101: MILLHOUSE MEXICO | N101: 601 - General de Ley Personas Morales | O101: CPM1604014I1 | P101: CHASE PLASTICS DE MEXICO | Q101: G03 - Gastos en general | R101: 601 - General de Ley Personas Morales | S101: 6500 | T101: 99 - Por definir | U101: PPD | W101: SERVICIO LOGISTICO: TERRESTRE ORIGEN: EL MARQUÉS, QA DESTINO: IRAPUATO, GJ PRO NUMBER: 1122369 OBSERVACIONES: 2537751 / NIFCO / 1479941 | Y101: 7200 | Z101: 0 | AA101: 1152 | AC101: 8352 | AD101: =Y101*AH101 -> 7200 | AE101: =VLOOKUP(D101,'FACTURAS INGRESOS'!$I$487:$P$718,8,0) -> 7200 | AF101: =AD101-AE101 -> 0 | AG101: MXN | AH101: 1 | AM101: 1152 | AV101: 1.0000007e+15 | AW101: 1.0000007e+15 | AX101: C:\AdminXML\BovedaCFDi\MME1507071ZA\Emitidas\2025\03\CCCB39C1-7079-41D9-B7D1-4D60DAA88BAD@0000000000XX0.xml
D102: E70A90B0-9B3C-436D-B2C8-3C4D3C70A294 | E102: F | F102: F4520 | G102: 4 | H102: I - Ingreso | I102: 2025-03-10T17:11:51 | J102: 2025-03-10T17:11:04 | K102: 66260 | L102: MME1507071ZA | M102: MILLHOUSE MEXICO | N102: 601 - General de Ley Personas Morales | O102: MMG201001LG5 | P102: MOLEX DE MEXICO GUADALAJARA 2 | Q102: G03 - Gastos en general | R102: 601 - General de Ley Personas Morales | S102: 45777 | T102: 99 - Por definir | U102: PPD | W102: SERVICIO LOGISTICO: TERRESTRE ORIGEN: CENTRO LOGISTICO JALISCO II, JA DESTINO: GUADALAJARA (MIGUEL HIDALGO Y COSTILLA), JA PRO NUMBER: 1122952 OBSERVACIONES: 1122952 | Y102: 3500 | Z102: 0 | AA102: 560 | AC102: 4060 | AD102: =Y102*AH102 -> 3500 | AE102: =VLOOKUP(D102,'FACTURAS INGRESOS'!$I$487:$P$718,8,0) -> 3500 | AF102: =AD102-AE102 -> 0 | AG102: MXN | AH102: 1 | AM102: 560 | AV102: 1.0000007e+15 | AW102: 1.0000007e+15 | AX102: C:\AdminXML\BovedaCFDi\MME1507071ZA\Emitidas\2025\03\E70A90B0-9B3C-436D-B2C8-3C4D3C70A294@0000000000XX0.xml
D103: D4D35DFB-BDA9-4E70-87A6-13507E0AA010 | E103: FC | F103: 943 | G103: 4 | H103: I - Ingreso | I103: 2025-03-10T18:24:03 | J103: 2025-03-10T18:24:00 | K103: 66260 | L103: MME1507071ZA | M103: MILLHOUSE MEXICO | N103: 601 - General de Ley Personas Morales | O103: XEXX010101000 | P103: FAURECIA INTERIOR SYSTEMS INC, US17 | Q103: S01 - Sin efectos fiscales | R103: 616 - Sin obligaciones fiscales | S103: 66260 | T103: 99 - Por definir | U103: PPD | W103: SERVICIO LOGISTICO: TERRESTRE ORIGEN: BENTON HARBOR, MI DESTINO: GRAIN VALLEY, MO PRO NUMBER: 1088980 OBSERVACIONES: XF2410NM5D / 7100159217 / 8200086820 | Y103: 1800 | AA103: 0 | AC103: 1800 | AD103: =Y103*AH103 -> 36499.86 | AE103: =VLOOKUP(D103,'FACTURAS INGRESOS'!$I$487:$P$718,8,0) -> 36499.86 | AF103: =AD103-AE103 -> 0 | AG103: USD | AH103: 20.2777 | AK103: 1800 | AV103: 1.0000007e+15 | AW103: 1.0000007e+15 | AX103: C:\AdminXML\BovedaCFDi\MME1507071ZA\Emitidas\2025\03\D4D35DFB-BDA9-4E70-87A6-13507E0AA010@0000000000XX0.xml
D104: 3D39FDA1-7ED8-4481-ACB0-EEB683BE14CC | E104: FC | F104: 944 | G104: 4 | H104: I - Ingreso | I104: 2025-03-10T18:26:55 | J104: 2025-03-10T18:26:53 | K104: 66260 | L104: MME1507071ZA | M104: MILLHOUSE MEXICO | N104: 601 - General de Ley Personas Morales | O104: XEXX010101000 | P104: FAURECIA INTERIOR SYSTEMS INC, US17 | Q104: S01 - Sin efectos fiscales | R104: 616 - Sin obligaciones fiscales | S104: 66260 | T104: 99 - Por definir | U104: PPD | W104: SERVICIO LOGISTICO: TERRESTRE ORIGEN: ROMULUS, MI DESTINO: SPRING HILL, TN PRO NUMBER: 1090675 OBSERVACIONES: ID241014KD / 7100159941 / 8200085457 | Y104: 950 | AA104: 0 | AC104: 950 | AD104: =Y104*AH104 -> 19263.815 | AE104: =VLOOKUP(D104,'FACTURAS INGRESOS'!$I$487:$P$718,8,0) -> 19263.82 | AF104: =AD104-AE104 -> -0.005 | AG104: USD | AH104: 20.2777 | AK104: 950 | AV104: 1.0000007e+15 | AW104: 1.0000007e+15 | AX104: C:\AdminXML\BovedaCFDi\MME1507071ZA\Emitidas\2025\03\3D39FDA1-7ED8-4481-ACB0-EEB683BE14CC@0000000000XX0.xml
D105: EADC6E68-F7AA-4DA9-A087-D05190F7EB96 | E105: FC | F105: 945 | G105: 4 | H105: I - Ingreso | I105: 2025-03-10T18:34:07 | J105: 2025-03-10T18:33:44 | K105: 66260 | L105: MME1507071ZA | M105: MILLHOUSE MEXICO | N105: 601 - General de Ley Personas Morales | O105: XEXX010101000 | P105: FAURECIA INTERIOR SYSTEMS INC, US17 | Q105: S01 - Sin efectos fiscales | R105: 616 - Sin obligaciones fiscales | S105: 66260 | T105: 99 - Por definir | U105: PPD | W105: SERVICIO LOGISTICO: TERRESTRE ORIGEN: CEDAR SPRINGS, MI DESTINO: SALINE, MI PRO NUMBER: 1092233 OBSERVACIONES: XF241126JM / 7100161238 / 8200083850 | Y105: 680 | AA105: 0 | AC105: 680 | AD105: =Y105*AH105 -> 13788.836 | AE105: =VLOOKUP(D105,'FACTURAS INGRESOS'!$I$487:$P$718,8,0) -> 13788.84 | AF105: =AD105-AE105 -> -0.004 | AG105: USD | AH105: 20.2777 | AK105: 680 | AV105: 1.0000007e+15 | AW105: 1.0000007e+15 | AX105: C:\AdminXML\BovedaCFDi\MME1507071ZA\Emitidas\2025\03\EADC6E68-F7AA-4DA9-A087-D05190F7EB96@0000000000XX0.xml
D106: CFF0F63F-E0B9-4B0E-A4B2-78175D50ACFD | E106: FC | F106: 946 | G106: 4 | H106: I - Ingreso | I106: 2025-03-10T18:35:38 | J106: 2025-03-10T18:35:35 | K106: 66260 | L106: MME1507071ZA | M106: MILLHOUSE MEXICO | N106: 601 - General de Ley Personas Morales | O106: XEXX010101000 | P106: FAURECIA INTERIOR SYSTEMS INC, US17 | Q106: S01 - Sin efectos fiscales | R106: 616 - Sin obligaciones fiscales | S106: 66260 | T106: 99 - Por definir | U106: PPD | W106: SERVICIO LOGISTICO: TERRESTRE ORIGEN: ROMULUS, MI DESTINO: SPRING HILL, TN PRO NUMBER: 1093277 OBSERVACIONES: ID241131AN / 7100160897 / 8200083890 | Y106: 730 | AA106: 0 | AC106: 730 | AD106: =Y106*AH106 -> 14802.721 | AE106: =VLOOKUP(D106,'FACTURAS INGRESOS'!$I$487:$P$718,8,0) -> 14802.72 | AF106: =AD106-AE106 -> 0.001 | AG106: USD | AH106: 20.2777 | AK106: 730 | AV106: 1.0000007e+15 | AW106: 1.0000007e+15 | AX106: C:\AdminXML\BovedaCFDi\MME1507071ZA\Emitidas\2025\03\CFF0F63F-E0B9-4B0E-A4B2-78175D50ACFD@0000000000XX0.xml
D107: F4C8B1F3-25A0-4A0F-B3F1-45109F10BD88 | E107: FC | F107: 947 | G107: 4 | H107: I - Ingreso | I107: 2025-03-10T18:37:46 | J107: 2025-03-10T18:37:22 | K107: 66260 | L107: MME1507071ZA | M107: MILLHOUSE MEXICO | N107: 601 - General de Ley Personas Morales | O107: XEXX010101000 | P107: FAURECIA INTERIOR SYSTEMS INC, US17 | Q107: S01 - Sin efectos fiscales | R107: 616 - Sin obligaciones fiscales | S107: 66260 | T107: 99 - Por definir | U107: PPD | W107: SERVICIO LOGISTICO: TERRESTRE ORIGEN: SPRING HILL, TN DESTINO: LOUISVILLE, KY PRO NUMBER: 1118829 OBSERVACIONES: XF2502N1IL / XF2502N1IL / XF2502N1IL | Y107: 120 | AA107: 0 | AC107: 120 | AD107: =Y107*AH107 -> 2433.324 | AE107: =VLOOKUP(D107,'FACTURAS INGRESOS'!$I$487:$P$718,8,0) -> 2433.32 | AF107: =AD107-AE107 -> 0.004 | AG107: USD | AH107: 20.2777 | AK107: 120 | AV107: 1.0000007e+15 | AW107: 1.0000007e+15 | AX107: C:\AdminXML\BovedaCFDi\MME1507071ZA\Emitidas\2025\03\F4C8B1F3-25A0-4A0F-B3F1-45109F10BD88@0000000000XX0.xml
D108: 70A41C70-0606-4F8F-90ED-36F3C9D0A222 | E108: F | F108: F4521 | G108: 4 | H108: I - Ingreso | I108: 2025-03-13T12:09:50 | J108: 2025-03-13T12:05:47 | K108: 66260 | L108: MME1507071ZA | M108: MILLHOUSE MEXICO | N108: 601 - General de Ley Personas Morales | O108: BLO1508261JA | P108: BONANZA LOGISTICS | Q108: G03 - Gastos en general | R108: 601 - General de Ley Personas Morales | S108: 6700 | T108: 99 - Por definir | U108: PPD | W108: SERVICIO LOGISTICO: TERRESTRE ORIGEN: APODACA CENTRO, NX DESTINO: NEWTOWN, CT PRO NUMBER: 1122027 OBSERVACIONES: BL25-462 | Y108: 3150 | Z108: 0 | AA108: 0 | AC108: 3150 | AD108: =Y108*AH108 -> 64067.22 | AE108: =VLOOKUP(D108,'FACTURAS INGRESOS'!$I$487:$P$718,8,0) -> 64067.22 | AF108: =AD108-AE108 -> 0 | AG108: USD | AH108: 20.3388 | AK108: 3150 | AV108: 1.0000007e+15 | AW108: 1.0000007e+15 | AX108: C:\AdminXML\BovedaCFDi\MME1507071ZA\Emitidas\2025\03\70A41C70-0606-4F8F-90ED-36F3C9D0A222@0000000000XX0.xml
D109: A3217833-7D9C-4E44-A885-4692F393D652 | E109: F | F109: F4522 | G109: 4 | H109: I - Ingreso | I109: 2025-03-13T12:13:16 | J109: 2025-03-13T12:11:02 | K109: 66260 | L109: MME1507071ZA | M109: MILLHOUSE MEXICO | N109: 601 - General de Ley Personas Morales | O109: CPM1604014I1 | P109: CHASE PLASTICS DE MEXICO | Q109: G03 - Gastos en general | R109: 601 - General de Ley Personas Morales | S109: 6500 | T109: 99 - Por definir | U109: PPD | W109: SERVICIO LOGISTICO: TERRESTRE ORIGEN: EL MARQUÉS, QA DESTINO: LEÓN DE LOS ALDAMA, GJ PRO NUMBER: 1123082 OBSERVACIONES: 2538167 / Novatecleon / 1467758 | Y109: 8000 | Z109: 0 | AA109: 1280 | AC109: 9280 | AD109: =Y109*AH109 -> 8000 | AE109: =VLOOKUP(D109,'FACTURAS INGRESOS'!$I$487:$P$718,8,0) -> 8000 | AF109: =AD109-AE109 -> 0 | AG109: MXN | AH109: 1 | AM109: 1280 | AV109: 1.0000007e+15 | AW109: 1.0000007e+15 | AX109: C:\AdminXML\BovedaCFDi\MME1507071ZA\Emitidas\2025\03\A3217833-7D9C-4E44-A885-4692F393D652@0000000000XX0.xml
D110: 47D9E916-A892-4588-A343-FD9B88A40212 | E110: F | F110: F4523 | G110: 4 | H110: I - Ingreso | I110: 2025-03-13T12:15:05 | J110: 2025-03-13T12:13:52 | K110: 66260 | L110: MME1507071ZA | M110: MILLHOUSE MEXICO | N110: 601 - General de Ley Personas Morales | O110: CFO030723285 | P110: CONTINENTE FORWARDING | Q110: G03 - Gastos en general | R110: 601 - General de Ley Personas Morales | S110: 66260 | T110: 99 - Por definir | U110: PPD | W110: SERVICIO LOGISTICO: TERRESTRE ORIGEN: AZUSA, CA DESTINO: EL PASO, TX PRO NUMBER: 1121667 OBSERVACIONES: C45959 | Y110: 1850 | Z110: 0 | AA110: 0 | AC110: 1850 | AD110: =Y110*AH110 -> 37626.78 | AE110: =VLOOKUP(D110,'FACTURAS INGRESOS'!$I$487:$P$718,8,0) -> 37626.78 | AF110: =AD110-AE110 -> 0 | AG110: USD | AH110: 20.3388 | AK110: 1850 | AV110: 1.0000007e+15 | AW110: 1.0000007e+15 | AX110: C:\AdminXML\BovedaCFDi\MME1507071ZA\Emitidas\2025\03\47D9E916-A892-4588-A343-FD9B88A40212@0000000000XX0.xml
D111: CC803CAD-989D-44A1-B744-4C96F6DD44E0 | E111: F | F111: F4524 | G111: 4 | H111: I - Ingreso | I111: 2025-03-13T12:16:30 | J111: 2025-03-13T12:15:38 | K111: 66260 | L111: MME1507071ZA | M111: MILLHOUSE MEXICO | N111: 601 - General de Ley Personas Morales | O111: CFO030723285 | P111: CONTINENTE FORWARDING | Q111: G03 - Gastos en general | R111: 601 - General de Ley Personas Morales | S111: 66260 | T111: 99 - Por definir | U111: PPD | W111: SERVICIO LOGISTICO: TERRESTRE ORIGEN: LAREDO, TX DESTINO: JANESVILLE, WI PRO NUMBER: 1123278 OBSERVACIONES: C45895 | Y111: 2500 | Z111: 0 | AA111: 0 | AC111: 2500 | AD111: =Y111*AH111 -> 50847 | AE111: =VLOOKUP(D111,'FACTURAS INGRESOS'!$I$487:$P$718,8,0) -> 50847 | AF111: =AD111-AE111 -> 0 | AG111: USD | AH111: 20.3388 | AK111: 2500 | AV111: 1.0000007e+15 | AW111: 1.0000007e+15 | AX111: C:\AdminXML\BovedaCFDi\MME1507071ZA\Emitidas\2025\03\CC803CAD-989D-44A1-B744-4C96F6DD44E0@0000000000XX0.xml
D112: 6C63197D-D59B-4DFE-A7EF-AAE60B319494 | E112: F | F112: F4525 | G112: 4 | H112: I - Ingreso | I112: 2025-03-13T12:18:36 | J112: 2025-03-13T12:17:36 | K112: 66260 | L112: MME1507071ZA | M112: MILLHOUSE MEXICO | N112: 601 - General de Ley Personas Morales | O112: EOP640608I13 | P112: HELLA AUTOMOTIVE MEXICO | Q112: G03 - Gastos en general | R112: 601 - General de Ley Personas Morales | S112: 45601 | T112: 99 - Por definir | U112: PPD | W112: SERVICIO LOGISTICO: TERRESTRE ORIGEN: LAREDO, TX DESTINO: VANCE, AL PRO NUMBER: 1121499 OBSERVACIONES: PL7-OV25-OUTC1-00356-4514-639208-USD | Y112: 3260 | Z112: 0 | AA112: 0 | AC112: 3260 | AD112: =Y112*AH112 -> 66304.488 | AE112: =VLOOKUP(D112,'FACTURAS INGRESOS'!$I$487:$P$718,8,0) -> 66304.49 | AF112: =AD112-AE112 -> -0.002 | AG112: USD | AH112: 20.3388 | AK112: 3260 | AV112: 1.0000007e+15 | AW112: 1.0000007e+15 | AX112: C:\AdminXML\BovedaCFDi\MME1507071ZA\Emitidas\2025\03\6C63197D-D59B-4DFE-A7EF-AAE60B319494@0000000000XX0.xml
D113: A7553BA5-53D9-4E9E-87DF-F824A0A2B477 | E113: F | F113: F4526 | G113: 4 | H113: I - Ingreso | I113: 2025-03-13T12:21:51 | J113: 2025-03-13T12:19:17 | K113: 66260 | L113: MME1507071ZA | M113: MILLHOUSE MEXICO | N113: 601 - General de Ley Personas Morales | O113: XEXX010101000 | P113: JABIL EMS SWITZERLAND | Q113: S01 - Sin efectos fiscales | R113: 616 - Sin obligaciones fiscales | S113: 66260 | T113: 99 - Por definir | U113: PPD | W113: SERVICIO LOGISTICO: AEREO ORIGEN: GARLAND, TX DESTINO: ALTAGRACIA, JA PRO NUMBER: 1123734 OBSERVACIONES: HCOPT110325 | Y113: 2295 | Z113: 0 | AA113: 0 | AC113: 2295 | AD113: =Y113*AH113 -> 46677.546 | AE113: =VLOOKUP(D113,'FACTURAS INGRESOS'!$I$487:$P$718,8,0) -> 46677.55 | AF113: =AD113-AE113 -> -0.004 | AG113: USD | AH113: 20.3388 | AK113: 2295 | AV113: 1.0000007e+15 | AW113: 1.0000007e+15 | AX113: C:\AdminXML\BovedaCFDi\MME1507071ZA\Emitidas\2025\03\A7553BA5-53D9-4E9E-87DF-F824A0A2B477@0000000000XX0.xml
D114: 6D20444E-E72F-47FD-9C7D-56859777998D | E114: FC | F114: 948 | G114: 4 | H114: I - Ingreso | I114: 2025-03-13T14:50:20 | J114: 2025-03-13T14:50:18 | K114: 66260 | L114: MME1507071ZA | M114: MILLHOUSE MEXICO | N114: 601 - General de Ley Personas Morales | O114: XEXX010101000 | P114: FAURECIA INTERIOR SYSTEMS INC, US17 | Q114: S01 - Sin efectos fiscales | R114: 616 - Sin obligaciones fiscales | S114: 66260 | T114: 99 - Por definir | U114: PPD | W114: SERVICIO LOGISTICO: TERRESTRE ORIGEN: LAREDO, TX DESTINO: LOUISVILLE, KY PRO NUMBER: 1108210 OBSERVACIONES: XF2501EI42 / 7100169234 / 8200091407 | Y114: 3300 | AA114: 0 | AC114: 3300 | AD114: =Y114*AH114 -> 67118.04 | AE114: =VLOOKUP(D114,'FACTURAS INGRESOS'!$I$487:$P$718,8,0) -> 67118.04 | AF114: =AD114-AE114 -> 0 | AG114: USD | AH114: 20.3388 | AK114: 3300 | AV114: 1.0000007e+15 | AW114: 1.0000007e+15 | AX114: C:\AdminXML\BovedaCFDi\MME1507071ZA\Emitidas\2025\03\6D20444E-E72F-47FD-9C7D-56859777998D@0000000000XX0.xml
D115: 2A742757-0481-4D44-888C-FA021569E616 | E115: FC | F115: 949 | G115: 4 | H115: I - Ingreso | I115: 2025-03-13T14:51:45 | J115: 2025-03-13T14:51:43 | K115: 66260 | L115: MME1507071ZA | M115: MILLHOUSE MEXICO | N115: 601 - General de Ley Personas Morales | O115: XEXX010101000 | P115: FAURECIA INTERIOR SYSTEMS INC, US17 | Q115: S01 - Sin efectos fiscales | R115: 616 - Sin obligaciones fiscales | S115: 66260 | T115: 99 - Por definir | U115: PPD | W115: SERVICIO LOGISTICO: TERRESTRE ORIGEN: FRASER, MI DESTINO: BARDSTOWN, KY PRO NUMBER: 1106665 OBSERVACIONES: XF2501DGNM / XF2501DGNM / XF2501DGNM | Y115: 190 | AA115: 0 | AC115: 190 | AD115: =Y115*AH115 -> 3864.372 | AE115: =VLOOKUP(D115,'FACTURAS INGRESOS'!$I$487:$P$718,8,0) -> 3864.37 | AF115: =AD115-AE115 -> 0.002 | AG115: USD | AH115: 20.3388 | AK115: 190 | AV115: 1.0000007e+15 | AW115: 1.0000007e+15 | AX115: C:\AdminXML\BovedaCFDi\MME1507071ZA\Emitidas\2025\03\2A742757-0481-4D44-888C-FA021569E616@0000000000XX0.xml
D116: 6736B6E3-4F25-4788-9E1F-01DD66DF686C | E116: FC | F116: 950 | G116: 4 | H116: I - Ingreso | I116: 2025-03-13T14:53:29 | J116: 2025-03-13T14:53:27 | K116: 66260 | L116: MME1507071ZA | M116: MILLHOUSE MEXICO | N116: 601 - General de Ley Personas Morales | O116: XEXX010101000 | P116: FAURECIA INTERIOR SYSTEMS INC, US17 | Q116: S01 - Sin efectos fiscales | R116: 616 - Sin obligaciones fiscales | S116: 66260 | T116: 99 - Por definir | U116: PPD | W116: SERVICIO LOGISTICO: TERRESTRE ORIGEN: LOUISVILLE, KY DESTINO: LOUISVILLE, KY PRO NUMBER: 1113799 OBSERVACIONES: XF2501IH79 / XF2501IH79 / XF2501IH79 | Y116: 650 | AA116: 0 | AC116: 650 | AD116: =Y116*AH116 -> 13220.22 | AE116: =VLOOKUP(D116,'FACTURAS INGRESOS'!$I$487:$P$718,8,0) -> 13220.22 | AF116: =AD116-AE116 -> 0 | AG116: USD | AH116: 20.3388 | AK116: 650 | AV116: 1.0000007e+15 | AW116: 1.0000007e+15 | AX116: C:\AdminXML\BovedaCFDi\MME1507071ZA\Emitidas\2025\03\6736B6E3-4F25-4788-9E1F-01DD66DF686C@0000000000XX0.xml
D117: 50A2D550-80B3-46FF-A656-F38DC946D3D2 | E117: FC | F117: 951 | G117: 4 | H117: I - Ingreso | I117: 2025-03-13T14:55:22 | J117: 2025-03-13T14:55:19 | K117: 66260 | L117: MME1507071ZA | M117: MILLHOUSE MEXICO | N117: 601 - General de Ley Personas Morales | O117: XEXX010101000 | P117: FAURECIA INTERIOR SYSTEMS INC, US17 | Q117: S01 - Sin efectos fiscales | R117: 616 - Sin obligaciones fiscales | S117: 66260 | T117: 99 - Por definir | U117: PPD | W117: SERVICIO LOGISTICO: TERRESTRE ORIGEN: CEDAR SPRINGS, MI DESTINO: SPRING HILL, TN PRO NUMBER: 1120496 OBSERVACIONES: XF25020BGH / 7100174554 / 8200095556 | Y117: 1250 | AA117: 0 | AC117: 1250 | AD117: =Y117*AH117 -> 25423.5 | AE117: =VLOOKUP(D117,'FACTURAS INGRESOS'!$I$487:$P$718,8,0) -> 25423.5 | AF117: =AD117-AE117 -> 0 | AG117: USD | AH117: 20.3388 | AK117: 1250 | AV117: 1.0000007e+15 | AW117: 1.0000007e+15 | AX117: C:\AdminXML\BovedaCFDi\MME1507071ZA\Emitidas\2025\03\50A2D550-80B3-46FF-A656-F38DC946D3D2@0000000000XX0.xml
D118: E6018B90-93B2-4750-9AE2-093A4A94B8B6 | E118: FC | F118: 952 | G118: 4 | H118: I - Ingreso | I118: 2025-03-13T14:56:49 | J118: 2025-03-13T14:56:47 | K118: 66260 | L118: MME1507071ZA | M118: MILLHOUSE MEXICO | N118: 601 - General de Ley Personas Morales | O118: XEXX010101000 | P118: FAURECIA INTERIOR SYSTEMS INC, US17 | Q118: S01 - Sin efectos fiscales | R118: 616 - Sin obligaciones fiscales | S118: 66260 | T118: 99 - Por definir | U118: PPD | W118: SERVICIO LOGISTICO: TERRESTRE ORIGEN: GREER, SC DESTINO: LOUISVILLE, KY PRO NUMBER: 1120587 OBSERVACIONES: ID25020GC3 / 7100174712 / 8200095385 | Y118: 550 | AA118: 0 | AC118: 550 | AD118: =Y118*AH118 -> 11186.34 | AE118: =VLOOKUP(D118,'FACTURAS INGRESOS'!$I$487:$P$718,8,0) -> 11186.34 | AF118: =AD118-AE118 -> 0 | AG118: USD | AH118: 20.3388 | AK118: 550 | AV118: 1.0000007e+15 | AW118: 1.0000007e+15 | AX118: C:\AdminXML\BovedaCFDi\MME1507071ZA\Emitidas\2025\03\E6018B90-93B2-4750-9AE2-093A4A94B8B6@0000000000XX0.xml
D119: 0B504F81-BCFF-432E-90D6-45142A5357EF | E119: FC | F119: 953 | G119: 4 | H119: I - Ingreso | I119: 2025-03-13T14:59:23 | J119: 2025-03-13T14:59:21 | K119: 66260 | L119: MME1507071ZA | M119: MILLHOUSE MEXICO | N119: 601 - General de Ley Personas Morales | O119: XEXX010101000 | P119: FAURECIA INTERIOR SYSTEMS INC, US17 | Q119: S01 - Sin efectos fiscales | R119: 616 - Sin obligaciones fiscales | S119: 66260 | T119: 99 - Por definir | U119: PPD | W119: SERVICIO LOGISTICO: TERRESTRE ORIGEN: GRAIN VALLEY, MO DESTINO: NEW BALTIMORE, MI PRO NUMBER: 1121047 OBSERVACIONES: XF250210EG / XF250210EG / XF250210EG | Y119: 900 | AA119: 0 | AC119: 900 | AD119: =Y119*AH119 -> 18304.92 | AE119: =VLOOKUP(D119,'FACTURAS INGRESOS'!$I$487:$P$718,8,0) -> 18304.92 | AF119: =AD119-AE119 -> 0 | AG119: USD | AH119: 20.3388 | AK119: 900 | AV119: 1.0000007e+15 | AW119: 1.0000007e+15 | AX119: C:\AdminXML\BovedaCFDi\MME1507071ZA\Emitidas\2025\03\0B504F81-BCFF-432E-90D6-45142A5357EF@0000000000XX0.xml
D120: BB9D720F-DD73-4BA1-B7CD-18A4648FF158 | E120: FC | F120: 954 | G120: 4 | H120: I - Ingreso | I120: 2025-03-13T15:00:48 | J120: 2025-03-13T15:00:46 | K120: 66260 | L120: MME1507071ZA | M120: MILLHOUSE MEXICO | N120: 601 - General de Ley Personas Morales | O120: XEXX010101000 | P120: FAURECIA INTERIOR SYSTEMS INC, US17 | Q120: S01 - Sin efectos fiscales | R120: 616 - Sin obligaciones fiscales | S120: 66260 | T120: 99 - Por definir | U120: PPD | W120: SERVICIO LOGISTICO: TERRESTRE ORIGEN: GRAIN VALLEY, MO DESTINO: NEW BALTIMORE, MI PRO NUMBER: 1117679 OBSERVACIONES: XF2502LMHH / XF2502LMHH / XF2502LMHH | Y120: 820 | AA120: 0 | AC120: 820 | AD120: =Y120*AH120 -> 16677.816 | AE120: =VLOOKUP(D120,'FACTURAS INGRESOS'!$I$487:$P$718,8,0) -> 16677.82 | AF120: =AD120-AE120 -> -0.004 | AG120: USD | AH120: 20.3388 | AK120: 820 | AV120: 1.0000007e+15 | AW120: 1.0000007e+15 | AX120: C:\AdminXML\BovedaCFDi\MME1507071ZA\Emitidas\2025\03\BB9D720F-DD73-4BA1-B7CD-18A4648FF158@0000000000XX0.xml
D121: F428C985-A5B8-45E8-A393-EC2524944857 | E121: FC | F121: 955 | G121: 4 | H121: I - Ingreso | I121: 2025-03-13T15:09:45 | J121: 2025-03-13T15:09:43 | K121: 66260 | L121: MME1507071ZA | M121: MILLHOUSE MEXICO | N121: 601 - General de Ley Personas Morales | O121: XEXX010101000 | P121: FAURECIA INTERIOR SYSTEMS INC, US17 | Q121: S01 - Sin efectos fiscales | R121: 616 - Sin obligaciones fiscales | S121: 66260 | T121: 99 - Por definir | U121: PPD | W121: SERVICIO LOGISTICO: TERRESTRE ORIGEN: HOLLAND, MI DESTINO: SPRING HILL, TN PRO NUMBER: 1121346 OBSERVACIONES: ID250217JF / ID250217JF / ID250217JF | Y121: 780 | AA121: 0 | AC121: 780 | AD121: =Y121*AH121 -> 15864.264 | AE121: =VLOOKUP(D121,'FACTURAS INGRESOS'!$I$487:$P$718,8,0) -> 15864.26 | AF121: =AD121-AE121 -> 0.004 | AG121: USD | AH121: 20.3388 | AK121: 780 | AV121: 1.0000007e+15 | AW121: 1.0000007e+15 | AX121: C:\AdminXML\BovedaCFDi\MME1507071ZA\Emitidas\2025\03\F428C985-A5B8-45E8-A393-EC2524944857@0000000000XX0.xml
D122: 761E798D-8CE7-4AB0-A80C-B40C41B4C7C3 | E122: F | F122: F4527 | G122: 4 | H122: I - Ingreso | I122: 2025-03-14T16:44:02 | J122: 2025-03-14T16:42:55 | K122: 66260 | L122: MME1507071ZA | M122: MILLHOUSE MEXICO | N122: 601 - General de Ley Personas Morales | O122: ECL831108M87 | P122: ELECTRONICA CLARION | Q122: G03 - Gastos en general | R122: 601 - General de Ley Personas Morales | S122: 76803 | T122: 99 - Por definir | U122: PPD | W122: SERVICIO LOGISTICO: AEREO ORIGEN: JI AN SHI, XX DESTINO: SAN JUAN, XX PRO NUMBER: 1122443 OBSERVACIONES: XF250323DJ | Y122: 3100.8 | Z122: 0 | AA122: 0 | AC122: 3100.8 | AD122: =Y122*AH122 -> 62582.826 | AE122: =VLOOKUP(D122,'FACTURAS INGRESOS'!$I$487:$P$718,8,0) -> 62582.83 | AF122: =AD122-AE122 -> -0.00376 | AG122: USD | AH122: 20.1828 | AK122: 3100.8 | AV122: 1.0000007e+15 | AW122: 1.0000007e+15 | AX122: C:\AdminXML\BovedaCFDi\MME1507071ZA\Emitidas\2025\03\761E798D-8CE7-4AB0-A80C-B40C41B4C7C3@0000000000XX0.xml
D123: 47A4E6E8-5F04-4539-97C0-405BC08FED37 | E123: F | F123: F4528 | G123: 4 | H123: I - Ingreso | I123: 2025-03-14T16:45:55 | J123: 2025-03-14T16:44:42 | K123: 66260 | L123: MME1507071ZA | M123: MILLHOUSE MEXICO | N123: 601 - General de Ley Personas Morales | O123: CFO030723285 | P123: CONTINENTE FORWARDING | Q123: G03 - Gastos en general | R123: 601 - General de Ley Personas Morales | S123: 66260 | T123: 99 - Por definir | U123: PPD | W123: SERVICIO LOGISTICO: TERRESTRE ORIGEN: HOUSTON, TX DESTINO: LAREDO, TX PRO NUMBER: 1122766 OBSERVACIONES: C46272 | Y123: 550 | Z123: 0 | AA123: 0 | AC123: 550 | AD123: =Y123*AH123 -> 11100.54 | AE123: =VLOOKUP(D123,'FACTURAS INGRESOS'!$I$487:$P$718,8,0) -> 11100.54 | AF123: =AD123-AE123 -> 0 | AG123: USD | AH123: 20.1828 | AK123: 550 | AV123: 1.0000007e+15 | AW123: 1.0000007e+15 | AX123: C:\AdminXML\BovedaCFDi\MME1507071ZA\Emitidas\2025\03\47A4E6E8-5F04-4539-97C0-405BC08FED37@0000000000XX0.xml
D124: 82A2B816-F933-4012-B5BF-51C3735915BF | E124: F | F124: F4529 | G124: 4 | H124: I - Ingreso | I124: 2025-03-14T16:47:55 | J124: 2025-03-14T16:46:35 | K124: 66260 | L124: MME1507071ZA | M124: MILLHOUSE MEXICO | N124: 601 - General de Ley Personas Morales | O124: EOP640608I13 | P124: HELLA AUTOMOTIVE MEXICO | Q124: G03 - Gastos en general | R124: 601 - General de Ley Personas Morales | S124: 45601 | T124: 99 - Por definir | U124: PPD | W124: SERVICIO LOGISTICO: AEREO ORIGEN: CHICAGO, IL DESTINO: PLYMOUTH, MI PRO NUMBER: 1122662 OBSERVACIONES: PL5-AIR25-OUTC1-0664-161829-639213USD | Y124: 3318.02 | Z124: 0 | AA124: 0 | AC124: 3318.02 | AD124: =Y124*AH124 -> 66966.934 | AE124: =VLOOKUP(D124,'FACTURAS INGRESOS'!$I$487:$P$718,8,0) -> 66966.93 | AF124: =AD124-AE124 -> 0.004056 | AG124: USD | AH124: 20.1828 | AK124: 3318.02 | AV124: 1.0000007e+15 | AW124: 1.0000007e+15 | AX124: C:\AdminXML\BovedaCFDi\MME1507071ZA\Emitidas\2025\03\82A2B816-F933-4012-B5BF-51C3735915BF@0000000000XX0.xml
D125: 10A815AC-1B6B-4B56-ABF2-4D6E407FDB97 | E125: F | F125: F4530 | G125: 4 | H125: I - Ingreso | I125: 2025-03-14T16:49:51 | J125: 2025-03-14T16:48:40 | K125: 66260 | L125: MME1507071ZA | M125: MILLHOUSE MEXICO | N125: 601 - General de Ley Personas Morales | O125: XEXX010101000 | P125: JABIL EMS SWITZERLAND | Q125: S01 - Sin efectos fiscales | R125: 616 - Sin obligaciones fiscales | S125: 66260 | T125: 99 - Por definir | U125: PPD | W125: SERVICIO LOGISTICO: AEREO ORIGEN: ANNAPOLIS, MD DESTINO: ALTAGRACIA, JA PRO NUMBER: 1121612 OBSERVACIONES: 160-88737644 | Y125: 3750 | Z125: 0 | AA125: 0 | AC125: 3750 | AD125: =Y125*AH125 -> 75685.5 | AE125: =VLOOKUP(D125,'FACTURAS INGRESOS'!$I$487:$P$718,8,0) -> 75685.5 | AF125: =AD125-AE125 -> 0 | AG125: USD | AH125: 20.1828 | AK125: 3750 | AV125: 1.0000007e+15 | AW125: 1.0000007e+15 | AX125: C:\AdminXML\BovedaCFDi\MME1507071ZA\Emitidas\2025\03\10A815AC-1B6B-4B56-ABF2-4D6E407FDB97@0000000000XX0.xml
D126: BD56D948-9C16-4273-913C-B0777907B443 | E126: F | F126: F4531 | G126: 4 | H126: I - Ingreso | I126: 2025-03-14T16:52:23 | J126: 2025-03-14T16:51:21 | K126: 66260 | L126: MME1507071ZA | M126: MILLHOUSE MEXICO | N126: 601 - General de Ley Personas Morales | O126: CFO030723285 | P126: CONTINENTE FORWARDING | Q126: G03 - Gastos en general | R126: 601 - General de Ley Personas Morales | S126: 66260 | T126: 99 - Por definir | U126: PPD | W126: SERVICIO LOGISTICO: TERRESTRE ORIGEN: HARRISON, OH DESTINO: LAREDO, TX PRO NUMBER: 1123092 OBSERVACIONES: C46394 | Y126: 2200 | Z126: 0 | AA126: 0 | AC126: 2200 | AD126: =Y126*AH126 -> 44402.16 | AE126: =VLOOKUP(D126,'FACTURAS INGRESOS'!$I$487:$P$718,8,0) -> 44402.16 | AF126: =AD126-AE126 -> 0 | AG126: USD | AH126: 20.1828 | AK126: 2200 | AV126: 1.0000007e+15 | AW126: 1.0000007e+15 | AX126: C:\AdminXML\BovedaCFDi\MME1507071ZA\Emitidas\2025\03\BD56D948-9C16-4273-913C-B0777907B443@0000000000XX0.xml
D127: A63F2CA2-BEF6-4259-903D-F9EF771FC349 | E127: F | F127: F4532 | G127: 4 | H127: I - Ingreso | I127: 2025-03-14T16:54:33 | J127: 2025-03-14T16:53:10 | K127: 66260 | L127: MME1507071ZA | M127: MILLHOUSE MEXICO | N127: 601 - General de Ley Personas Morales | O127: EOP640608I13 | P127: HELLA AUTOMOTIVE MEXICO | Q127: G03 - Gastos en general | R127: 601 - General de Ley Personas Morales | S127: 45601 | T127: 99 - Por definir | U127: PPD | W127: SERVICIO LOGISTICO: AEREO ORIGEN: CERRO DEL TESORO, JA DESTINO: PLYMOUTH, MI PRO NUMBER: 1123456 OBSERVACIONES: PL5-AIR25-OUTC1-1303-161829-639208-USD | Y127: 3079.53 | Z127: 0 | AA127: 0 | AC127: 3079.53 | AD127: =Y127*AH127 -> 62153.538 | AE127: =VLOOKUP(D127,'FACTURAS INGRESOS'!$I$487:$P$718,8,0) -> 62153.54 | AF127: =AD127-AE127 -> -0.001916 | AG127: USD | AH127: 20.1828 | AK127: 3079.53 | AV127: 1.0000007e+15 | AW127: 1.0000007e+15 | AX127: C:\AdminXML\BovedaCFDi\MME1507071ZA\Emitidas\2025\03\A63F2CA2-BEF6-4259-903D-F9EF771FC349@0000000000XX0.xml
D128: 950BBA61-FCE1-4039-ABBB-BD0F992EA93D | E128: FC | F128: 956 | G128: 4 | H128: I - Ingreso | I128: 2025-03-14T17:00:58 | J128: 2025-03-14T17:00:34 | K128: 66260 | L128: MME1507071ZA | M128: MILLHOUSE MEXICO | N128: 601 - General de Ley Personas Morales | O128: FSA980318AL3 | P128: FAURECIA SISTEMAS AUTOMOTRICES DE MEXICO | Q128: G03 - Gastos en general | R128: 601 - General de Ley Personas Morales | S128: 72710 | T128: 99 - Por definir | U128: PPD | W128: SERVICIO LOGISTICO: TERRESTRE ORIGEN: CHIPPEWA FALLS, WI DESTINO: FINSA, PU PRO NUMBER: 1096434 OBSERVACIONES: ID24115ECA / 7100168368 / 8200096809 | Y128: 350 | AA128: 0 | AC128: 350 | AD128: =Y128*AH128 -> 7063.98 | AE128: =VLOOKUP(D128,'FACTURAS INGRESOS'!$I$487:$P$718,8,0) -> 7063.98 | AF128: =AD128-AE128 -> 0 | AG128: USD | AH128: 20.1828 | AK128: 350 | AV128: 1.0000007e+15 | AW128: 1.0000007e+15 | AX128: C:\AdminXML\BovedaCFDi\MME1507071ZA\Emitidas\2025\03\950BBA61-FCE1-4039-ABBB-BD0F992EA93D@0000000000XX0.xml
D129: 8A3BD526-008D-42B6-B1C9-4DEF88AB7DA4 | E129: FC | F129: 957 | G129: 4 | H129: I - Ingreso | I129: 2025-03-14T17:03:01 | J129: 2025-03-14T17:02:33 | K129: 66260 | L129: MME1507071ZA | M129: MILLHOUSE MEXICO | N129: 601 - General de Ley Personas Morales | O129: XEXX010101000 | P129: FAURECIA INTERIOR SYSTEMS INC, US17 | Q129: S01 - Sin efectos fiscales | R129: 616 - Sin obligaciones fiscales | S129: 66260 | T129: 99 - Por definir | U129: PPD | W129: SERVICIO LOGISTICO: TERRESTRE ORIGEN: LOUISVILLE, KY DESTINO: SPRING HILL, TN PRO NUMBER: 1088846 OBSERVACIONES: XF2410NL70 / 7100159163 / 8200086819 | Y129: 1200 | AA129: 0 | AC129: 1200 | AD129: =Y129*AH129 -> 24219.36 | AE129: =VLOOKUP(D129,'FACTURAS INGRESOS'!$I$487:$P$718,8,0) -> 24219.36 | AF129: =AD129-AE129 -> 0 | AG129: USD | AH129: 20.1828 | AK129: 1200 | AV129: 1.0000007e+15 | AW129: 1.0000007e+15 | AX129: C:\AdminXML\BovedaCFDi\MME1507071ZA\Emitidas\2025\03\8A3BD526-008D-42B6-B1C9-4DEF88AB7DA4@0000000000XX0.xml
D130: 737EBBC1-26B0-4144-A371-275327036962 | E130: F | F130: F4533 | G130: 4 | H130: I - Ingreso | I130: 2025-03-17T21:01:10 | J130: 2025-03-17T20:59:31 | K130: 66260 | L130: MME1507071ZA | M130: MILLHOUSE MEXICO | N130: 601 - General de Ley Personas Morales | O130: ETR140924VC7 | P130: EXO TRANSPORT | Q130: G03 - Gastos en general | R130: 601 - General de Ley Personas Morales | S130: 66260 | T130: 99 - Por definir | U130: PPD | W130: SERVICIO LOGISTICO: TERRESTRE ORIGEN: CHEEKTOWAGA, NY DESTINO: LAREDO, TX PRO NUMBER: 1123061 OBSERVACIONES: DT-0325-69592 | Y130: 4600 | Z130: 0 | AA130: 0 | AC130: 4600 | AD130: =Y130*AH130 -> 92390.08 | AE130: =VLOOKUP(D130,'FACTURAS INGRESOS'!$I$487:$P$718,8,0) -> 92390.08 | AF130: =AD130-AE130 -> 0 | AG130: USD | AH130: 20.0848 | AK130: 4600 | AV130: 1.0000007e+15 | AW130: 1.0000007e+15 | AX130: C:\AdminXML\BovedaCFDi\MME1507071ZA\Emitidas\2025\03\737EBBC1-26B0-4144-A371-275327036962@0000000000XX0.xml
D131: D57601E8-23B4-41F6-A0F4-F43C0268A814 | E131: FC | F131: 958 | G131: 4 | H131: I - Ingreso | I131: 2025-03-17T21:06:22 | J131: 2025-03-17T21:05:58 | K131: 66260 | L131: MME1507071ZA | M131: MILLHOUSE MEXICO | N131: 601 - General de Ley Personas Morales | O131: FSA980318AL3 | P131: FAURECIA SISTEMAS AUTOMOTRICES DE MEXICO | Q131: G03 - Gastos en general | R131: 601 - General de Ley Personas Morales | S131: 72710 | T131: 99 - Por definir | U131: PPD | W131: SERVICIO LOGISTICO: TERRESTRE ORIGEN: BUENAVISTA, GJ DESTINO: BUENAVISTA, GJ PRO NUMBER: 1105465 OBSERVACIONES: ID2412D9JA / 7100167326 / 8200096800 | Y131: 550 | AA131: 0 | AC131: 550 | AD131: =Y131*AH131 -> 11046.64 | AE131: =VLOOKUP(D131,'FACTURAS INGRESOS'!$I$487:$P$718,8,0) -> 11046.64 | AF131: =AD131-AE131 -> 0 | AG131: USD | AH131: 20.0848 | AK131: 550 | AV131: 1.0000007e+15 | AW131: 1.0000007e+15 | AX131: C:\AdminXML\BovedaCFDi\MME1507071ZA\Emitidas\2025\03\D57601E8-23B4-41F6-A0F4-F43C0268A814@0000000000XX0.xml
D132: 3A861AEA-B5DC-4546-A7B8-DB0A81B64202 | E132: FC | F132: 959 | G132: 4 | H132: I - Ingreso | I132: 2025-03-17T21:08:54 | J132: 2025-03-17T21:08:31 | K132: 66260 | L132: MME1507071ZA | M132: MILLHOUSE MEXICO | N132: 601 - General de Ley Personas Morales | O132: FSA980318AL3 | P132: FAURECIA SISTEMAS AUTOMOTRICES DE MEXICO | Q132: G03 - Gastos en general | R132: 601 - General de Ley Personas Morales | S132: 72710 | T132: 99 - Por definir | U132: PPD | W132: SERVICIO LOGISTICO: TERRESTRE ORIGEN: COLUMBUS, IN DESTINO: FORT WAYNE, IN PRO NUMBER: 1113176 OBSERVACIONES: ID2501I9JJ / 7100172580 / 8200096484 | Y132: 150 | AA132: 0 | AC132: 150 | AD132: =Y132*AH132 -> 3012.72 | AE132: =VLOOKUP(D132,'FACTURAS INGRESOS'!$I$487:$P$718,8,0) -> 3012.72 | AF132: =AD132-AE132 -> 0 | AG132: USD | AH132: 20.0848 | AK132: 150 | AV132: 1.0000007e+15 | AW132: 1.0000007e+15 | AX132: C:\AdminXML\BovedaCFDi\MME1507071ZA\Emitidas\2025\03\3A861AEA-B5DC-4546-A7B8-DB0A81B64202@0000000000XX0.xml
D133: DF86BAB6-0165-4EB8-843A-66ADF0F7925B | E133: FC | F133: 960 | G133: 4 | H133: I - Ingreso | I133: 2025-03-17T21:11:14 | J133: 2025-03-17T21:10:51 | K133: 66260 | L133: MME1507071ZA | M133: MILLHOUSE MEXICO | N133: 601 - General de Ley Personas Morales | O133: FSA980318AL3 | P133: FAURECIA SISTEMAS AUTOMOTRICES DE MEXICO | Q133: G03 - Gastos en general | R133: 601 - General de Ley Personas Morales | S133: 72710 | T133: 99 - Por definir | U133: PPD | W133: SERVICIO LOGISTICO: TERRESTRE ORIGEN: COLUMBUS, IN DESTINO: LOUISVILLE, KY PRO NUMBER: 1118350 OBSERVACIONES: ID2502MD28 / 7100173364 / 8200096249 | Y133: 850 | AA133: 0 | AC133: 850 | AD133: =Y133*AH133 -> 17072.08 | AE133: =VLOOKUP(D133,'FACTURAS INGRESOS'!$I$487:$P$718,8,0) -> 17072.08 | AF133: =AD133-AE133 -> 0 | AG133: USD | AH133: 20.0848 | AK133: 850 | AV133: 1.0000007e+15 | AW133: 1.0000007e+15 | AX133: C:\AdminXML\BovedaCFDi\MME1507071ZA\Emitidas\2025\03\DF86BAB6-0165-4EB8-843A-66ADF0F7925B@0000000000XX0.xml
D134: 6E9E17C6-9C32-4211-AB78-AF22772F764C | E134: FC | F134: 961 | G134: 4 | H134: I - Ingreso | I134: 2025-03-17T21:12:51 | J134: 2025-03-17T21:12:49 | K134: 66260 | L134: MME1507071ZA | M134: MILLHOUSE MEXICO | N134: 601 - General de Ley Personas Morales | O134: FSA980318AL3 | P134: FAURECIA SISTEMAS AUTOMOTRICES DE MEXICO | Q134: G03 - Gastos en general | R134: 601 - General de Ley Personas Morales | S134: 72710 | T134: 99 - Por definir | U134: PPD | W134: SERVICIO LOGISTICO: TERRESTRE ORIGEN: COLUMBUS, IN DESTINO: FORT WAYNE, IN PRO NUMBER: 1119371 OBSERVACIONES: ID2502NBN1 / 7100173930 / 8200096251 | Y134: 920 | AA134: 0 | AC134: 920 | AD134: =Y134*AH134 -> 18478.016 | AE134: =VLOOKUP(D134,'FACTURAS INGRESOS'!$I$487:$P$718,8,0) -> 18478.02 | AF134: =AD134-AE134 -> -0.004 | AG134: USD | AH134: 20.0848 | AK134: 920 | AV134: 1.0000007e+15 | AW134: 1.0000007e+15 | AX134: C:\AdminXML\BovedaCFDi\MME1507071ZA\Emitidas\2025\03\6E9E17C6-9C32-4211-AB78-AF22772F764C@0000000000XX0.xml
...

Sheet Aux. ingresos
B2: ENERO
B3: Tipo | C3: Etiqueta | D3: Fecha de ingreso | E3: Fecha del documento | F3: Folio | G3: Cliente | H3: RFC | I3: Régimen Fiscal | J3: Forma de Pago | K3: Método de Pago | L3: Uso de CFDI | M3: Importe Total de Factura (Sin Impuestos) | N3: Importe Base de Factura que gravó IVA 16% | O3: Importe Base de Factura que gravó IVA 8% | P3: Importe Base de Factura Tasa 0 | Q3: Importe Base de Factura Exento | R3: Importe Base Factura No objeto de Impuestos | S3: Importe Base No Considerados | T3: IVA Facturado 16% | U3: IVA Facturado 8% | V3: IVA Retenido | W3: ISR Retenido | X3: ISR Retenido de Nómina | Y3: Importe Total (Inc. Impuestos y Retenciones) | Z3: Importe del Ingreso | AA3: % del Cobro | AB3: Ingreso cobrado tasa 16% | AC3: Ingreso cobrado tasa 8% | AD3: Ingreso Cobrado 0% | AE3: Ingreso Cobrado Exento | AF3: Ingreso Cobrado No Objeto de impuesto | AG3: Ingreso Cobrado Base No Considerados | AH3: IVA Efectivamente cobrado | AI3: Importe Cobrado con Tasa 8 | AJ3: Retención de IVA Efectivamente cobrada | AK3: Retención de ISR Efectivamente cobrada
B4: Factura | C4: 401-04 ~ Ventas y/o servicios gravados al 0% | D4: 2025-01-02 | E4: 2024-09-30 | F4: F3501 | G4: SEA CARGO LOGISTICS | H4: SCL090414QE0 | I4: 601 - General de Ley Personas Morales | J4: Por definir | K4: PPD - Pago en Parcialidades o Diferido | L4: G03 - Gastos en general | M4: 86367.6 | N4: 0 | O4: 0 | P4: 86367.6 | Q4: 0 | R4: 0 | S4: 0 | T4: 0 | U4: 0 | V4: 0 | W4: 0 | X4: 0 | Y4: 86367.6 | Z4: 90245.32 | AA4: 1 | AB4: 0 | AC4: 0 | AD4: 90244 | AE4: 0 | AF4: 0 | AG4: 0 | AH4: 0 | AI4: 0 | AJ4: 0 | AK4: 0
B5: Factura | C5: 401-04 ~ Ventas y/o servicios gravados al 0% | D5: 2025-01-02 | E5: 2024-08-14 | F5: F3125 | G5: SEA CARGO LOGISTICS | H5: SCL090414QE0 | I5: 601 - General de Ley Personas Morales | J5: Por definir | K5: PPD - Pago en Parcialidades o Diferido | L5: G03 - Gastos en general | M5: 114192 | N5: 0 | O5: 0 | P5: 114192 | Q5: 0 | R5: 0 | S5: 0 | T5: 0 | U5: 0 | V5: 0 | W5: 0 | X5: 0 | Y5: 114192 | Z5: 123061.8 | AA5: 1 | AB5: 0 | AC5: 0 | AD5: 123060 | AE5: 0 | AF5: 0 | AG5: 0 | AH5: 0 | AI5: 0 | AJ5: 0 | AK5: 0
B6: Factura | C6: 401-01 ~ Ventas y/o servicios gravados a la tasa general | D6: 2025-01-02 | E6: 2024-02-06 | F6: F1487 | G6: PABLO IGNACIO MICHEL ONTIVEROS | H6: MIOP6904169V2 | I6: 612 - Personas Físicas con Actividades Empresariales y Profesionales | J6: Por definir | K6: PPD - Pago en Parcialidades o Diferido | L6: G03 - Gastos en general | M6: 42000 | N6: 42000 | O6: 0 | Q6: 0 | R6: 0 | S6: 0 | T6: 6720 | U6: 0 | V6: 0 | W6: 0 | X6: 0 | Y6: 48720 | Z6: 48720 | AA6: 1 | AB6: 42000 | AC6: 0 | AE6: 0 | AF6: 0 | AG6: 0 | AH6: 6720 | AI6: 0 | AJ6: 0 | AK6: 0
B7: Factura | C7: 401-01 ~ Ventas y/o servicios gravados a la tasa general | D7: 2025-01-02 | E7: 2024-09-19 | F7: F3349 | G7: SEA CARGO LOGISTICS | H7: SCL090414QE0 | I7: 601 - General de Ley Personas Morales | J7: Por definir | K7: PPD - Pago en Parcialidades o Diferido | L7: G03 - Gastos en general | M7: 54815.578 | N7: 13704.617 | O7: 0 | P7: 41110.961 | Q7: 0 | R7: 0 | S7: 0 | T7: 2192.7773 | U7: 0 | V7: 0 | W7: 0 | X7: 0 | Y7: 57008.356 | Z7: 60687.106 | AA7: 1 | AB7: 14588.976 | AC7: 0 | AD7: 43763.213 | AE7: 0 | AF7: 0 | AG7: 0 | AH7: 2334.2772 | AI7: 0 | AJ7: 0 | AK7: 0
B8: Factura | C8: 401-01 ~ Ventas y/o servicios gravados a la tasa general | D8: 2025-01-02 | E8: 2024-10-16 | F8: F3632 | G8: SEA CARGO LOGISTICS | H8: SCL090414QE0 | I8: 601 - General de Ley Personas Morales | J8: Por definir | K8: PPD - Pago en Parcialidades o Diferido | L8: G03 - Gastos en general | M8: 18374.9 | N8: 18374.9 | O8: 0 | Q8: 0 | R8: 0 | S8: 0 | T8: 2939.984 | U8: 0 | V8: 0 | W8: 0 | X8: 0 | Y8: 21314.884 | Z8: 22602.351 | AA8: 1 | AB8: 19484.785 | AC8: 0 | AE8: 0 | AF8: 0 | AG8: 0 | AH8: 3117.5656 | AI8: 0 | AJ8: 0 | AK8: 0
B9: Factura | C9: 401-01 ~ Ventas y/o servicios gravados a la tasa general | D9: 2025-01-02 | E9: 2024-02-28 | F9: F1652 | G9: PABLO IGNACIO MICHEL ONTIVEROS | H9: MIOP6904169V2 | I9: 612 - Personas Físicas con Actividades Empresariales y Profesionales | J9: Por definir | K9: PPD - Pago en Parcialidades o Diferido | L9: G03 - Gastos en general | M9: 42000 | N9: 42000 | O9: 0 | Q9: 0 | R9: 0 | S9: 0 | T9: 6720 | U9: 0 | V9: 0 | W9: 0 | X9: 0 | Y9: 48720 | Z9: 48720 | AA9: 1 | AB9: 42000 | AC9: 0 | AE9: 0 | AF9: 0 | AG9: 0 | AH9: 6720 | AI9: 0 | AJ9: 0 | AK9: 0
B10: Factura | C10: 401-01 ~ Ventas y/o servicios gravados a la tasa general | D10: 2025-01-02 | E10: 2024-10-08 | F10: F3574 | G10: SEA CARGO LOGISTICS | H10: SCL090414QE0 | I10: 601 - General de Ley Personas Morales | J10: Por definir | K10: PPD - Pago en Parcialidades o Diferido | L10: G03 - Gastos en general | M10: 18252.065 | N10: 18252.065 | O10: 0 | Q10: 0 | R10: 0 | S10: 0 | T10: 2920.3304 | U10: 0 | V10: 0 | W10: 0 | X10: 0 | Y10: 21172.395 | Z10: 22602.351 | AA10: 1 | AB10: 19484.785 | AC10: 0 | AE10: 0 | AF10: 0 | AG10: 0 | AH10: 3117.5656 | AI10: 0 | AJ10: 0 | AK10: 0
B11: Factura | C11: 401-01 ~ Ventas y/o servicios gravados a la tasa general | D11: 2025-01-02 | E11: 2024-09-17 | F11: F3336 | G11: SEA CARGO LOGISTICS | H11: SCL090414QE0 | I11: 601 - General de Ley Personas Morales | J11: Por definir | K11: PPD - Pago en Parcialidades o Diferido | L11: G03 - Gastos en general | M11: 124810.38 | N11: 31202.84 | O11: 0 | P11: 93607.541 | Q11: 0 | R11: 0 | S11: 0 | T11: 4992.3761 | U11: 0 | V11: 0 | W11: 0 | X11: 0 | Y11: 129802.76 | Z11: 135909.66 | AA11: 1 | AB11: 32670.857 | AC11: 0 | AD11: 98010.111 | AE11: 0 | AF11: 0 | AG11: 0 | AH11: 5227.2551 | AI11: 0 | AJ11: 0 | AK11: 0
B12: Factura | C12: 401-01 ~ Ventas y/o servicios gravados a la tasa general | D12: 2025-01-02 | E12: 2024-11-13 | F12: F3838 | G12: SEA CARGO LOGISTICS | H12: SCL090414QE0 | I12: 601 - General de Ley Personas Morales | J12: Por definir | K12: PPD - Pago en Parcialidades o Diferido | L12: G03 - Gastos en general | M12: 19427.69 | N12: 19427.69 | O12: 0 | Q12: 0 | R12: 0 | S12: 0 | T12: 3108.4304 | U12: 0 | V12: 0 | W12: 0 | X12: 0 | Y12: 22536.12 | Z12: 22602.351 | AA12: 1 | AB12: 19484.785 | AC12: 0 | AE12: 0 | AF12: 0 | AG12: 0 | AH12: 3117.5656 | AI12: 0 | AJ12: 0 | AK12: 0
B13: Factura | C13: 401-04 ~ Ventas y/o servicios gravados al 0% | D13: 2025-01-02 | E13: 2024-07-25 | F13: F2914 | G13: SEA CARGO LOGISTICS | H13: SCL090414QE0 | I13: 601 - General de Ley Personas Morales | J13: Por definir | K13: PPD - Pago en Parcialidades o Diferido | L13: G03 - Gastos en general | M13: 105786.9 | N13: 0 | O13: 0 | P13: 105786.9 | Q13: 0 | R13: 0 | S13: 0 | T13: 0 | U13: 0 | V13: 0 | W13: 0 | X13: 0 | Y13: 105786.9 | Z13: 119882.7 | AA13: 1 | AB13: 0 | AC13: 0 | AD13: 119880.95 | AE13: 0 | AF13: 0 | AG13: 0 | AH13: 0 | AI13: 0 | AJ13: 0 | AK13: 0
B14: Factura | C14: 401-01 ~ Ventas y/o servicios gravados a la tasa general | D14: 2025-01-02 | E14: 2024-09-26 | F14: F3484 | G14: SEA CARGO LOGISTICS | H14: SCL090414QE0 | I14: 601 - General de Ley Personas Morales | J14: Por definir | K14: PPD - Pago en Parcialidades o Diferido | L14: G03 - Gastos en general | M14: 18388.39 | N14: 18388.39 | O14: 0 | Q14: 0 | R14: 0 | S14: 0 | T14: 2942.1424 | U14: 0 | V14: 0 | W14: 0 | X14: 0 | Y14: 21330.532 | Z14: 22602.351 | AA14: 1 | AB14: 19484.785 | AC14: 0 | AE14: 0 | AF14: 0 | AG14: 0 | AH14: 3117.5656 | AI14: 0 | AJ14: 0 | AK14: 0
B15: Factura | C15: 401-04 ~ Ventas y/o servicios gravados al 0% | D15: 2025-01-02 | E15: 2024-09-05 | F15: F3254 | G15: SEA CARGO LOGISTICS | H15: SCL090414QE0 | I15: 601 - General de Ley Personas Morales | J15: Por definir | K15: PPD - Pago en Parcialidades o Diferido | L15: G03 - Gastos en general | M15: 93217.45 | N15: 0 | O15: 0 | P15: 93217.45 | Q15: 0 | R15: 0 | S15: 0 | T15: 0 | U15: 0 | V15: 0 | W15: 0 | X15: 0 | Y15: 93217.45 | Z15: 96398.41 | AA15: 1 | AB15: 0 | AC15: 0 | AD15: 96397 | AE15: 0 | AF15: 0 | AG15: 0 | AH15: 0 | AI15: 0 | AJ15: 0 | AK15: 0
B16: Factura | C16: 401-04 ~ Ventas y/o servicios gravados al 0% | D16: 2025-01-02 | E16: 2024-10-11 | F16: F3612 | G16: SEA CARGO LOGISTICS | H16: SCL090414QE0 | I16: 601 - General de Ley Personas Morales | J16: Por definir | K16: PPD - Pago en Parcialidades o Diferido | L16: G03 - Gastos en general | M16: 49405.693 | N16: 0 | O16: 0 | P16: 49405.693 | Q16: 0 | R16: 0 | S16: 0 | T16: 0 | U16: 0 | V16: 0 | W16: 0 | X16: 0 | Y16: 49405.693 | Z16: 52186.202 | AA16: 1 | AB16: 0 | AC16: 0 | AD16: 52185.439 | AE16: 0 | AF16: 0 | AG16: 0 | AH16: 0 | AI16: 0 | AJ16: 0 | AK16: 0
B17: Factura | C17: 401-04 ~ Ventas y/o servicios gravados al 0% | D17: 2025-01-02 | E17: 2024-09-26 | F17: F3485 | G17: SEA CARGO LOGISTICS | H17: SCL090414QE0 | I17: 601 - General de Ley Personas Morales | J17: Por definir | K17: PPD - Pago en Parcialidades o Diferido | L17: G03 - Gastos en general | M17: 85167.28 | N17: 0 | O17: 0 | P17: 85167.28 | Q17: 0 | R17: 0 | S17: 0 | T17: 0 | U17: 0 | V17: 0 | W17: 0 | X17: 0 | Y17: 85167.28 | Z17: 90245.32 | AA17: 1 | AB17: 0 | AC17: 0 | AD17: 90244 | AE17: 0 | AF17: 0 | AG17: 0 | AH17: 0 | AI17: 0 | AJ17: 0 | AK17: 0
B18: Factura | C18: 401-04 ~ Ventas y/o servicios gravados al 0% | D18: 2025-01-02 | E18: 2024-07-30 | F18: F2975 | G18: SEA CARGO LOGISTICS | H18: SCL090414QE0 | I18: 601 - General de Ley Personas Morales | J18: Por definir | K18: PPD - Pago en Parcialidades o Diferido | L18: G03 - Gastos en general | M18: 112529.75 | N18: 0 | O18: 0 | P18: 112529.75 | Q18: 0 | R18: 0 | S18: 0 | T18: 0 | U18: 0 | V18: 0 | W18: 0 | X18: 0 | Y18: 112529.75 | Z18: 125112.83 | AA18: 1 | AB18: 0 | AC18: 0 | AD18: 125111 | AE18: 0 | AF18: 0 | AG18: 0 | AH18: 0 | AI18: 0 | AJ18: 0 | AK18: 0
B19: Factura | C19: 401-04 ~ Ventas y/o servicios gravados al 0% | D19: 2025-01-02 | E19: 2024-09-30 | F19: F3500 | G19: SEA CARGO LOGISTICS | H19: SCL090414QE0 | I19: 601 - General de Ley Personas Morales | J19: Por definir | K19: PPD - Pago en Parcialidades o Diferido | L19: G03 - Gastos en general | M19: 94219.2 | N19: 0 | O19: 0 | P19: 94219.2 | Q19: 0 | R19: 0 | S19: 0 | T19: 0 | U19: 0 | V19: 0 | W19: 0 | X19: 0 | Y19: 94219.2 | Z19: 98449.44 | AA19: 1 | AB19: 0 | AC19: 0 | AD19: 98448 | AE19: 0 | AF19: 0 | AG19: 0 | AH19: 0 | AI19: 0 | AJ19: 0 | AK19: 0
B20: Factura | C20: 401-01 ~ Ventas y/o servicios gravados a la tasa general | D20: 2025-01-02 | E20: 2024-02-06 | F20: F1488 | G20: PABLO IGNACIO MICHEL ONTIVEROS | H20: MIOP6904169V2 | I20: 612 - Personas Físicas con Actividades Empresariales y Profesionales | J20: Por definir | K20: PPD - Pago en Parcialidades o Diferido | L20: G03 - Gastos en general | M20: 42000 | N20: 42000 | O20: 0 | Q20: 0 | R20: 0 | S20: 0 | T20: 6720 | U20: 0 | V20: 0 | W20: 0 | X20: 0 | Y20: 48720 | Z20: 48720 | AA20: 1 | AB20: 42000 | AC20: 0 | AE20: 0 | AF20: 0 | AG20: 0 | AH20: 6720 | AI20: 0 | AJ20: 0 | AK20: 0
B21: Concepto Contable | C21: 899-04 ~ Traspaso Bancario | D21: 2025-01-03 | E21: Sin fecha | F21: 0030125 030125 | G21: Sin nombre | H21: Sin nombre | M21: 1621620 | N21: 0 | O21: 0 | P21: 0 | Q21: 0 | R21: 0 | S21: 1621620 | T21: 0 | U21: 0 | V21: 0 | W21: 0 | X21: 0 | Y21: 1621620 | Z21: 1621620 | AA21: 1 | AB21: 0 | AC21: 0 | AD21: 0 | AE21: 0 | AF21: 0 | AG21: 0 | AH21: 0 | AI21: 0 | AJ21: 0 | AK21: 0
B22: Concepto Contable | C22: 899-04 ~ Traspaso Bancario | D22: 2025-01-03 | E22: Sin fecha | F22: CUENTA CANCELADA | G22: Sin nombre | H22: Sin nombre | M22: 49527.59 | N22: 0 | O22: 0 | P22: 0 | Q22: 0 | R22: 0 | S22: 49527.59 | T22: 0 | U22: 0 | V22: 0 | W22: 0 | X22: 0 | Y22: 49527.59 | Z22: 49527.59 | AA22: 1 | AB22: 0 | AC22: 0 | AD22: 0 | AE22: 0 | AF22: 0 | AG22: 0 | AH22: 0 | AI22: 0 | AJ22: 0 | AK22: 0
B23: Factura | C23: 401-01 ~ Ventas y/o servicios gravados a la tasa general | D23: 2025-01-07 | E23: 2024-09-17 | F23: F3335 | G23: SEA CARGO LOGISTICS | H23: SCL090414QE0 | I23: 601 - General de Ley Personas Morales | J23: Por definir | K23: PPD - Pago en Parcialidades o Diferido | L23: G03 - Gastos en general | M23: 58616.638 | N23: 14653.719 | O23: 0 | P23: 43962.919 | Q23: 0 | R23: 0 | S23: 0 | T23: 2344.5715 | U23: 0 | V23: 0 | W23: 0 | X23: 0 | Y23: 60961.21 | Z23: 64328.77 | AA23: 1 | AB23: 15463.205 | AC23: 0 | AD23: 46391.476 | AE23: 0 | AF23: 0 | AG23: 0 | AH23: 2474.0881 | AI23: 0 | AJ23: 0 | AK23: 0
B24: Factura | C24: 401-04 ~ Ventas y/o servicios gravados al 0% | D24: 2025-01-07 | E24: 2024-10-25 | F24: F3676 | G24: NOATUM LOGISTICS MEXICO | H24: NLM210414UA5 | I24: 601 - General de Ley Personas Morales | J24: Por definir | K24: PPD - Pago en Parcialidades o Diferido | L24: G03 - Gastos en general | M24: 47841.12 | N24: 0 | O24: 0 | P24: 47841.12 | Q24: 0 | R24: 0 | S24: 0 | T24: 0 | U24: 0 | V24: 0 | W24: 0 | X24: 0 | Y24: 47841.12 | Z24: 49609.92 | AA24: 1 | AB24: 0 | AC24: 0 | AD24: 49609.92 | AE24: 0 | AF24: 0 | AG24: 0 | AH24: 0 | AI24: 0 | AJ24: 0 | AK24: 0
B25: Factura | C25: 401-04 ~ Ventas y/o servicios gravados al 0% | D25: 2025-01-07 | E25: 2024-09-30 | F25: F3502 | G25: SEA CARGO LOGISTICS | H25: SCL090414QE0 | I25: 601 - General de Ley Personas Morales | J25: Por definir | K25: PPD - Pago en Parcialidades o Diferido | L25: G03 - Gastos en general | M25: 118421.76 | N25: 0 | O25: 0 | P25: 118421.76 | Q25: 0 | R25: 0 | S25: 0 | T25: 0 | U25: 0 | V25: 0 | W25: 0 | X25: 0 | Y25: 118421.76 | Z25: 124706.94 | AA25: 1 | AB25: 0 | AC25: 0 | AD25: 124706.94 | AE25: 0 | AF25: 0 | AG25: 0 | AH25: 0 | AI25: 0 | AJ25: 0 | AK25: 0
B26: Factura | C26: 401-04 ~ Ventas y/o servicios gravados al 0% | D26: 2025-01-07 | E26: 2024-11-22 | F26: F3915 | G26: INGENIERIA Y MAQUINARIA DE GUADALUPE | H26: IMG860612JKA | I26: 601 - General de Ley Personas Morales | J26: Por definir | K26: PPD - Pago en Parcialidades o Diferido | L26: G03 - Gastos en general | M26: 24348.36 | N26: 0 | O26: 0 | P26: 24348.36 | Q26: 0 | R26: 0 | S26: 0 | T26: 0 | U26: 0 | V26: 0 | W26: 0 | X26: 0 | Y26: 24348.36 | Z26: 24804.96 | AA26: 1 | AB26: 0 | AC26: 0 | AD26: 24804.96 | AE26: 0 | AF26: 0 | AG26: 0 | AH26: 0 | AI26: 0 | AJ26: 0 | AK26: 0
B27: Factura | C27: 401-04 ~ Ventas y/o servicios gravados al 0% | D27: 2025-01-07 | E27: 2024-10-11 | F27: F3609 | G27: SEA CARGO LOGISTICS | H27: SCL090414QE0 | I27: 601 - General de Ley Personas Morales | J27: Por definir | K27: PPD - Pago en Parcialidades o Diferido | L27: G03 - Gastos en general | M27: 85437 | N27: 0 | O27: 0 | P27: 85437 | Q27: 0 | R27: 0 | S27: 0 | T27: 0 | U27: 0 | V27: 0 | W27: 0 | X27: 0 | Y27: 85437 | Z27: 90951.52 | AA27: 1 | AB27: 0 | AC27: 0 | AD27: 90951.52 | AE27: 0 | AF27: 0 | AG27: 0 | AH27: 0 | AI27: 0 | AJ27: 0 | AK27: 0
B28: Factura | C28: 401-04 ~ Ventas y/o servicios gravados al 0% | D28: 2025-01-07 | E28: 2024-11-08 | F28: F3800 | G28: NOATUM LOGISTICS MEXICO | H28: NLM210414UA5 | I28: 601 - General de Ley Personas Morales | J28: Por definir | K28: PPD - Pago en Parcialidades o Diferido | L28: G03 - Gastos en general | M28: 63974.295 | N28: 0 | O28: 0 | P28: 63974.295 | Q28: 0 | R28: 0 | S28: 0 | T28: 0 | U28: 0 | V28: 0 | W28: 0 | X28: 0 | Y28: 63974.295 | Z28: 65113.02 | AA28: 1 | AB28: 0 | AC28: 0 | AD28: 65113.02 | AE28: 0 | AF28: 0 | AG28: 0 | AH28: 0 | AI28: 0 | AJ28: 0 | AK28: 0
B29: Factura | C29: 401-01 ~ Ventas y/o servicios gravados a la tasa general | D29: 2025-01-07 | E29: 2024-09-17 | F29: F3337 | G29: SEA CARGO LOGISTICS | H29: SCL090414QE0 | I29: 601 - General de Ley Personas Morales | J29: Por definir | K29: PPD - Pago en Parcialidades o Diferido | L29: G03 - Gastos en general | M29: 124810.58 | N29: 31202.84 | O29: 0 | P29: 93607.737 | Q29: 0 | R29: 0 | S29: 0 | T29: 4992.3761 | U29: 0 | V29: 0 | W29: 0 | X29: 0 | Y29: 129802.95 | Z29: 136973.4 | AA29: 1 | AB29: 32926.517 | AC29: 0 | AD29: 98778.725 | AE29: 0 | AF29: 0 | AG29: 0 | AH29: 5268.1601 | AI29: 0 | AJ29: 0 | AK29: 0
